Workbook

Sheet Relatorio_Validar
A1: numero_ticket | B1: Data_entrada | C1: Assunto_ticket | D1: Título_ticket | E1: Usuario_criador_ticket | F1: Status_ticket | G1: Grupo_responsavel_ticket | H1: Responsavel_ticket | I1: Tags_ticket | J1: Total_interações
A2: 184750 | B2: 45474.209 | D2: [Granatum] Aviso de Agendamentos Pendentes | E2: Granatum | F2: Cancelado | G2: Suporte | H2: Lucas Muniz | I2: - | J2: 2
A3: 184751 | B3: 45474.375 | D3: ✨ Retently Monthly Digest for Octadesk (June 2024) | E3: Retently Digests | F3: Cancelado | G3: Suporte | H3: Lucas Muniz | I3: - | J3: 2
A4: 184752 | B4: 45474.385 | D4: Olá José Ribamar Cosme farias, aqui está nossa conversa! | E4: José Ribamar Cosme farias | F4: Cancelado | G4: Suporte | H4: Lucas Muniz | I4: - | J4: 2
A5: 184753 | B5: 45474.421 | D5: Teste help em beta | E5: William Lima | F5: Cancelado | G5: Suporte | I5: - | J5: 2
A6: 184754 | B6: 45474.442 | D6: Your Datadog Plan Was Converted to Free | E6: Datadog | F6: Cancelado | G6: Suporte | H6: Lucas Muniz | I6: - | J6: 2
A7: 184755 | B7: 45474.447 | D7: [Incidente] não localiza ticket ao pesquisar - cibracoimoveis #184554 #157512 | E7: atendimento | F7: Cancelado | G7: Suporte | H7: Lucas Muniz | I7: - | J7: 2
A8: 184756 | B8: 45474.458 | C8: 3080 Tickets abertos | D8: Menção não funciona em tickets - o180711-06d | E8: Natalia Schuch | F8: Resolvido | G8: N2 | I8: chat, 184728, ticket-corrigido | J8: 6
A9: 184757 | B9: 45474.46 | D9: Announcing Warehouse Connectors 2.0 | E9: Mixpanel | F9: Cancelado | G9: Suporte | H9: Lucas Muniz | I9: - | J9: 2
A10: 184758 | B10: 45474.468 | C10: 3058 Backup | D10: Backup da conta | E10: rennie | F10: Resolvido | G10: N2 | H10: Gabrielle | I10: chat, problema-envio-email | J10: 9
A11: 184759 | B11: 45474.469 | D11: Será VOCÊ o(a) melhor jogador(a) do Brasil? | E11: Poker de Botequim | F11: Cancelado | G11: Suporte | H11: Lucas Muniz | I11: - | J11: 4
A12: 184760 | B12: 45474.469 | C12: 3080 Tickets abertos | D12: Menção nos tickets não está funcionando | E12: Bruno | F12: Resolvido | G12: N2 | I12: chat, ticket-corrigido | J12: 8
A13: 184761 | B13: 45474.475 | C13: 3080 Tickets abertos | D13: Menção nos tickets não está funcionando | E13: Andre Leite Souza | F13: Resolvido | G13: N2 | I13: chat, 184728, ticket-corrigido | J13: 10
A14: 184762 | B14: 45474.488 | C14: 3038 Exportar | D14: Download de relatório de tickets não aparece nas notificações - o179024-820 | E14: Phylipe | F14: Resolvido | G14: N2 | H14: Gabrielle | I14: chat | J14: 8
A15: 184763 | B15: 45474.509 | C15: 3012 Anotação interna | D15: Erro ao realizar menção a agente dentro de ticket | E15: Érica Oliveira | F15: Resolvido | G15: N2 | H15: Gabrielle A. | I15: chat, 184728, ticket-corrigido | J15: 11
A16: 184764 | B16: 45474.512 | D16: Smartband Samsung Galaxy Fit 3 a partir de R$ 277,92*!🔥 | E16: Fujioka Distribuidor | F16: Cancelado | G16: Suporte | H16: Lucas Muniz | I16: - | J16: 2
A17: 184765 | B17: 45474.515 | C17: 3012 Anotação interna | D17: Erro ao realizar menção a agente dentro de ticket | E17: Renato Herrerias Bueno | F17: Resolvido | G17: N2 | I17: chat, Automacao-Encerra-72hrs | J17: 8
A18: 184766 | B18: 45474.516 | C18: Análise da aplicação | Pods em CrashLoopBack | D18: Direcionar alertas de filas para o canal do helpdesk | E18: William Lima | F18: Resolvido | G18: PROD - Infra | I18: monitoramento | J18: 2
A19: 184767 | B19: 45474.523 | C19: 3137 Adicionar Número Web | D19: Retorno conversa ID: 240701775243 | E19: Saulo S. | F19: Resolvido | G19: Suporte | H19: Saulo S. | I19: - | J19: 2
A20: 184768 | B20: 45474.524 | C20: Análise da aplicação | Pods em CrashLoopBack | D20: Direcionar alertas de serviços para o canal do helpdesk | E20: William Lima | F20: Resolvido | G20: PROD - Infra | I20: monitoramento, problema-envio-email | J20: 3
A21: 184769 | B21: 45474.525 | C21: 3058 Backup | D21: Backup - Total de Conversas. | E21: Daniel | F21: Resolvido | G21: N2 | H21: Gabrielle A. | I21: chat, Automacao-Encerra-72hrs | J21: 9
A22: 184770 | B22: 45474.535 | D22: 30% OFF NA VOLTA ÀS AULAS LEGALE! 📚 | E22: Legale Educacional | F22: Cancelado | G22: Suporte | H22: Lucas Muniz | I22: - | J22: 2
A23: 184771 | B23: 45474.541 | D23: Your Daily Digest from Datadog | E23: Datadog | F23: Cancelado | G23: Suporte | H23: Lucas Muniz | I23: - | J23: 2
A24: 184772 | B24: 45474.584 | D24: Aumente a Conscientização com Brindes Personalizados! | E24: Juana | F24: Cancelado | G24: Suporte | H24: Lucas Muniz | I24: - | J24: 2
A25: 184773 | B25: 45474.612 | D25: Convite para se juntar ao Octadesk | E25: octadesk | efetivação de plano | F25: Cancelado | G25: Suporte | H25: Lucas Muniz | I25: - | J25: 2
A26: 184774 | B26: 45474.619 | D26: TICKET CLIENTE - EXEMPLO | E26: Patricia Oliveira | F26: Cancelado | G26: Suporte | H26: Lucas Muniz | I26: - | J26: 3
A27: 184775 | B27: 45474.623 | D27: Alguns clientes não tem os dados alterados no momento da conversa - o179673-362 #184122 | E27: Fernando Pesaro | F27: Resolvido | G27: Suporte | H27: Lucas Muniz | I27: - | J27: 2
A28: 184776 | B28: 45474.635 | D28: Máscara para CPAP e BiPAP 🎁 | E28: Geferson | F28: Cancelado | G28: Suporte | H28: Lucas Muniz | I28: - | J28: 2
A29: 184777 | B29: 45474.639 | C29: 3012 Anotação interna | D29: Erro ao realizar menção a agente dentro de ticket | E29: joao | F29: Resolvido | G29: N2 | I29: chat, 184728, ticket-corrigido | J29: 7
A30: 184778 | B30: 45474.639 | D30: LAB8 EMPRESA DE MARKETING E PUBLICIDADE - NFS-e Nº 816 | E30: LOBBY TECH | F30: Cancelado | G30: Suporte | H30: Lucas Muniz | I30: - | J30: 2
A31: 184779 | B31: 45474.658 | D31: Recuperação de Conta | E31: Beatriz Ahmed | F31: Resolvido | G31: Suporte | H31: Lucas Muniz | I31: automacao-24horas, Automacao-Encerra-72hrs | J31: 8
A32: 184780 | B32: 45474.669 | C32: 3080 Tickets abertos | D32: Chat com Pedro Lopes iniciada às 01/07/2024 15:27 | E32: Pedro Lopes | F32: Resolvido | G32: N2 | I32: chat, ticket-corrigido | J32: 6
A33: 184781 | B33: 45474.677 | C33: 3080 Tickets abertos | D33: Menção nos tickets não está funcionando | E33: joao.rodrigues | F33: Resolvido | G33: N2 | I33: chat, 184728, ticket-corrigido | J33: 9
A34: 184782 | B34: 45474.689 | C34: 3080 Tickets abertos | D34: Menção nos tickets não está funcionando | E34: Octo O. Amarelo | F34: Resolvido | G34: Suporte | I34: chat, 184728, ticket-corrigido, problema-envio-email | J34: 9
A35: 184783 | B35: 45474.697 | C35: 3011 Notificação | D35: Lembrete não gerou notificação na barra de notificações | E35: Daniel | F35: Resolvido | G35: N2 | H35: Juan C. | I35: chat, 184971, ticket-corrigido | J35: 14
A36: 184784 | B36: 45474.7 | D36: Resposta automática: Erro Octadesk - Cliente não encontrada #184007 | E36: Andressa Favacho | F36: Cancelado | G36: Suporte | I36: - | J36: 2
A37: 184785 | B37: 45474.703 | D37: Migração Número WhatsApp | E37: Patricia | F37: Cancelado | G37: Suporte | I37: - | J37: 2
A38: 184786 | B38: 45474.705 | D38: Erro de Mensagens | E38: Patricia | F38: Resolvido | G38: Suporte | H38: Lucas Muniz | I38: - | J38: 3
A39: 184787 | B39: 45474.708 | C39: 3028 Restringir | D39: Pré-visualização de conversas restritas para agentes que não deveriam ter acesso | E39: Jessica Wettermann | F39: Resolvido | G39: N2 | H39: Juan C. | I39: chat, 185628, ticket-corrigido | J39: 35
A40: 184788 | B40: 45474.713 | C40: 3058 Backup | D40: PROD - Infra - Backup da collection planoeplano_ticketarchived e informações sobre tamanho de uso de armazenamento - planoeplano | E40: Juan C. | F40: Resolvido | G40: PROD - Infra | I40: 184421, problema-envio-email | J40: 4
A41: 184789 | B41: 45474.731 | C41: Dúvidas sobre o Contrato | D41: Informações sobre o contrato | E41: Thaís | F41: Resolvido | G41: Suporte | I41: chat, problema-envio-email, automacao-24horas, Automacao-Encerra-72hrs | J41: 4
A42: 184790 | B42: 45474.731 | C42: 3052 Salvar respostas | D42: Widget - Chatbot cria e-mail genérico e cria novo contato | E42: Neuton Júnior | F42: Resolvido | G42: N2 | H42: William Kagiyama | I42: chat, 184013, ticket-corrigido | J42: 10
A43: 184791 | B43: 45474.733 | D43: Chat com Marcos iniciada às 01/07/2024 16:30 | E43: Marcos | F43: Cancelado | G43: Suporte | I43: chat | J43: 10
A44: 184792 | B44: 45474.735 | D44: Vídeo para análise - Ticket 184688 | E44: suporte02 | F44: Cancelado | G44: Suporte | H44: Lucas Muniz | I44: - | J44: 2
A45: 184793 | B45: 45474.748 | D45: Olá Marcus, aqui está nossa conversa! #8901 | E45: Bruno Torraque | F45: Cancelado | G45: Suporte | H45: Lucas Muniz | I45: - | J45: 2
A46: 184794 | B46: 45474.754 | D46: 💓 Queremos ouvir você! | E46: Especialistas AE Patrimônio | F46: Cancelado | G46: Financeiro | I46: - | J46: 2
A47: 184795 | B47: 45474.756 | D47: Dmarc aggregate report | E47: forcepointadmin | F47: Cancelado | G47: Suporte | H47: Lucas Muniz | I47: - | J47: 2
A48: 184796 | B48: 45474.759 | C48: Usuários | D48: Usuário inexistente aparecendo no momento de distribuir conversas e no filtro de contatos | E48: Danilo | F48: Resolvido | G48: N2 | I48: chat, Automacao-Encerra-72hrs | J48: 8
A49: 184797 | B49: 45474.76 | D49: Resposta automática: [Problema] API Tickets Count não está exibindo quantidade corretas de tickets - nita #181163 | E49: Jhonatan da Silva | F49: Cancelado | G49: Suporte | H49: Lucas Muniz | I49: - | J49: 2
A50: 184798 | B50: 45474.765 | C50: 3052 Salvar respostas | D50: Etapa do whatsBOT com erro de gravação de e-mail | E50: Aline S. | F50: Em andamento | G50: N2 | I50: 184992, fup-cliente | J50: 23
A51: 184799 | B51: 45474.85 | D51: Your Stitch Payment Was Successfully Processed (Stitch, Inc.) | E51: Talend Inc. Finance Department | F51: Cancelado | G51: Suporte | H51: Lucas Muniz | I51: - | J51: 2
A52: 184800 | B52: 45474.929 | D52: Your Google Cloud Platform & APIs documents are ready | E52: Google Payments | F52: Cancelado | G52: Suporte | H52: Lucas Muniz | I52: - | J52: 2
A53: 184801 | B53: 45474.982 | D53: Google: Your June 2024 statement of account for OCTADESK LTDA | E53: Google Payments | F53: Cancelado | G53: Suporte | H53: Lucas Muniz | I53: - | J53: 2
A54: 184802 | B54: 45475.169 | D54: Google Cloud Platform & APIs: We've received your payment for 013FDC-241F5D-FFDCF3 | E54: Google Payments | F54: Cancelado | G54: Suporte | H54: Lucas Muniz | I54: - | J54: 2
A55: 184803 | B55: 45475.169 | D55: Google: We've received your payment for 6812485484 | E55: Google Payments | F55: Cancelado | G55: Suporte | H55: Lucas Muniz | I55: - | J55: 2
A56: 184804 | B56: 45475.187 | D56: [Granatum] Aviso de Agendamentos Pendentes | E56: Granatum | F56: Cancelado | G56: Suporte | H56: Lucas Muniz | I56: - | J56: 2
A57: 184805 | B57: 45475.282 | D57: Este é o seu cartão de embarque! Vamos viajar? | E57: Uber | F57: Cancelado | G57: Suporte | H57: Lucas Muniz | I57: - | J57: 2
A58: 184806 | B58: 45475.293 | D58: Claranet - Relação de títulos a vencer - R$ 260,48 | E58: Comunicados Claranet | F58: Cancelado | G58: Suporte | H58: Lucas Muniz | I58: - | J58: 2
A59: 184807 | B59: 45475.381 | C59: 7002 - Migração de Plano | D59: Migração de plano do cliente não sobe- Subdominio: o137341-1e6 | E59: Mariana C. | F59: Resolvido | G59: PROD - Backoffice | H59: Gabriel Alves | I59: - | J59: 8
A60: 184808 | B60: 45475.382 | C60: 3058 Backup | D60: Backup de conversas - vendperto1 | E60: Fernanda | F60: Resolvido | G60: N2 | H60: Gabrielle A. | I60: chat, backup, Automacao-Encerra-72hrs | J60: 10
A61: 184809 | B61: 45475.407 | D61: As festas continuam! 🌽 | E61: CartuchoNet | F61: Cancelado | G61: Suporte | H61: Lucas Muniz | I61: - | J61: 2
A62: 184810 | B62: 45475.412 | D62: NF boleto Octadesk chegou! | E62: Ana Paula - Compras | Carmen Steffens | F62: Cancelado | G62: Suporte | H62: Lucas Muniz | I62: - | J62: 2
A63: 184811 | B63: 45475.418 | D63: Seu boletim econômico chegou! | E63: Serasa Experian | F63: Cancelado | G63: Suporte | H63: Lucas Muniz | I63: - | J63: 2
A64: 184812 | B64: 45475.419 | D64: Como Foi Sua Experiência com a Drika? | E64: Juana | F64: Cancelado | G64: Suporte | H64: Lucas Muniz | I64: - | J64: 2
A65: 184813 | B65: 45475.42 | C65: 6013 - Outros | D65: PROD Backoffice - Acesso bloqueado antes do 11ª dia em atraso - o184068-7a6 | E65: Will | F65: Cancelado | G65: PROD - Backoffice | H65: Gabriel Alves 1 | I65: 184701 | J65: 8
A66: 184814 | B66: 45475.44 | C66: 3058 Backup | D66: Backup de conversas e tickets - o147360-9cf | E66: Shannon Lee Lobato | F66: Resolvido | G66: N2 | H66: Gabrielle A. | I66: chat | J66: 9
A67: 184815 | B67: 45475.445 | C67: 3058 Backup | D67: Solicita backup de conversas de todo o período | E67: Eduarda Silva | F67: Resolvido | G67: N2 | H67: Gabrielle A. | I67: chat, problema-envio-email | J67: 10
A68: 184816 | B68: 45475.46 | D68: Seu boleto Octadesk chegou! | E68: Jonecleia Castor | F68: Resolvido | G68: Financeiro | I68: problema-envio-email | J68: 3
A69: 184817 | B69: 45475.47 | C69: Solicitação de Configuração | D69: Conectar chat commerce | E69: Rafael | F69: Resolvido | G69: N2 | I69: chat, 184892, ticket-corrigido | J69: 6
A70: 184818 | B70: 45475.472 | C70: 3035 Lentidão | D70: Post-Mortem - Lentidão no recebimento de mensagens do WhatsApp | E70: Cristiane | F70: Resolvido | G70: PROD - Chat-Mobile-Widget | I70: problema-envio-email | J70: 13
A71: 184819 | B71: 45475.475 | C71: 3035 Lentidão | D71: Post-Mortem - Lentidão no recebimento de mensagens do WhatsApp | E71: Cristiane | F71: Resolvido | G71: PROD - Meta-Commerce | H71: Fabricio Rocha | I71: problema-envio-email | J71: 7
A72: 184820 | B72: 45475.477 | C72: 3035 Lentidão | D72: Post-Mortem - Lentidão no recebimento de mensagens do WhatsApp | E72: Cristiane | F72: Cancelado | G72: PROD - Meta-Commerce | H72: Fabricio Rocha | I72: problema-envio-email | J72: 11
A73: 184821 | B73: 45475.478 | D73: What’s changed in private capital fundraising in 2024? | E73: Intralinks | F73: Cancelado | G73: Suporte | H73: Lucas Muniz | I73: - | J73: 2
A74: 184822 | B74: 45475.481 | C74: 3056 Valide uma informação | D74: [Incidente] valide informação bot v2 - o180409-0a6 | E74: Larissa | F74: Resolvido | G74: N2 | H74: Will | I74: chat, Automacao-Encerra-72hrs | J74: 7
A75: 184823 | B75: 45475.501 | C75: Erro na Migração de Número | D75: Migração sem sucesso | E75: vanessa | F75: Resolvido | G75: N2 | H75: Will | I75: chat | J75: 14
A76: 184824 | B76: 45475.567 | D76: [Elasticsearch Service] We received your payment (#38676872170095) | E76: Elastic Cloud | F76: Cancelado | G76: Suporte | H76: Lucas Muniz | I76: - | J76: 2
A77: 184825 | B77: 45475.571 | C77: 3007 Adicionar | D77: PROD Backoffice - Nucleus retorna 500 em GET no endpoint 'summary?progress=true', impedindo adição de usuários - vários ambientes | E77: Will | F77: Resolvido | G77: PROD - Backoffice | I77: 184828 | J77: 13
A78: 184826 | B78: 45475.575 | C78: Alterar status | D78: Alterar nome de exibição - o158860-b4b | E78: Leonardo VIeira | F78: Resolvido | G78: N2 | H78: Will | I78: chat, Automacao-Encerra-72hrs | J78: 12
A79: 184827 | B79: 45475.583 | D79: favor verificar - Empresa Maria Dolores | E79: Susan - Suprimentos | F79: Resolvido | G79: Financeiro | I79: - | J79: 11
A80: 184828 | B80: 45475.61 | C80: 3007 Adicionar | D80: PROD Backoffice - Contagem de usuários zerada e impossibilidade de adicionar usuários - frogpay | E80: Will | F80: Cancelado | G80: PROD - Backoffice | H80: Gabriel Alves | I80: 184825 | J80: 5
A81: 184829 | B81: 45475.637 | D81: HUB CNA | Banco BV | Open Dexco | Oxygea Labs | E81: Innoscience Consultoria | F81: Cancelado | G81: Suporte | I81: - | J81: 2
A82: 184830 | B82: 45475.644 | C82: 3058 Backup | D82: Backup de conversas | E82: Laura coronel | F82: Resolvido | G82: N2 | H82: Will | I82: chat | J82: 7
A83: 184831 | B83: 45475.653 | D83: Veja como transformar dados em resultados | E83: Serasa Experian | F83: Cancelado | G83: Suporte | H83: Lucas Muniz | I83: - | J83: 2
A84: 184832 | B84: 45475.657 | C84: Nome | D84: PROD - Chat-Mobile-Widget - Canal Messenger não aparece no filtro de conversas - o188488-923 | E84: Juan C. | F84: Resolvido | G84: PROD - Chat-Mobile-Widget | H84: Camila Rizato | I84: 184704 | J84: 6
A85: 184833 | B85: 45475.67 | D85: Chegou! 🙌 Tudo sobre a Economia das PMEs 🤩 | E85: Serasa Experian | F85: Cancelado | G85: Suporte | H85: Lucas Muniz | I85: - | J85: 2
A86: 184834 | B86: 45475.673 | D86: Your Daily Digest from Datadog | E86: Datadog | F86: Cancelado | G86: Suporte | H86: Lucas Muniz | I86: - | J86: 2
A87: 184835 | B87: 45475.692 | D87: Reclame Aqui (Obvio Brasil) - RPS da Nota Fiscal 295140 OCTADESK DESENVOLVIMENTO DE SOFTWARE LTDA. | E87: OBVIO BRASIL SOFTWARE E SERVIÇOS LTDA. | F87: Cancelado | G87: Suporte | H87: Lucas Muniz | I87: - | J87: 2
A88: 184836 | B88: 45475.692 | D88: Reclame Aqui (Obvio Brasil) - RPS da Nota Fiscal 295140 OCTADESK DESENVOLVIMENTO DE SOFTWARE LTDA. | E88: OBVIO BRASIL SOFTWARE E SERVIÇOS LTDA. | F88: Cancelado | G88: Suporte | H88: Lucas Muniz | I88: - | J88: 2
A89: 184837 | B89: 45475.692 | D89: Reclame Aqui (Obvio Brasil) - RPS da Nota Fiscal 295542 OCTADESK DESENVOLVIMENTO DE SOFTWARE LTDA. | E89: OBVIO BRASIL SOFTWARE E SERVIÇOS LTDA. | F89: Cancelado | G89: Suporte | H89: Lucas Muniz | I89: - | J89: 2
A90: 184838 | B90: 45475.692 | D90: Reclame Aqui (Obvio Brasil) - RPS da Nota Fiscal 295542 OCTADESK DESENVOLVIMENTO DE SOFTWARE LTDA. | E90: OBVIO BRASIL SOFTWARE E SERVIÇOS LTDA. | F90: Cancelado | G90: Suporte | H90: Lucas Muniz | I90: - | J90: 2
A91: 184839 | B91: 45475.708 | D91: Recall: Usuário tentando redefinir a senha no Octadesk | E91: Vanessa Candido(ACBZ) | F91: Resolvido | G91: N2 | I91: automacao-24horas, Automacao-Encerra-72hrs | J91: 6
A92: 184840 | B92: 45475.708 | D92: Recall: Usuário tentando redefinir a senha no Octadesk | E92: Vanessa Candido(ACBZ) | F92: Cancelado | G92: Suporte | H92: Lucas Muniz | I92: - | J92: 2
A93: 184841 | B93: 45475.71 | D93: Seu boleto Octadesk chegou! | E93: Sap Maquina Solo | F93: Resolvido | G93: Financeiro | I93: - | J93: 2
A94: 184842 | B94: 45475.74 | C94: Transcrição de áudio | D94: Woz não está transcrevendo | E94: Thiago Souza | F94: Resolvido | G94: N2 | H94: Juan C. | I94: chat, ticket-corrigido | J94: 9
A95: 184843 | B95: 45475.743 | D95: A/C Departamento de T.I - O que você está fazendo com seus descartes eletrônicos? | E95: Elisabete Castro | F95: Cancelado | G95: Suporte | I95: - | J95: 2
A96: 184844 | B96: 45475.744 | C96: 3058 Backup | D96: Backup - Total de Conversas. | E96: Aline | F96: Resolvido | G96: N2 | H96: Will | I96: chat | J96: 6
A97: 184845 | B97: 45475.863 | D97: Você foldaria essa mão? | E97: Poker de Botequim | F97: Cancelado | G97: Suporte | H97: Lucas Muniz | I97: - | J97: 4
A98: 184846 | B98: 45476.078 | D98: Print your Boleto to make a Google payment | E98: Google Payments | F98: Cancelado | G98: Suporte | H98: Lucas Muniz | I98: - | J98: 2
A99: 184847 | B99: 45476.105 | D99: Stitch Notification - We're encountering some errors with your hsdeals_2 integration | E99: Stitch Notifications | F99: Cancelado | G99: Suporte | H99: Lucas Muniz | I99: - | J99: 2
A100: 184848 | B100: 45476.126 | D100: Print your Boleto to make a Google Cloud Platform & APIs payment | E100: Google Payments | F100: Cancelado | G100: Suporte | H100: Lucas Muniz | I100: - | J100: 2
...

Sheet Base
A1: ticket | B1: data_entrada
A2: 184750 | B2: 45474.209
A3: 184751 | B3: 45474.375
A4: 184752 | B4: 45474.385
A5: 184753 | B5: 45474.421
A6: 184754 | B6: 45474.442
A7: 184755 | B7: 45474.447
A8: 184756 | B8: 45474.458
A9: 184757 | B9: 45474.46
A10: 184758 | B10: 45474.468
A11: 184759 | B11: 45474.469
A12: 184760 | B12: 45474.469
A13: 184761 | B13: 45474.475
... A8262: 193280 | B8262: 45781.834

Sheet Relatorio
B1: ticket | C1: Validação | D1: Data_entrada | E1: Data_resolução | F1: Data_resolucao | G1: Titulo_ticket | H1: Usuario_criador_ticket | I1: Status | J1: Grupo_responsavel | K1: Responsavel_ticket | L1: Tags_ticket | M1: Total_de_interacoes
B2: 193140 | C2: =IFERROR(VLOOKUP(Relatorio_[[#This Row],[ticket]],Base!A:A,1,0),"-") -> 193140 | D2: 45777.335 | E2: 45777.466 | F2: =IF(Relatorio_[[#This Row],[Data_resolução]]=0,"",Relatorio_[[#This Row],[Data_resolução]]) -> 45777.466 | G2: [IMPORTANTE] Conta PJ sem em andamento | H2: Inter Empresas | I2: Cancelado | J2: Financeiro | L2: - | M2: 2 | O2: ="INSERT INTO octadesk.stickets ("&$B$1&","&$D$1&","&$F$1&","&$G$1&","&$H$1&","&$I$1&","&$J$1&","&$K$1&","&$L$1&","&$M$1&") values("&IF(B2="","NULL","'"&B2&"'")&",'"&TEXT(D2,"aaaa-mm-dd hh:mm:ss")&"',"&IF(E2="","NULL","'"&TEXT(E2,"aaaa-mm-dd hh:mm:ss")&"'")&","&IF(G2="","NULL","'"&G2&"'")&","&IF(H2="","NULL","'"&H2&"'")&","&IF(I2="","NULL","'"&I2&"'")&","&IF(J2="","NULL","'"&J2&"'")&","&IF(K2="","NULL","'"&K2&"'")&","&IF(L2="","NULL","'"&L2&"'")&","&IF(M2="","NULL","'"&M2&"'")&");" -> INSERT INTO octadesk.stickets (ticket,Data_entrada,Data_resolucao,Titulo_ticket,Usuario_criador_ticket,Status,Grupo_responsavel,Responsavel_ticket,Tags_ticket,Total_de_interacoes) values('193140','2025-04-30 08:03:03','2025-04-30 11:10:39','[IMPORTANTE] Conta PJ sem em andamento','Inter Empresas','Cancelado','Financeiro',NULL,'-','2');
B3: 193141 | C3: =IFERROR(VLOOKUP(Relatorio_[[#This Row],[ticket]],Base!A:A,1,0),"-") -> 193141 | D3: 45777.378 | E3: 45778.591 | F3: =IF(Relatorio_[[#This Row],[Data_resolução]]=0,"",Relatorio_[[#This Row],[Data_resolução]]) -> 45778.591 | G3: Solicitação de suporte interno | H3: Suporte Octadesk | I3: Resolvido | J3: Suporte | K3: Brenda | L3: suporte-interno | M3: 8 | O3: ="INSERT INTO octadesk.stickets ("&$B$1&","&$D$1&","&$F$1&","&$G$1&","&$H$1&","&$I$1&","&$J$1&","&$K$1&","&$L$1&","&$M$1&") values("&IF(B3="","NULL","'"&B3&"'")&",'"&TEXT(D3,"aaaa-mm-dd hh:mm:ss")&"',"&IF(E3="","NULL","'"&TEXT(E3,"aaaa-mm-dd hh:mm:ss")&"'")&","&IF(G3="","NULL","'"&G3&"'")&","&IF(H3="","NULL","'"&H3&"'")&","&IF(I3="","NULL","'"&I3&"'")&","&IF(J3="","NULL","'"&J3&"'")&","&IF(K3="","NULL","'"&K3&"'")&","&IF(L3="","NULL","'"&L3&"'")&","&IF(M3="","NULL","'"&M3&"'")&");" -> INSERT INTO octadesk.stickets (ticket,Data_entrada,Data_resolucao,Titulo_ticket,Usuario_criador_ticket,Status,Grupo_responsavel,Responsavel_ticket,Tags_ticket,Total_de_interacoes) values('193141','2025-04-30 09:04:14','2025-05-01 14:10:35','Solicitação de suporte interno','Suporte Octadesk','Resolvido','Suporte','Brenda','suporte-interno','8');
B4: 193142 | C4: =IFERROR(VLOOKUP(Relatorio_[[#This Row],[ticket]],Base!A:A,1,0),"-") -> 193142 | D4: 45777.395 | F4: =IF(Relatorio_[[#This Row],[Data_resolução]]=0,"",Relatorio_[[#This Row],[Data_resolução]]) | G4: Troca de titularidade - CONECTA SERVICOS DE TI LTDA | H4: Marcos | I4: Em andamento | J4: Financeiro | L4: - | M4: 2 | O4: ="INSERT INTO octadesk.stickets ("&$B$1&","&$D$1&","&$F$1&","&$G$1&","&$H$1&","&$I$1&","&$J$1&","&$K$1&","&$L$1&","&$M$1&") values("&IF(B4="","NULL","'"&B4&"'")&",'"&TEXT(D4,"aaaa-mm-dd hh:mm:ss")&"',"&IF(E4="","NULL","'"&TEXT(E4,"aaaa-mm-dd hh:mm:ss")&"'")&","&IF(G4="","NULL","'"&G4&"'")&","&IF(H4="","NULL","'"&H4&"'")&","&IF(I4="","NULL","'"&I4&"'")&","&IF(J4="","NULL","'"&J4&"'")&","&IF(K4="","NULL","'"&K4&"'")&","&IF(L4="","NULL","'"&L4&"'")&","&IF(M4="","NULL","'"&M4&"'")&");" -> INSERT INTO octadesk.stickets (ticket,Data_entrada,Data_resolucao,Titulo_ticket,Usuario_criador_ticket,Status,Grupo_responsavel,Responsavel_ticket,Tags_ticket,Total_de_interacoes) values('193142','2025-04-30 09:28:47',NULL,'Troca de titularidade - CONECTA SERVICOS DE TI LTDA','Marcos','Em andamento','Financeiro',NULL,'-','2');
B5: 193143 | C5: =IFERROR(VLOOKUP(Relatorio_[[#This Row],[ticket]],Base!A:A,1,0),"-") -> 193143 | D5: 45777.403 | F5: =IF(Relatorio_[[#This Row],[Data_resolução]]=0,"",Relatorio_[[#This Row],[Data_resolução]]) | G5: Conversas fugiram do fluxo de horário de atendimento | H5: Ailton | I5: Novo | J5: N2 | L5: chat | M5: 6 | O5: ="INSERT INTO octadesk.stickets ("&$B$1&","&$D$1&","&$F$1&","&$G$1&","&$H$1&","&$I$1&","&$J$1&","&$K$1&","&$L$1&","&$M$1&") values("&IF(B5="","NULL","'"&B5&"'")&",'"&TEXT(D5,"aaaa-mm-dd hh:mm:ss")&"',"&IF(E5="","NULL","'"&TEXT(E5,"aaaa-mm-dd hh:mm:ss")&"'")&","&IF(G5="","NULL","'"&G5&"'")&","&IF(H5="","NULL","'"&H5&"'")&","&IF(I5="","NULL","'"&I5&"'")&","&IF(J5="","NULL","'"&J5&"'")&","&IF(K5="","NULL","'"&K5&"'")&","&IF(L5="","NULL","'"&L5&"'")&","&IF(M5="","NULL","'"&M5&"'")&");" -> INSERT INTO octadesk.stickets (ticket,Data_entrada,Data_resolucao,Titulo_ticket,Usuario_criador_ticket,Status,Grupo_responsavel,Responsavel_ticket,Tags_ticket,Total_de_interacoes) values('193143','2025-04-30 09:40:44',NULL,'Conversas fugiram do fluxo de horário de atendimento','Ailton','Novo','N2',NULL,'chat','6');
B6: 193144 | C6: =IFERROR(VLOOKUP(Relatorio_[[#This Row],[ticket]],Base!A:A,1,0),"-") -> 193144 | D6: 45777.413 | F6: =IF(Relatorio_[[#This Row],[Data_resolução]]=0,"",Relatorio_[[#This Row],[Data_resolução]]) | G6: Possibilidade de LOG de exclusão de usuário - runningsolutions | H6: JULIANO MARTINS MENESES | I6: Pendente | J6: N2 | L6: chat, problema-envio-email | M6: 7 | O6: ="INSERT INTO octadesk.stickets ("&$B$1&","&$D$1&","&$F$1&","&$G$1&","&$H$1&","&$I$1&","&$J$1&","&$K$1&","&$L$1&","&$M$1&") values("&IF(B6="","NULL","'"&B6&"'")&",'"&TEXT(D6,"aaaa-mm-dd hh:mm:ss")&"',"&IF(E6="","NULL","'"&TEXT(E6,"aaaa-mm-dd hh:mm:ss")&"'")&","&IF(G6="","NULL","'"&G6&"'")&","&IF(H6="","NULL","'"&H6&"'")&","&IF(I6="","NULL","'"&I6&"'")&","&IF(J6="","NULL","'"&J6&"'")&","&IF(K6="","NULL","'"&K6&"'")&","&IF(L6="","NULL","'"&L6&"'")&","&IF(M6="","NULL","'"&M6&"'")&");" -> INSERT INTO octadesk.stickets (ticket,Data_entrada,Data_resolucao,Titulo_ticket,Usuario_criador_ticket,Status,Grupo_responsavel,Responsavel_ticket,Tags_ticket,Total_de_interacoes) values('193144','2025-04-30 09:54:22',NULL,'Possibilidade de LOG de exclusão de usuário - runningsolutions','JULIANO MARTINS MENESES','Pendente','N2',NULL,'chat, problema-envio-email','7');
B7: 193145 | C7: =IFERROR(VLOOKUP(Relatorio_[[#This Row],[ticket]],Base!A:A,1,0),"-") -> 193145 | D7: 45777.414 | F7: =IF(Relatorio_[[#This Row],[Data_resolução]]=0,"",Relatorio_[[#This Row],[Data_resolução]]) | G7: Solicitação de suporte interno | H7: Suporte Octadesk | I7: Pendente | J7: Suporte | K7: Brenda | L7: suporte-interno, automacao-24horas | M7: 6 | O7: ="INSERT INTO octadesk.stickets ("&$B$1&","&$D$1&","&$F$1&","&$G$1&","&$H$1&","&$I$1&","&$J$1&","&$K$1&","&$L$1&","&$M$1&") values("&IF(B7="","NULL","'"&B7&"'")&",'"&TEXT(D7,"aaaa-mm-dd hh:mm:ss")&"',"&IF(E7="","NULL","'"&TEXT(E7,"aaaa-mm-dd hh:mm:ss")&"'")&","&IF(G7="","NULL","'"&G7&"'")&","&IF(H7="","NULL","'"&H7&"'")&","&IF(I7="","NULL","'"&I7&"'")&","&IF(J7="","NULL","'"&J7&"'")&","&IF(K7="","NULL","'"&K7&"'")&","&IF(L7="","NULL","'"&L7&"'")&","&IF(M7="","NULL","'"&M7&"'")&");" -> INSERT INTO octadesk.stickets (ticket,Data_entrada,Data_resolucao,Titulo_ticket,Usuario_criador_ticket,Status,Grupo_responsavel,Responsavel_ticket,Tags_ticket,Total_de_interacoes) values('193145','2025-04-30 09:56:21',NULL,'Solicitação de suporte interno','Suporte Octadesk','Pendente','Suporte','Brenda','suporte-interno, automacao-24horas','6');
B8: 193146 | C8: =IFERROR(VLOOKUP(Relatorio_[[#This Row],[ticket]],Base!A:A,1,0),"-") -> 193146 | D8: 45777.423 | F8: =IF(Relatorio_[[#This Row],[Data_resolução]]=0,"",Relatorio_[[#This Row],[Data_resolução]]) | G8: Parcelamento Renovação - Dal Comercio Ltda | H8: Silvia S. | I8: Novo | J8: OTC | L8: - | M8: 1 | O8: ="INSERT INTO octadesk.stickets ("&$B$1&","&$D$1&","&$F$1&","&$G$1&","&$H$1&","&$I$1&","&$J$1&","&$K$1&","&$L$1&","&$M$1&") values("&IF(B8="","NULL","'"&B8&"'")&",'"&TEXT(D8,"aaaa-mm-dd hh:mm:ss")&"',"&IF(E8="","NULL","'"&TEXT(E8,"aaaa-mm-dd hh:mm:ss")&"'")&","&IF(G8="","NULL","'"&G8&"'")&","&IF(H8="","NULL","'"&H8&"'")&","&IF(I8="","NULL","'"&I8&"'")&","&IF(J8="","NULL","'"&J8&"'")&","&IF(K8="","NULL","'"&K8&"'")&","&IF(L8="","NULL","'"&L8&"'")&","&IF(M8="","NULL","'"&M8&"'")&");" -> INSERT INTO octadesk.stickets (ticket,Data_entrada,Data_resolucao,Titulo_ticket,Usuario_criador_ticket,Status,Grupo_responsavel,Responsavel_ticket,Tags_ticket,Total_de_interacoes) values('193146','2025-04-30 10:09:28',NULL,'Parcelamento Renovação - Dal Comercio Ltda','Silvia S.','Novo','OTC',NULL,'-','1');
B9: 193147 | C9: =IFERROR(VLOOKUP(Relatorio_[[#This Row],[ticket]],Base!A:A,1,0),"-") -> 193147 | D9: 45777.431 | E9: 45777.485 | F9: =IF(Relatorio_[[#This Row],[Data_resolução]]=0,"",Relatorio_[[#This Row],[Data_resolução]]) -> 45777.485 | G9: OCTADESCK 173521 NF | H9: Naiara Debia | I9: Resolvido | J9: Financeiro | L9: - | M9: 2 | O9: ="INSERT INTO octadesk.stickets ("&$B$1&","&$D$1&","&$F$1&","&$G$1&","&$H$1&","&$I$1&","&$J$1&","&$K$1&","&$L$1&","&$M$1&") values("&IF(B9="","NULL","'"&B9&"'")&",'"&TEXT(D9,"aaaa-mm-dd hh:mm:ss")&"',"&IF(E9="","NULL","'"&TEXT(E9,"aaaa-mm-dd hh:mm:ss")&"'")&","&IF(G9="","NULL","'"&G9&"'")&","&IF(H9="","NULL","'"&H9&"'")&","&IF(I9="","NULL","'"&I9&"'")&","&IF(J9="","NULL","'"&J9&"'")&","&IF(K9="","NULL","'"&K9&"'")&","&IF(L9="","NULL","'"&L9&"'")&","&IF(M9="","NULL","'"&M9&"'")&");" -> INSERT INTO octadesk.stickets (ticket,Data_entrada,Data_resolucao,Titulo_ticket,Usuario_criador_ticket,Status,Grupo_responsavel,Responsavel_ticket,Tags_ticket,Total_de_interacoes) values('193147','2025-04-30 10:20:04','2025-04-30 11:38:11','OCTADESCK 173521 NF','Naiara Debia','Resolvido','Financeiro',NULL,'-','2');
B10: 193148 | C10: =IFERROR(VLOOKUP(Relatorio_[[#This Row],[ticket]],Base!A:A,1,0),"-") -> 193148 | D10: 45777.436 | F10: =IF(Relatorio_[[#This Row],[Data_resolução]]=0,"",Relatorio_[[#This Row],[Data_resolução]]) | G10: Solicitação de suporte interno | H10: Suporte Octadesk | I10: Em andamento | J10: Suporte | K10: Brenda | L10: suporte-interno | M10: 2 | O10: ="INSERT INTO octadesk.stickets ("&$B$1&","&$D$1&","&$F$1&","&$G$1&","&$H$1&","&$I$1&","&$J$1&","&$K$1&","&$L$1&","&$M$1&") values("&IF(B10="","NULL","'"&B10&"'")&",'"&TEXT(D10,"aaaa-mm-dd hh:mm:ss")&"',"&IF(E10="","NULL","'"&TEXT(E10,"aaaa-mm-dd hh:mm:ss")&"'")&","&IF(G10="","NULL","'"&G10&"'")&","&IF(H10="","NULL","'"&H10&"'")&","&IF(I10="","NULL","'"&I10&"'")&","&IF(J10="","NULL","'"&J10&"'")&","&IF(K10="","NULL","'"&K10&"'")&","&IF(L10="","NULL","'"&L10&"'")&","&IF(M10="","NULL","'"&M10&"'")&");" -> INSERT INTO octadesk.stickets (ticket,Data_entrada,Data_resolucao,Titulo_ticket,Usuario_criador_ticket,Status,Grupo_responsavel,Responsavel_ticket,Tags_ticket,Total_de_interacoes) values('193148','2025-04-30 10:28:26',NULL,'Solicitação de suporte interno','Suporte Octadesk','Em andamento','Suporte','Brenda','suporte-interno','2');
B11: 193149 | C11: =IFERROR(VLOOKUP(Relatorio_[[#This Row],[ticket]],Base!A:A,1,0),"-") -> 193149 | D11: 45777.44 | E11: 45777.445 | F11: =IF(Relatorio_[[#This Row],[Data_resolução]]=0,"",Relatorio_[[#This Row],[Data_resolução]]) -> 45777.445 | G11: [Solicitação recebida] | H11: Support | I11: Cancelado | J11: Suporte | K11: Brenda | L11: - | M11: 2 | O11: ="INSERT INTO octadesk.stickets ("&$B$1&","&$D$1&","&$F$1&","&$G$1&","&$H$1&","&$I$1&","&$J$1&","&$K$1&","&$L$1&","&$M$1&") values("&IF(B11="","NULL","'"&B11&"'")&",'"&TEXT(D11,"aaaa-mm-dd hh:mm:ss")&"',"&IF(E11="","NULL","'"&TEXT(E11,"aaaa-mm-dd hh:mm:ss")&"'")&","&IF(G11="","NULL","'"&G11&"'")&","&IF(H11="","NULL","'"&H11&"'")&","&IF(I11="","NULL","'"&I11&"'")&","&IF(J11="","NULL","'"&J11&"'")&","&IF(K11="","NULL","'"&K11&"'")&","&IF(L11="","NULL","'"&L11&"'")&","&IF(M11="","NULL","'"&M11&"'")&");" -> INSERT INTO octadesk.stickets (ticket,Data_entrada,Data_resolucao,Titulo_ticket,Usuario_criador_ticket,Status,Grupo_responsavel,Responsavel_ticket,Tags_ticket,Total_de_interacoes) values('193149','2025-04-30 10:34:15','2025-04-30 10:40:46','[Solicitação recebida]','Support','Cancelado','Suporte','Brenda','-','2');
B12: 193150 | C12: =IFERROR(VLOOKUP(Relatorio_[[#This Row],[ticket]],Base!A:A,1,0),"-") -> 193150 | D12: 45777.441 | E12: 45777.445 | F12: =IF(Relatorio_[[#This Row],[Data_resolução]]=0,"",Relatorio_[[#This Row],[Data_resolução]]) -> 45777.445 | G12: [Solicitação recebida] | H12: Support | I12: Cancelado | J12: Suporte | K12: Brenda | L12: - | M12: 2 | O12: ="INSERT INTO octadesk.stickets ("&$B$1&","&$D$1&","&$F$1&","&$G$1&","&$H$1&","&$I$1&","&$J$1&","&$K$1&","&$L$1&","&$M$1&") values("&IF(B12="","NULL","'"&B12&"'")&",'"&TEXT(D12,"aaaa-mm-dd hh:mm:ss")&"',"&IF(E12="","NULL","'"&TEXT(E12,"aaaa-mm-dd hh:mm:ss")&"'")&","&IF(G12="","NULL","'"&G12&"'")&","&IF(H12="","NULL","'"&H12&"'")&","&IF(I12="","NULL","'"&I12&"'")&","&IF(J12="","NULL","'"&J12&"'")&","&IF(K12="","NULL","'"&K12&"'")&","&IF(L12="","NULL","'"&L12&"'")&","&IF(M12="","NULL","'"&M12&"'")&");" -> INSERT INTO octadesk.stickets (ticket,Data_entrada,Data_resolucao,Titulo_ticket,Usuario_criador_ticket,Status,Grupo_responsavel,Responsavel_ticket,Tags_ticket,Total_de_interacoes) values('193150','2025-04-30 10:34:21','2025-04-30 10:40:46','[Solicitação recebida]','Support','Cancelado','Suporte','Brenda','-','2');
B13: 193151 | C13: =IFERROR(VLOOKUP(Relatorio_[[#This Row],[ticket]],Base!A:A,1,0),"-") -> 193151 | D13: 45777.441 | E13: 45777.445 | F13: =IF(Relatorio_[[#This Row],[Data_resolução]]=0,"",Relatorio_[[#This Row],[Data_resolução]]) -> 45777.445 | G13: [Solicitação recebida] | H13: Support | I13: Cancelado | J13: Suporte | K13: Brenda | L13: - | M13: 2 | O13: ="INSERT INTO octadesk.stickets ("&$B$1&","&$D$1&","&$F$1&","&$G$1&","&$H$1&","&$I$1&","&$J$1&","&$K$1&","&$L$1&","&$M$1&") values("&IF(B13="","NULL","'"&B13&"'")&",'"&TEXT(D13,"aaaa-mm-dd hh:mm:ss")&"',"&IF(E13="","NULL","'"&TEXT(E13,"aaaa-mm-dd hh:mm:ss")&"'")&","&IF(G13="","NULL","'"&G13&"'")&","&IF(H13="","NULL","'"&H13&"'")&","&IF(I13="","NULL","'"&I13&"'")&","&IF(J13="","NULL","'"&J13&"'")&","&IF(K13="","NULL","'"&K13&"'")&","&IF(L13="","NULL","'"&L13&"'")&","&IF(M13="","NULL","'"&M13&"'")&");" -> INSERT INTO octadesk.stickets (ticket,Data_entrada,Data_resolucao,Titulo_ticket,Usuario_criador_ticket,Status,Grupo_responsavel,Responsavel_ticket,Tags_ticket,Total_de_interacoes) values('193151','2025-04-30 10:34:23','2025-04-30 10:40:46','[Solicitação recebida]','Support','Cancelado','Suporte','Brenda','-','2');
B14: 193152 | C14: =IFERROR(VLOOKUP(Relatorio_[[#This Row],[ticket]],Base!A:A,1,0),"-") -> 193152 | D14: 45777.441 | E14: 45777.445 | F14: =IF(Relatorio_[[#This Row],[Data_resolução]]=0,"",Relatorio_[[#This Row],[Data_resolução]]) -> 45777.445 | G14: [Solicitação recebida] | H14: Support | I14: Cancelado | J14: Suporte | K14: Brenda | L14: - | M14: 2 | O14: ="INSERT INTO octadesk.stickets ("&$B$1&","&$D$1&","&$F$1&","&$G$1&","&$H$1&","&$I$1&","&$J$1&","&$K$1&","&$L$1&","&$M$1&") values("&IF(B14="","NULL","'"&B14&"'")&",'"&TEXT(D14,"aaaa-mm-dd hh:mm:ss")&"',"&IF(E14="","NULL","'"&TEXT(E14,"aaaa-mm-dd hh:mm:ss")&"'")&","&IF(G14="","NULL","'"&G14&"'")&","&IF(H14="","NULL","'"&H14&"'")&","&IF(I14="","NULL","'"&I14&"'")&","&IF(J14="","NULL","'"&J14&"'")&","&IF(K14="","NULL","'"&K14&"'")&","&IF(L14="","NULL","'"&L14&"'")&","&IF(M14="","NULL","'"&M14&"'")&");" -> INSERT INTO octadesk.stickets (ticket,Data_entrada,Data_resolucao,Titulo_ticket,Usuario_criador_ticket,Status,Grupo_responsavel,Responsavel_ticket,Tags_ticket,Total_de_interacoes) values('193152','2025-04-30 10:34:27','2025-04-30 10:40:46','[Solicitação recebida]','Support','Cancelado','Suporte','Brenda','-','2');
B15: 193153 | C15: =IFERROR(VLOOKUP(Relatorio_[[#This Row],[ticket]],Base!A:A,1,0),"-") -> 193153 | D15: 45777.441 | E15: 45777.445 | F15: =IF(Relatorio_[[#This Row],[Data_resolução]]=0,"",Relatorio_[[#This Row],[Data_resolução]]) -> 45777.445 | G15: [Solicitação recebida] | H15: Support | I15: Cancelado | J15: Suporte | K15: Brenda | L15: - | M15: 2 | O15: ="INSERT INTO octadesk.stickets ("&$B$1&","&$D$1&","&$F$1&","&$G$1&","&$H$1&","&$I$1&","&$J$1&","&$K$1&","&$L$1&","&$M$1&") values("&IF(B15="","NULL","'"&B15&"'")&",'"&TEXT(D15,"aaaa-mm-dd hh:mm:ss")&"',"&IF(E15="","NULL","'"&TEXT(E15,"aaaa-mm-dd hh:mm:ss")&"'")&","&IF(G15="","NULL","'"&G15&"'")&","&IF(H15="","NULL","'"&H15&"'")&","&IF(I15="","NULL","'"&I15&"'")&","&IF(J15="","NULL","'"&J15&"'")&","&IF(K15="","NULL","'"&K15&"'")&","&IF(L15="","NULL","'"&L15&"'")&","&IF(M15="","NULL","'"&M15&"'")&");" -> INSERT INTO octadesk.stickets (ticket,Data_entrada,Data_resolucao,Titulo_ticket,Usuario_criador_ticket,Status,Grupo_responsavel,Responsavel_ticket,Tags_ticket,Total_de_interacoes) values('193153','2025-04-30 10:34:36','2025-04-30 10:40:46','[Solicitação recebida]','Support','Cancelado','Suporte','Brenda','-','2');
B16: 193154 | C16: =IFERROR(VLOOKUP(Relatorio_[[#This Row],[ticket]],Base!A:A,1,0),"-") -> 193154 | D16: 45777.441 | E16: 45777.445 | F16: =IF(Relatorio_[[#This Row],[Data_resolução]]=0,"",Relatorio_[[#This Row],[Data_resolução]]) -> 45777.445 | G16: [Solicitação recebida] | H16: Support | I16: Cancelado | J16: Suporte | K16: Brenda | L16: - | M16: 2 | O16: ="INSERT INTO octadesk.stickets ("&$B$1&","&$D$1&","&$F$1&","&$G$1&","&$H$1&","&$I$1&","&$J$1&","&$K$1&","&$L$1&","&$M$1&") values("&IF(B16="","NULL","'"&B16&"'")&",'"&TEXT(D16,"aaaa-mm-dd hh:mm:ss")&"',"&IF(E16="","NULL","'"&TEXT(E16,"aaaa-mm-dd hh:mm:ss")&"'")&","&IF(G16="","NULL","'"&G16&"'")&","&IF(H16="","NULL","'"&H16&"'")&","&IF(I16="","NULL","'"&I16&"'")&","&IF(J16="","NULL","'"&J16&"'")&","&IF(K16="","NULL","'"&K16&"'")&","&IF(L16="","NULL","'"&L16&"'")&","&IF(M16="","NULL","'"&M16&"'")&");" -> INSERT INTO octadesk.stickets (ticket,Data_entrada,Data_resolucao,Titulo_ticket,Usuario_criador_ticket,Status,Grupo_responsavel,Responsavel_ticket,Tags_ticket,Total_de_interacoes) values('193154','2025-04-30 10:34:40','2025-04-30 10:40:46','[Solicitação recebida]','Support','Cancelado','Suporte','Brenda','-','2');
B17: 193155 | C17: =IFERROR(VLOOKUP(Relatorio_[[#This Row],[ticket]],Base!A:A,1,0),"-") -> 193155 | D17: 45777.441 | E17: 45777.445 | F17: =IF(Relatorio_[[#This Row],[Data_resolução]]=0,"",Relatorio_[[#This Row],[Data_resolução]]) -> 45777.445 | G17: [Solicitação recebida] | H17: Support | I17: Cancelado | J17: Suporte | K17: Brenda | L17: - | M17: 2 | O17: ="INSERT INTO octadesk.stickets ("&$B$1&","&$D$1&","&$F$1&","&$G$1&","&$H$1&","&$I$1&","&$J$1&","&$K$1&","&$L$1&","&$M$1&") values("&IF(B17="","NULL","'"&B17&"'")&",'"&TEXT(D17,"aaaa-mm-dd hh:mm:ss")&"',"&IF(E17="","NULL","'"&TEXT(E17,"aaaa-mm-dd hh:mm:ss")&"'")&","&IF(G17="","NULL","'"&G17&"'")&","&IF(H17="","NULL","'"&H17&"'")&","&IF(I17="","NULL","'"&I17&"'")&","&IF(J17="","NULL","'"&J17&"'")&","&IF(K17="","NULL","'"&K17&"'")&","&IF(L17="","NULL","'"&L17&"'")&","&IF(M17="","NULL","'"&M17&"'")&");" -> INSERT INTO octadesk.stickets (ticket,Data_entrada,Data_resolucao,Titulo_ticket,Usuario_criador_ticket,Status,Grupo_responsavel,Responsavel_ticket,Tags_ticket,Total_de_interacoes) values('193155','2025-04-30 10:35:12','2025-04-30 10:40:46','[Solicitação recebida]','Support','Cancelado','Suporte','Brenda','-','2');
B18: 193156 | C18: =IFERROR(VLOOKUP(Relatorio_[[#This Row],[ticket]],Base!A:A,1,0),"-") -> 193156 | D18: 45777.441 | E18: 45777.445 | F18: =IF(Relatorio_[[#This Row],[Data_resolução]]=0,"",Relatorio_[[#This Row],[Data_resolução]]) -> 45777.445 | G18: [Solicitação recebida] | H18: Support | I18: Cancelado | J18: Suporte | K18: Brenda | L18: - | M18: 2 | O18: ="INSERT INTO octadesk.stickets ("&$B$1&","&$D$1&","&$F$1&","&$G$1&","&$H$1&","&$I$1&","&$J$1&","&$K$1&","&$L$1&","&$M$1&") values("&IF(B18="","NULL","'"&B18&"'")&",'"&TEXT(D18,"aaaa-mm-dd hh:mm:ss")&"',"&IF(E18="","NULL","'"&TEXT(E18,"aaaa-mm-dd hh:mm:ss")&"'")&","&IF(G18="","NULL","'"&G18&"'")&","&IF(H18="","NULL","'"&H18&"'")&","&IF(I18="","NULL","'"&I18&"'")&","&IF(J18="","NULL","'"&J18&"'")&","&IF(K18="","NULL","'"&K18&"'")&","&IF(L18="","NULL","'"&L18&"'")&","&IF(M18="","NULL","'"&M18&"'")&");" -> INSERT INTO octadesk.stickets (ticket,Data_entrada,Data_resolucao,Titulo_ticket,Usuario_criador_ticket,Status,Grupo_responsavel,Responsavel_ticket,Tags_ticket,Total_de_interacoes) values('193156','2025-04-30 10:35:16','2025-04-30 10:40:46','[Solicitação recebida]','Support','Cancelado','Suporte','Brenda','-','2');
B19: 193157 | C19: =IFERROR(VLOOKUP(Relatorio_[[#This Row],[ticket]],Base!A:A,1,0),"-") -> 193157 | D19: 45777.441 | E19: 45777.445 | F19: =IF(Relatorio_[[#This Row],[Data_resolução]]=0,"",Relatorio_[[#This Row],[Data_resolução]]) -> 45777.445 | G19: [Solicitação recebida] | H19: Support | I19: Cancelado | J19: Suporte | K19: Brenda | L19: - | M19: 2 | O19: ="INSERT INTO octadesk.stickets ("&$B$1&","&$D$1&","&$F$1&","&$G$1&","&$H$1&","&$I$1&","&$J$1&","&$K$1&","&$L$1&","&$M$1&") values("&IF(B19="","NULL","'"&B19&"'")&",'"&TEXT(D19,"aaaa-mm-dd hh:mm:ss")&"',"&IF(E19="","NULL","'"&TEXT(E19,"aaaa-mm-dd hh:mm:ss")&"'")&","&IF(G19="","NULL","'"&G19&"'")&","&IF(H19="","NULL","'"&H19&"'")&","&IF(I19="","NULL","'"&I19&"'")&","&IF(J19="","NULL","'"&J19&"'")&","&IF(K19="","NULL","'"&K19&"'")&","&IF(L19="","NULL","'"&L19&"'")&","&IF(M19="","NULL","'"&M19&"'")&");" -> INSERT INTO octadesk.stickets (ticket,Data_entrada,Data_resolucao,Titulo_ticket,Usuario_criador_ticket,Status,Grupo_responsavel,Responsavel_ticket,Tags_ticket,Total_de_interacoes) values('193157','2025-04-30 10:35:25','2025-04-30 10:40:46','[Solicitação recebida]','Support','Cancelado','Suporte','Brenda','-','2');
B20: 193158 | C20: =IFERROR(VLOOKUP(Relatorio_[[#This Row],[ticket]],Base!A:A,1,0),"-") -> 193158 | D20: 45777.444 | E20: 45779.438 | F20: =IF(Relatorio_[[#This Row],[Data_resolução]]=0,"",Relatorio_[[#This Row],[Data_resolução]]) -> 45779.438 | G20: Escalado por CS - o206726-bd7 | H20: Suporte Octadesk | I20: Cancelado | J20: N2 | K20: Juan C. | L20: suporte-interno | M20: 8 | O20: ="INSERT INTO octadesk.stickets ("&$B$1&","&$D$1&","&$F$1&","&$G$1&","&$H$1&","&$I$1&","&$J$1&","&$K$1&","&$L$1&","&$M$1&") values("&IF(B20="","NULL","'"&B20&"'")&",'"&TEXT(D20,"aaaa-mm-dd hh:mm:ss")&"',"&IF(E20="","NULL","'"&TEXT(E20,"aaaa-mm-dd hh:mm:ss")&"'")&","&IF(G20="","NULL","'"&G20&"'")&","&IF(H20="","NULL","'"&H20&"'")&","&IF(I20="","NULL","'"&I20&"'")&","&IF(J20="","NULL","'"&J20&"'")&","&IF(K20="","NULL","'"&K20&"'")&","&IF(L20="","NULL","'"&L20&"'")&","&IF(M20="","NULL","'"&M20&"'")&");" -> INSERT INTO octadesk.stickets (ticket,Data_entrada,Data_resolucao,Titulo_ticket,Usuario_criador_ticket,Status,Grupo_responsavel,Responsavel_ticket,Tags_ticket,Total_de_interacoes) values('193158','2025-04-30 10:38:39','2025-05-02 10:30:56','Escalado por CS - o206726-bd7','Suporte Octadesk','Cancelado','N2','Juan C.','suporte-interno','8');
B21: 193159 | C21: =IFERROR(VLOOKUP(Relatorio_[[#This Row],[ticket]],Base!A:A,1,0),"-") -> 193159 | D21: 45777.444 | F21: =IF(Relatorio_[[#This Row],[Data_resolução]]=0,"",Relatorio_[[#This Row],[Data_resolução]]) | G21: Erro na distribuição de conversas Wpp Web - drogalima | H21: Alberto | I21: Novo | J21: N2 | L21: chat | M21: 3 | O21: ="INSERT INTO octadesk.stickets ("&$B$1&","&$D$1&","&$F$1&","&$G$1&","&$H$1&","&$I$1&","&$J$1&","&$K$1&","&$L$1&","&$M$1&") values("&IF(B21="","NULL","'"&B21&"'")&",'"&TEXT(D21,"aaaa-mm-dd hh:mm:ss")&"',"&IF(E21="","NULL","'"&TEXT(E21,"aaaa-mm-dd hh:mm:ss")&"'")&","&IF(G21="","NULL","'"&G21&"'")&","&IF(H21="","NULL","'"&H21&"'")&","&IF(I21="","NULL","'"&I21&"'")&","&IF(J21="","NULL","'"&J21&"'")&","&IF(K21="","NULL","'"&K21&"'")&","&IF(L21="","NULL","'"&L21&"'")&","&IF(M21="","NULL","'"&M21&"'")&");" -> INSERT INTO octadesk.stickets (ticket,Data_entrada,Data_resolucao,Titulo_ticket,Usuario_criador_ticket,Status,Grupo_responsavel,Responsavel_ticket,Tags_ticket,Total_de_interacoes) values('193159','2025-04-30 10:40:03',NULL,'Erro na distribuição de conversas Wpp Web - drogalima','Alberto','Novo','N2',NULL,'chat','3');
B22: 193160 | C22: =IFERROR(VLOOKUP(Relatorio_[[#This Row],[ticket]],Base!A:A,1,0),"-") -> 193160 | D22: 45777.459 | E22: 45777.643 | F22: =IF(Relatorio_[[#This Row],[Data_resolução]]=0,"",Relatorio_[[#This Row],[Data_resolução]]) -> 45777.643 | G22: ❌ Não tem como vender mais se você prospecta leads ruins | H22: Talita da Speedio | I22: Cancelado | J22: Suporte | K22: Brenda | L22: - | M22: 2 | O22: ="INSERT INTO octadesk.stickets ("&$B$1&","&$D$1&","&$F$1&","&$G$1&","&$H$1&","&$I$1&","&$J$1&","&$K$1&","&$L$1&","&$M$1&") values("&IF(B22="","NULL","'"&B22&"'")&",'"&TEXT(D22,"aaaa-mm-dd hh:mm:ss")&"',"&IF(E22="","NULL","'"&TEXT(E22,"aaaa-mm-dd hh:mm:ss")&"'")&","&IF(G22="","NULL","'"&G22&"'")&","&IF(H22="","NULL","'"&H22&"'")&","&IF(I22="","NULL","'"&I22&"'")&","&IF(J22="","NULL","'"&J22&"'")&","&IF(K22="","NULL","'"&K22&"'")&","&IF(L22="","NULL","'"&L22&"'")&","&IF(M22="","NULL","'"&M22&"'")&");" -> INSERT INTO octadesk.stickets (ticket,Data_entrada,Data_resolucao,Titulo_ticket,Usuario_criador_ticket,Status,Grupo_responsavel,Responsavel_ticket,Tags_ticket,Total_de_interacoes) values('193160','2025-04-30 11:01:16','2025-04-30 15:26:07','❌ Não tem como vender mais se você prospecta leads ruins','Talita da Speedio','Cancelado','Suporte','Brenda','-','2');
B23: 193161 | C23: =IFERROR(VLOOKUP(Relatorio_[[#This Row],[ticket]],Base!A:A,1,0),"-") -> 193161 | D23: 45777.476 | F23: =IF(Relatorio_[[#This Row],[Data_resolução]]=0,"",Relatorio_[[#This Row],[Data_resolução]]) | G23: Não recebe notificação (email) de criação de tickets ou menção | H23: Mailon Dos Santos Sanches | I23: Em andamento | J23: N2 | L23: chat, problema-envio-email | M23: 7 | O23: ="INSERT INTO octadesk.stickets ("&$B$1&","&$D$1&","&$F$1&","&$G$1&","&$H$1&","&$I$1&","&$J$1&","&$K$1&","&$L$1&","&$M$1&") values("&IF(B23="","NULL","'"&B23&"'")&",'"&TEXT(D23,"aaaa-mm-dd hh:mm:ss")&"',"&IF(E23="","NULL","'"&TEXT(E23,"aaaa-mm-dd hh:mm:ss")&"'")&","&IF(G23="","NULL","'"&G23&"'")&","&IF(H23="","NULL","'"&H23&"'")&","&IF(I23="","NULL","'"&I23&"'")&","&IF(J23="","NULL","'"&J23&"'")&","&IF(K23="","NULL","'"&K23&"'")&","&IF(L23="","NULL","'"&L23&"'")&","&IF(M23="","NULL","'"&M23&"'")&");" -> INSERT INTO octadesk.stickets (ticket,Data_entrada,Data_resolucao,Titulo_ticket,Usuario_criador_ticket,Status,Grupo_responsavel,Responsavel_ticket,Tags_ticket,Total_de_interacoes) values('193161','2025-04-30 11:26:09',NULL,'Não recebe notificação (email) de criação de tickets ou menção','Mailon Dos Santos Sanches','Em andamento','N2',NULL,'chat, problema-envio-email','7');
B24: 193162 | C24: =IFERROR(VLOOKUP(Relatorio_[[#This Row],[ticket]],Base!A:A,1,0),"-") -> 193162 | D24: 45777.501 | F24: =IF(Relatorio_[[#This Row],[Data_resolução]]=0,"",Relatorio_[[#This Row],[Data_resolução]]) | G24: SOLICITAÇÃO DE BACKUP - CONVERSAS E CONTATOS | H24: Eduarda | I24: Pendente | J24: Suporte | K24: Brenda | L24: automacao-24horas | M24: 2 | O24: ="INSERT INTO octadesk.stickets ("&$B$1&","&$D$1&","&$F$1&","&$G$1&","&$H$1&","&$I$1&","&$J$1&","&$K$1&","&$L$1&","&$M$1&") values("&IF(B24="","NULL","'"&B24&"'")&",'"&TEXT(D24,"aaaa-mm-dd hh:mm:ss")&"',"&IF(E24="","NULL","'"&TEXT(E24,"aaaa-mm-dd hh:mm:ss")&"'")&","&IF(G24="","NULL","'"&G24&"'")&","&IF(H24="","NULL","'"&H24&"'")&","&IF(I24="","NULL","'"&I24&"'")&","&IF(J24="","NULL","'"&J24&"'")&","&IF(K24="","NULL","'"&K24&"'")&","&IF(L24="","NULL","'"&L24&"'")&","&IF(M24="","NULL","'"&M24&"'")&");" -> INSERT INTO octadesk.stickets (ticket,Data_entrada,Data_resolucao,Titulo_ticket,Usuario_criador_ticket,Status,Grupo_responsavel,Responsavel_ticket,Tags_ticket,Total_de_interacoes) values('193162','2025-04-30 12:01:50',NULL,'SOLICITAÇÃO DE BACKUP - CONVERSAS E CONTATOS','Eduarda','Pendente','Suporte','Brenda','automacao-24horas','2');
B25: 193163 | C25: =IFERROR(VLOOKUP(Relatorio_[[#This Row],[ticket]],Base!A:A,1,0),"-") -> 193163 | D25: 45777.505 | E25: 45779.732 | F25: =IF(Relatorio_[[#This Row],[Data_resolução]]=0,"",Relatorio_[[#This Row],[Data_resolução]]) -> 45779.732 | G25: Não entrou os créditos mensais - o179888-c27 | H25: MARCELA ROCHA | I25: Cancelado | J25: N2 | L25: chat | M25: 13 | O25: ="INSERT INTO octadesk.stickets ("&$B$1&","&$D$1&","&$F$1&","&$G$1&","&$H$1&","&$I$1&","&$J$1&","&$K$1&","&$L$1&","&$M$1&") values("&IF(B25="","NULL","'"&B25&"'")&",'"&TEXT(D25,"aaaa-mm-dd hh:mm:ss")&"',"&IF(E25="","NULL","'"&TEXT(E25,"aaaa-mm-dd hh:mm:ss")&"'")&","&IF(G25="","NULL","'"&G25&"'")&","&IF(H25="","NULL","'"&H25&"'")&","&IF(I25="","NULL","'"&I25&"'")&","&IF(J25="","NULL","'"&J25&"'")&","&IF(K25="","NULL","'"&K25&"'")&","&IF(L25="","NULL","'"&L25&"'")&","&IF(M25="","NULL","'"&M25&"'")&");" -> INSERT INTO octadesk.stickets (ticket,Data_entrada,Data_resolucao,Titulo_ticket,Usuario_criador_ticket,Status,Grupo_responsavel,Responsavel_ticket,Tags_ticket,Total_de_interacoes) values('193163','2025-04-30 12:07:14','2025-05-02 17:34:13','Não entrou os créditos mensais - o179888-c27','MARCELA ROCHA','Cancelado','N2',NULL,'chat','13');
B26: 193164 | C26: =IFERROR(VLOOKUP(Relatorio_[[#This Row],[ticket]],Base!A:A,1,0),"-") -> 193164 | D26: 45777.506 | E26: 45777.516 | F26: =IF(Relatorio_[[#This Row],[Data_resolução]]=0,"",Relatorio_[[#This Row],[Data_resolução]]) -> 45777.516 | G26: Customer, ofertas especiais para sua empresa | H26: Lenovo Brasil | I26: Cancelado | J26: Financeiro | L26: - | M26: 2 | O26: ="INSERT INTO octadesk.stickets ("&$B$1&","&$D$1&","&$F$1&","&$G$1&","&$H$1&","&$I$1&","&$J$1&","&$K$1&","&$L$1&","&$M$1&") values("&IF(B26="","NULL","'"&B26&"'")&",'"&TEXT(D26,"aaaa-mm-dd hh:mm:ss")&"',"&IF(E26="","NULL","'"&TEXT(E26,"aaaa-mm-dd hh:mm:ss")&"'")&","&IF(G26="","NULL","'"&G26&"'")&","&IF(H26="","NULL","'"&H26&"'")&","&IF(I26="","NULL","'"&I26&"'")&","&IF(J26="","NULL","'"&J26&"'")&","&IF(K26="","NULL","'"&K26&"'")&","&IF(L26="","NULL","'"&L26&"'")&","&IF(M26="","NULL","'"&M26&"'")&");" -> INSERT INTO octadesk.stickets (ticket,Data_entrada,Data_resolucao,Titulo_ticket,Usuario_criador_ticket,Status,Grupo_responsavel,Responsavel_ticket,Tags_ticket,Total_de_interacoes) values('193164','2025-04-30 12:08:36','2025-04-30 12:22:43','Customer, ofertas especiais para sua empresa','Lenovo Brasil','Cancelado','Financeiro',NULL,'-','2');
B27: 193165 | C27: =IFERROR(VLOOKUP(Relatorio_[[#This Row],[ticket]],Base!A:A,1,0),"-") -> 193165 | D27: 45777.536 | F27: =IF(Relatorio_[[#This Row],[Data_resolução]]=0,"",Relatorio_[[#This Row],[Data_resolução]]) | G27: PROD - Octa-Conversas - Bug visual na variável em componentes do bot - Vários ambientes | H27: Juan C. | I27: Novo | J27: PROD - Octa-Conversas | K27: Juliana Wilcke | L27: 192862 | M27: 3 | O27: ="INSERT INTO octadesk.stickets ("&$B$1&","&$D$1&","&$F$1&","&$G$1&","&$H$1&","&$I$1&","&$J$1&","&$K$1&","&$L$1&","&$M$1&") values("&IF(B27="","NULL","'"&B27&"'")&",'"&TEXT(D27,"aaaa-mm-dd hh:mm:ss")&"',"&IF(E27="","NULL","'"&TEXT(E27,"aaaa-mm-dd hh:mm:ss")&"'")&","&IF(G27="","NULL","'"&G27&"'")&","&IF(H27="","NULL","'"&H27&"'")&","&IF(I27="","NULL","'"&I27&"'")&","&IF(J27="","NULL","'"&J27&"'")&","&IF(K27="","NULL","'"&K27&"'")&","&IF(L27="","NULL","'"&L27&"'")&","&IF(M27="","NULL","'"&M27&"'")&");" -> INSERT INTO octadesk.stickets (ticket,Data_entrada,Data_resolucao,Titulo_ticket,Usuario_criador_ticket,Status,Grupo_responsavel,Responsavel_ticket,Tags_ticket,Total_de_interacoes) values('193165','2025-04-30 12:51:45',NULL,'PROD - Octa-Conversas - Bug visual na variável em componentes do bot - Vários ambientes','Juan C.','Novo','PROD - Octa-Conversas','Juliana Wilcke','192862','3');
B28: 193166 | C28: =IFERROR(VLOOKUP(Relatorio_[[#This Row],[ticket]],Base!A:A,1,0),"-") -> 193166 | D28: 45777.54 | F28: =IF(Relatorio_[[#This Row],[Data_resolução]]=0,"",Relatorio_[[#This Row],[Data_resolução]]) | G28: Erro atribuir responsável endpoint API - o157076-d18 | H28: Flai Silva Lino | I28: Novo | J28: N2 | L28: - | M28: 3 | O28: ="INSERT INTO octadesk.stickets ("&$B$1&","&$D$1&","&$F$1&","&$G$1&","&$H$1&","&$I$1&","&$J$1&","&$K$1&","&$L$1&","&$M$1&") values("&IF(B28="","NULL","'"&B28&"'")&",'"&TEXT(D28,"aaaa-mm-dd hh:mm:ss")&"',"&IF(E28="","NULL","'"&TEXT(E28,"aaaa-mm-dd hh:mm:ss")&"'")&","&IF(G28="","NULL","'"&G28&"'")&","&IF(H28="","NULL","'"&H28&"'")&","&IF(I28="","NULL","'"&I28&"'")&","&IF(J28="","NULL","'"&J28&"'")&","&IF(K28="","NULL","'"&K28&"'")&","&IF(L28="","NULL","'"&L28&"'")&","&IF(M28="","NULL","'"&M28&"'")&");" -> INSERT INTO octadesk.stickets (ticket,Data_entrada,Data_resolucao,Titulo_ticket,Usuario_criador_ticket,Status,Grupo_responsavel,Responsavel_ticket,Tags_ticket,Total_de_interacoes) values('193166','2025-04-30 12:58:00',NULL,'Erro atribuir responsável endpoint API - o157076-d18','Flai Silva Lino','Novo','N2',NULL,'-','3');
B29: 193167 | C29: =IFERROR(VLOOKUP(Relatorio_[[#This Row],[ticket]],Base!A:A,1,0),"-") -> 193167 | D29: 45777.559 | E29: 45778.597 | F29: =IF(Relatorio_[[#This Row],[Data_resolução]]=0,"",Relatorio_[[#This Row],[Data_resolução]]) -> 45778.597 | G29: Backup do historico de conversas - o148872-a4a | H29: Flávia | I29: Resolvido | J29: N2 | K29: Juan C. | L29: chat, problema-envio-email | M29: 11 | O29: ="INSERT INTO octadesk.stickets ("&$B$1&","&$D$1&","&$F$1&","&$G$1&","&$H$1&","&$I$1&","&$J$1&","&$K$1&","&$L$1&","&$M$1&") values("&IF(B29="","NULL","'"&B29&"'")&",'"&TEXT(D29,"aaaa-mm-dd hh:mm:ss")&"',"&IF(E29="","NULL","'"&TEXT(E29,"aaaa-mm-dd hh:mm:ss")&"'")&","&IF(G29="","NULL","'"&G29&"'")&","&IF(H29="","NULL","'"&H29&"'")&","&IF(I29="","NULL","'"&I29&"'")&","&IF(J29="","NULL","'"&J29&"'")&","&IF(K29="","NULL","'"&K29&"'")&","&IF(L29="","NULL","'"&L29&"'")&","&IF(M29="","NULL","'"&M29&"'")&");" -> INSERT INTO octadesk.stickets (ticket,Data_entrada,Data_resolucao,Titulo_ticket,Usuario_criador_ticket,Status,Grupo_responsavel,Responsavel_ticket,Tags_ticket,Total_de_interacoes) values('193167','2025-04-30 13:25:12','2025-05-01 14:19:21','Backup do historico de conversas - o148872-a4a','Flávia','Resolvido','N2','Juan C.','chat, problema-envio-email','11');
B30: 193168 | C30: =IFERROR(VLOOKUP(Relatorio_[[#This Row],[ticket]],Base!A:A,1,0),"-") -> 193168 | D30: 45777.578 | F30: =IF(Relatorio_[[#This Row],[Data_resolução]]=0,"",Relatorio_[[#This Row],[Data_resolução]]) | G30: Regarding your publication on octadesk.com | H30: COPYTRACK | I30: Novo | J30: Suporte | K30: Brenda | L30: - | M30: 1 | O30: ="INSERT INTO octadesk.stickets ("&$B$1&","&$D$1&","&$F$1&","&$G$1&","&$H$1&","&$I$1&","&$J$1&","&$K$1&","&$L$1&","&$M$1&") values("&IF(B30="","NULL","'"&B30&"'")&",'"&TEXT(D30,"aaaa-mm-dd hh:mm:ss")&"',"&IF(E30="","NULL","'"&TEXT(E30,"aaaa-mm-dd hh:mm:ss")&"'")&","&IF(G30="","NULL","'"&G30&"'")&","&IF(H30="","NULL","'"&H30&"'")&","&IF(I30="","NULL","'"&I30&"'")&","&IF(J30="","NULL","'"&J30&"'")&","&IF(K30="","NULL","'"&K30&"'")&","&IF(L30="","NULL","'"&L30&"'")&","&IF(M30="","NULL","'"&M30&"'")&");" -> INSERT INTO octadesk.stickets (ticket,Data_entrada,Data_resolucao,Titulo_ticket,Usuario_criador_ticket,Status,Grupo_responsavel,Responsavel_ticket,Tags_ticket,Total_de_interacoes) values('193168','2025-04-30 13:51:59',NULL,'Regarding your publication on octadesk.com','COPYTRACK','Novo','Suporte','Brenda','-','1');
B31: 193169 | C31: =IFERROR(VLOOKUP(Relatorio_[[#This Row],[ticket]],Base!A:A,1,0),"-") -> 193169 | D31: 45777.598 | E31: 45777.598 | F31: =IF(Relatorio_[[#This Row],[Data_resolução]]=0,"",Relatorio_[[#This Row],[Data_resolução]]) -> 45777.598 | G31: Retorno sobre recolhimento de Imposto. | H31: Mariana C. | I31: Resolvido | J31: Financeiro | L31: - | M31: 1 | O31: ="INSERT INTO octadesk.stickets ("&$B$1&","&$D$1&","&$F$1&","&$G$1&","&$H$1&","&$I$1&","&$J$1&","&$K$1&","&$L$1&","&$M$1&") values("&IF(B31="","NULL","'"&B31&"'")&",'"&TEXT(D31,"aaaa-mm-dd hh:mm:ss")&"',"&IF(E31="","NULL","'"&TEXT(E31,"aaaa-mm-dd hh:mm:ss")&"'")&","&IF(G31="","NULL","'"&G31&"'")&","&IF(H31="","NULL","'"&H31&"'")&","&IF(I31="","NULL","'"&I31&"'")&","&IF(J31="","NULL","'"&J31&"'")&","&IF(K31="","NULL","'"&K31&"'")&","&IF(L31="","NULL","'"&L31&"'")&","&IF(M31="","NULL","'"&M31&"'")&");" -> INSERT INTO octadesk.stickets (ticket,Data_entrada,Data_resolucao,Titulo_ticket,Usuario_criador_ticket,Status,Grupo_responsavel,Responsavel_ticket,Tags_ticket,Total_de_interacoes) values('193169','2025-04-30 14:21:04','2025-04-30 14:21:04','Retorno sobre recolhimento de Imposto.','Mariana C.','Resolvido','Financeiro',NULL,'-','1');
B32: 193170 | C32: =IFERROR(VLOOKUP(Relatorio_[[#This Row],[ticket]],Base!A:A,1,0),"-") -> 193170 | D32: 45777.605 | F32: =IF(Relatorio_[[#This Row],[Data_resolução]]=0,"",Relatorio_[[#This Row],[Data_resolução]]) | G32: (Confirmação de encaminhamento do LWSA: receber e-mail de ouvidoria@new.octadesk.com | H32: Gmail Equipe | I32: Novo | J32: Ouvidoria | K32: Mateus M. | L32: - | M32: 1 | O32: ="INSERT INTO octadesk.stickets ("&$B$1&","&$D$1&","&$F$1&","&$G$1&","&$H$1&","&$I$1&","&$J$1&","&$K$1&","&$L$1&","&$M$1&") values("&IF(B32="","NULL","'"&B32&"'")&",'"&TEXT(D32,"aaaa-mm-dd hh:mm:ss")&"',"&IF(E32="","NULL","'"&TEXT(E32,"aaaa-mm-dd hh:mm:ss")&"'")&","&IF(G32="","NULL","'"&G32&"'")&","&IF(H32="","NULL","'"&H32&"'")&","&IF(I32="","NULL","'"&I32&"'")&","&IF(J32="","NULL","'"&J32&"'")&","&IF(K32="","NULL","'"&K32&"'")&","&IF(L32="","NULL","'"&L32&"'")&","&IF(M32="","NULL","'"&M32&"'")&");" -> INSERT INTO octadesk.stickets (ticket,Data_entrada,Data_resolucao,Titulo_ticket,Usuario_criador_ticket,Status,Grupo_responsavel,Responsavel_ticket,Tags_ticket,Total_de_interacoes) values('193170','2025-04-30 14:30:57',NULL,'(Confirmação de encaminhamento do LWSA: receber e-mail de ouvidoria@new.octadesk.com','Gmail Equipe','Novo','Ouvidoria','Mateus M.','-','1');
B33: 193171 | C33: =IFERROR(VLOOKUP(Relatorio_[[#This Row],[ticket]],Base!A:A,1,0),"-") -> 193171 | D33: 45777.605 | E33: 45777.693 | F33: =IF(Relatorio_[[#This Row],[Data_resolução]]=0,"",Relatorio_[[#This Row],[Data_resolução]]) -> 45777.693 | G33: (Confirmação de encaminhamento do LWSA: receber e-mail de contasareceber@new.octadesk.com | H33: Gmail Equipe | I33: Resolvido | J33: Financeiro | L33: - | M33: 2 | O33: ="INSERT INTO octadesk.stickets ("&$B$1&","&$D$1&","&$F$1&","&$G$1&","&$H$1&","&$I$1&","&$J$1&","&$K$1&","&$L$1&","&$M$1&") values("&IF(B33="","NULL","'"&B33&"'")&",'"&TEXT(D33,"aaaa-mm-dd hh:mm:ss")&"',"&IF(E33="","NULL","'"&TEXT(E33,"aaaa-mm-dd hh:mm:ss")&"'")&","&IF(G33="","NULL","'"&G33&"'")&","&IF(H33="","NULL","'"&H33&"'")&","&IF(I33="","NULL","'"&I33&"'")&","&IF(J33="","NULL","'"&J33&"'")&","&IF(K33="","NULL","'"&K33&"'")&","&IF(L33="","NULL","'"&L33&"'")&","&IF(M33="","NULL","'"&M33&"'")&");" -> INSERT INTO octadesk.stickets (ticket,Data_entrada,Data_resolucao,Titulo_ticket,Usuario_criador_ticket,Status,Grupo_responsavel,Responsavel_ticket,Tags_ticket,Total_de_interacoes) values('193171','2025-04-30 14:31:28','2025-04-30 16:37:32','(Confirmação de encaminhamento do LWSA: receber e-mail de contasareceber@new.octadesk.com','Gmail Equipe','Resolvido','Financeiro',NULL,'-','2');
B34: 193172 | C34: =IFERROR(VLOOKUP(Relatorio_[[#This Row],[ticket]],Base!A:A,1,0),"-") -> 193172 | D34: 45777.614 | F34: =IF(Relatorio_[[#This Row],[Data_resolução]]=0,"",Relatorio_[[#This Row],[Data_resolução]]) | G34: Suporte - Tickets | H34: Gabriel - Gold Languages Traduções | I34: Pendente | J34: Suporte | K34: Brenda | L34: automacao-24horas | M34: 2 | O34: ="INSERT INTO octadesk.stickets ("&$B$1&","&$D$1&","&$F$1&","&$G$1&","&$H$1&","&$I$1&","&$J$1&","&$K$1&","&$L$1&","&$M$1&") values("&IF(B34="","NULL","'"&B34&"'")&",'"&TEXT(D34,"aaaa-mm-dd hh:mm:ss")&"',"&IF(E34="","NULL","'"&TEXT(E34,"aaaa-mm-dd hh:mm:ss")&"'")&","&IF(G34="","NULL","'"&G34&"'")&","&IF(H34="","NULL","'"&H34&"'")&","&IF(I34="","NULL","'"&I34&"'")&","&IF(J34="","NULL","'"&J34&"'")&","&IF(K34="","NULL","'"&K34&"'")&","&IF(L34="","NULL","'"&L34&"'")&","&IF(M34="","NULL","'"&M34&"'")&");" -> INSERT INTO octadesk.stickets (ticket,Data_entrada,Data_resolucao,Titulo_ticket,Usuario_criador_ticket,Status,Grupo_responsavel,Responsavel_ticket,Tags_ticket,Total_de_interacoes) values('193172','2025-04-30 14:44:44',NULL,'Suporte - Tickets','Gabriel - Gold Languages Traduções','Pendente','Suporte','Brenda','automacao-24horas','2');
B35: 193173 | C35: =IFERROR(VLOOKUP(Relatorio_[[#This Row],[ticket]],Base!A:A,1,0),"-") -> 193173 | D35: 45777.615 | F35: =IF(Relatorio_[[#This Row],[Data_resolução]]=0,"",Relatorio_[[#This Row],[Data_resolução]]) | G35: Erro ao alterar a atribuição dos tickets - o158707-351 | H35: Wilson | I35: Em andamento | J35: N2 | K35: Juan C. | L35: chat, problema-envio-email, 193194 | M35: 14 | O35: ="INSERT INTO octadesk.stickets ("&$B$1&","&$D$1&","&$F$1&","&$G$1&","&$H$1&","&$I$1&","&$J$1&","&$K$1&","&$L$1&","&$M$1&") values("&IF(B35="","NULL","'"&B35&"'")&",'"&TEXT(D35,"aaaa-mm-dd hh:mm:ss")&"',"&IF(E35="","NULL","'"&TEXT(E35,"aaaa-mm-dd hh:mm:ss")&"'")&","&IF(G35="","NULL","'"&G35&"'")&","&IF(H35="","NULL","'"&H35&"'")&","&IF(I35="","NULL","'"&I35&"'")&","&IF(J35="","NULL","'"&J35&"'")&","&IF(K35="","NULL","'"&K35&"'")&","&IF(L35="","NULL","'"&L35&"'")&","&IF(M35="","NULL","'"&M35&"'")&");" -> INSERT INTO octadesk.stickets (ticket,Data_entrada,Data_resolucao,Titulo_ticket,Usuario_criador_ticket,Status,Grupo_responsavel,Responsavel_ticket,Tags_ticket,Total_de_interacoes) values('193173','2025-04-30 14:45:16',NULL,'Erro ao alterar a atribuição dos tickets - o158707-351','Wilson','Em andamento','N2','Juan C.','chat, problema-envio-email, 193194','14');
B36: 193174 | C36: =IFERROR(VLOOKUP(Relatorio_[[#This Row],[ticket]],Base!A:A,1,0),"-") -> 193174 | D36: 45777.633 | F36: =IF(Relatorio_[[#This Row],[Data_resolução]]=0,"",Relatorio_[[#This Row],[Data_resolução]]) | G36: Reembolso - Brietzig Administracao E Corretagem De Imoveis | H36: Silvia S. | I36: Em andamento | J36: OTC | L36: - | M36: 2 | O36: ="INSERT INTO octadesk.stickets ("&$B$1&","&$D$1&","&$F$1&","&$G$1&","&$H$1&","&$I$1&","&$J$1&","&$K$1&","&$L$1&","&$M$1&") values("&IF(B36="","NULL","'"&B36&"'")&",'"&TEXT(D36,"aaaa-mm-dd hh:mm:ss")&"',"&IF(E36="","NULL","'"&TEXT(E36,"aaaa-mm-dd hh:mm:ss")&"'")&","&IF(G36="","NULL","'"&G36&"'")&","&IF(H36="","NULL","'"&H36&"'")&","&IF(I36="","NULL","'"&I36&"'")&","&IF(J36="","NULL","'"&J36&"'")&","&IF(K36="","NULL","'"&K36&"'")&","&IF(L36="","NULL","'"&L36&"'")&","&IF(M36="","NULL","'"&M36&"'")&");" -> INSERT INTO octadesk.stickets (ticket,Data_entrada,Data_resolucao,Titulo_ticket,Usuario_criador_ticket,Status,Grupo_responsavel,Responsavel_ticket,Tags_ticket,Total_de_interacoes) values('193174','2025-04-30 15:11:24',NULL,'Reembolso - Brietzig Administracao E Corretagem De Imoveis','Silvia S.','Em andamento','OTC',NULL,'-','2');
B37: 193175 | C37: =IFERROR(VLOOKUP(Relatorio_[[#This Row],[ticket]],Base!A:A,1,0),"-") -> 193175 | D37: 45777.633 | E37: 45777.644 | F37: =IF(Relatorio_[[#This Row],[Data_resolução]]=0,"",Relatorio_[[#This Row],[Data_resolução]]) -> 45777.644 | G37: Olá psi, aqui está nossa conversa! #15954 | H37: psi | I37: Cancelado | J37: Suporte | K37: Brenda | L37: - | M37: 2 | O37: ="INSERT INTO octadesk.stickets ("&$B$1&","&$D$1&","&$F$1&","&$G$1&","&$H$1&","&$I$1&","&$J$1&","&$K$1&","&$L$1&","&$M$1&") values("&IF(B37="","NULL","'"&B37&"'")&",'"&TEXT(D37,"aaaa-mm-dd hh:mm:ss")&"',"&IF(E37="","NULL","'"&TEXT(E37,"aaaa-mm-dd hh:mm:ss")&"'")&","&IF(G37="","NULL","'"&G37&"'")&","&IF(H37="","NULL","'"&H37&"'")&","&IF(I37="","NULL","'"&I37&"'")&","&IF(J37="","NULL","'"&J37&"'")&","&IF(K37="","NULL","'"&K37&"'")&","&IF(L37="","NULL","'"&L37&"'")&","&IF(M37="","NULL","'"&M37&"'")&");" -> INSERT INTO octadesk.stickets (ticket,Data_entrada,Data_resolucao,Titulo_ticket,Usuario_criador_ticket,Status,Grupo_responsavel,Responsavel_ticket,Tags_ticket,Total_de_interacoes) values('193175','2025-04-30 15:11:39','2025-04-30 15:26:57','Olá psi, aqui está nossa conversa! #15954','psi','Cancelado','Suporte','Brenda','-','2');
B38: 193176 | C38: =IFERROR(VLOOKUP(Relatorio_[[#This Row],[ticket]],Base!A:A,1,0),"-") -> 193176 | D38: 45777.633 | E38: 45777.644 | F38: =IF(Relatorio_[[#This Row],[Data_resolução]]=0,"",Relatorio_[[#This Row],[Data_resolução]]) -> 45777.644 | G38: Olá psi, aqui está nossa conversa! #15954 | H38: psi | I38: Cancelado | J38: Suporte | K38: Brenda | L38: - | M38: 2 | O38: ="INSERT INTO octadesk.stickets ("&$B$1&","&$D$1&","&$F$1&","&$G$1&","&$H$1&","&$I$1&","&$J$1&","&$K$1&","&$L$1&","&$M$1&") values("&IF(B38="","NULL","'"&B38&"'")&",'"&TEXT(D38,"aaaa-mm-dd hh:mm:ss")&"',"&IF(E38="","NULL","'"&TEXT(E38,"aaaa-mm-dd hh:mm:ss")&"'")&","&IF(G38="","NULL","'"&G38&"'")&","&IF(H38="","NULL","'"&H38&"'")&","&IF(I38="","NULL","'"&I38&"'")&","&IF(J38="","NULL","'"&J38&"'")&","&IF(K38="","NULL","'"&K38&"'")&","&IF(L38="","NULL","'"&L38&"'")&","&IF(M38="","NULL","'"&M38&"'")&");" -> INSERT INTO octadesk.stickets (ticket,Data_entrada,Data_resolucao,Titulo_ticket,Usuario_criador_ticket,Status,Grupo_responsavel,Responsavel_ticket,Tags_ticket,Total_de_interacoes) values('193176','2025-04-30 15:11:40','2025-04-30 15:26:46','Olá psi, aqui está nossa conversa! #15954','psi','Cancelado','Suporte','Brenda','-','2');
B39: 193177 | C39: =IFERROR(VLOOKUP(Relatorio_[[#This Row],[ticket]],Base!A:A,1,0),"-") -> 193177 | D39: 45777.638 | F39: =IF(Relatorio_[[#This Row],[Data_resolução]]=0,"",Relatorio_[[#This Row],[Data_resolução]]) | G39: Incidente - WOZ transcrição não está funcionando como deveria - o184072-481 | H39: Juan C. | I39: Pendente | J39: N2 | K39: Juan C. | L39: 193123, ticket-corrigido | M39: 4 | O39: ="INSERT INTO octadesk.stickets ("&$B$1&","&$D$1&","&$F$1&","&$G$1&","&$H$1&","&$I$1&","&$J$1&","&$K$1&","&$L$1&","&$M$1&") values("&IF(B39="","NULL","'"&B39&"'")&",'"&TEXT(D39,"aaaa-mm-dd hh:mm:ss")&"',"&IF(E39="","NULL","'"&TEXT(E39,"aaaa-mm-dd hh:mm:ss")&"'")&","&IF(G39="","NULL","'"&G39&"'")&","&IF(H39="","NULL","'"&H39&"'")&","&IF(I39="","NULL","'"&I39&"'")&","&IF(J39="","NULL","'"&J39&"'")&","&IF(K39="","NULL","'"&K39&"'")&","&IF(L39="","NULL","'"&L39&"'")&","&IF(M39="","NULL","'"&M39&"'")&");" -> INSERT INTO octadesk.stickets (ticket,Data_entrada,Data_resolucao,Titulo_ticket,Usuario_criador_ticket,Status,Grupo_responsavel,Responsavel_ticket,Tags_ticket,Total_de_interacoes) values('193177','2025-04-30 15:18:38',NULL,'Incidente - WOZ transcrição não está funcionando como deveria - o184072-481','Juan C.','Pendente','N2','Juan C.','193123, ticket-corrigido','4');
B40: 193178 | C40: =IFERROR(VLOOKUP(Relatorio_[[#This Row],[ticket]],Base!A:A,1,0),"-") -> 193178 | D40: 45777.646 | E40: 45778.728 | F40: =IF(Relatorio_[[#This Row],[Data_resolução]]=0,"",Relatorio_[[#This Row],[Data_resolução]]) -> 45778.728 | G40: Sua conta do WhatsApp Business está violando a política | H40: Facebook | I40: Resolvido | J40: Suporte | K40: Suporte | L40: - | M40: 2 | O40: ="INSERT INTO octadesk.stickets ("&$B$1&","&$D$1&","&$F$1&","&$G$1&","&$H$1&","&$I$1&","&$J$1&","&$K$1&","&$L$1&","&$M$1&") values("&IF(B40="","NULL","'"&B40&"'")&",'"&TEXT(D40,"aaaa-mm-dd hh:mm:ss")&"',"&IF(E40="","NULL","'"&TEXT(E40,"aaaa-mm-dd hh:mm:ss")&"'")&","&IF(G40="","NULL","'"&G40&"'")&","&IF(H40="","NULL","'"&H40&"'")&","&IF(I40="","NULL","'"&I40&"'")&","&IF(J40="","NULL","'"&J40&"'")&","&IF(K40="","NULL","'"&K40&"'")&","&IF(L40="","NULL","'"&L40&"'")&","&IF(M40="","NULL","'"&M40&"'")&");" -> INSERT INTO octadesk.stickets (ticket,Data_entrada,Data_resolucao,Titulo_ticket,Usuario_criador_ticket,Status,Grupo_responsavel,Responsavel_ticket,Tags_ticket,Total_de_interacoes) values('193178','2025-04-30 15:30:24','2025-05-01 17:28:47','Sua conta do WhatsApp Business está violando a política','Facebook','Resolvido','Suporte','Suporte','-','2');
B41: 193179 | C41: =IFERROR(VLOOKUP(Relatorio_[[#This Row],[ticket]],Base!A:A,1,0),"-") -> 193179 | D41: 45777.648 | E41: 45777.745 | F41: =IF(Relatorio_[[#This Row],[Data_resolução]]=0,"",Relatorio_[[#This Row],[Data_resolução]]) -> 45777.745 | G41: Olá psi, aqui está nossa conversa! #15954 | H41: psi | I41: Cancelado | J41: Suporte | K41: Brenda | L41: - | M41: 2 | O41: ="INSERT INTO octadesk.stickets ("&$B$1&","&$D$1&","&$F$1&","&$G$1&","&$H$1&","&$I$1&","&$J$1&","&$K$1&","&$L$1&","&$M$1&") values("&IF(B41="","NULL","'"&B41&"'")&",'"&TEXT(D41,"aaaa-mm-dd hh:mm:ss")&"',"&IF(E41="","NULL","'"&TEXT(E41,"aaaa-mm-dd hh:mm:ss")&"'")&","&IF(G41="","NULL","'"&G41&"'")&","&IF(H41="","NULL","'"&H41&"'")&","&IF(I41="","NULL","'"&I41&"'")&","&IF(J41="","NULL","'"&J41&"'")&","&IF(K41="","NULL","'"&K41&"'")&","&IF(L41="","NULL","'"&L41&"'")&","&IF(M41="","NULL","'"&M41&"'")&");" -> INSERT INTO octadesk.stickets (ticket,Data_entrada,Data_resolucao,Titulo_ticket,Usuario_criador_ticket,Status,Grupo_responsavel,Responsavel_ticket,Tags_ticket,Total_de_interacoes) values('193179','2025-04-30 15:33:33','2025-04-30 17:53:25','Olá psi, aqui está nossa conversa! #15954','psi','Cancelado','Suporte','Brenda','-','2');
B42: 193180 | C42: =IFERROR(VLOOKUP(Relatorio_[[#This Row],[ticket]],Base!A:A,1,0),"-") -> 193180 | D42: 45777.683 | F42: =IF(Relatorio_[[#This Row],[Data_resolução]]=0,"",Relatorio_[[#This Row],[Data_resolução]]) | G42: Webhook não dispara evento | H42: Marcelo | I42: Novo | J42: N2 | L42: chat | M42: 10 | O42: ="INSERT INTO octadesk.stickets ("&$B$1&","&$D$1&","&$F$1&","&$G$1&","&$H$1&","&$I$1&","&$J$1&","&$K$1&","&$L$1&","&$M$1&") values("&IF(B42="","NULL","'"&B42&"'")&",'"&TEXT(D42,"aaaa-mm-dd hh:mm:ss")&"',"&IF(E42="","NULL","'"&TEXT(E42,"aaaa-mm-dd hh:mm:ss")&"'")&","&IF(G42="","NULL","'"&G42&"'")&","&IF(H42="","NULL","'"&H42&"'")&","&IF(I42="","NULL","'"&I42&"'")&","&IF(J42="","NULL","'"&J42&"'")&","&IF(K42="","NULL","'"&K42&"'")&","&IF(L42="","NULL","'"&L42&"'")&","&IF(M42="","NULL","'"&M42&"'")&");" -> INSERT INTO octadesk.stickets (ticket,Data_entrada,Data_resolucao,Titulo_ticket,Usuario_criador_ticket,Status,Grupo_responsavel,Responsavel_ticket,Tags_ticket,Total_de_interacoes) values('193180','2025-04-30 16:23:12',NULL,'Webhook não dispara evento','Marcelo','Novo','N2',NULL,'chat','10');
B43: 193181 | C43: =IFERROR(VLOOKUP(Relatorio_[[#This Row],[ticket]],Base!A:A,1,0),"-") -> 193181 | D43: 45777.683 | E43: 45778.688 | F43: =IF(Relatorio_[[#This Row],[Data_resolução]]=0,"",Relatorio_[[#This Row],[Data_resolução]]) -> 45778.688 | G43: Sua conta do WhatsApp Business está violando a política | H43: Facebook | I43: Resolvido | J43: Suporte | K43: Suporte | L43: - | M43: 2 | O43: ="INSERT INTO octadesk.stickets ("&$B$1&","&$D$1&","&$F$1&","&$G$1&","&$H$1&","&$I$1&","&$J$1&","&$K$1&","&$L$1&","&$M$1&") values("&IF(B43="","NULL","'"&B43&"'")&",'"&TEXT(D43,"aaaa-mm-dd hh:mm:ss")&"',"&IF(E43="","NULL","'"&TEXT(E43,"aaaa-mm-dd hh:mm:ss")&"'")&","&IF(G43="","NULL","'"&G43&"'")&","&IF(H43="","NULL","'"&H43&"'")&","&IF(I43="","NULL","'"&I43&"'")&","&IF(J43="","NULL","'"&J43&"'")&","&IF(K43="","NULL","'"&K43&"'")&","&IF(L43="","NULL","'"&L43&"'")&","&IF(M43="","NULL","'"&M43&"'")&");" -> INSERT INTO octadesk.stickets (ticket,Data_entrada,Data_resolucao,Titulo_ticket,Usuario_criador_ticket,Status,Grupo_responsavel,Responsavel_ticket,Tags_ticket,Total_de_interacoes) values('193181','2025-04-30 16:23:39','2025-05-01 16:31:20','Sua conta do WhatsApp Business está violando a política','Facebook','Resolvido','Suporte','Suporte','-','2');
B44: 193182 | C44: =IFERROR(VLOOKUP(Relatorio_[[#This Row],[ticket]],Base!A:A,1,0),"-") -> 193182 | D44: 45777.691 | E44: 45779.545 | F44: =IF(Relatorio_[[#This Row],[Data_resolução]]=0,"",Relatorio_[[#This Row],[Data_resolução]]) -> 45779.545 | G44: Sua conta do WhatsApp Business está violando a política | H44: Facebook | I44: Resolvido | J44: Suporte | K44: Suporte | L44: - | M44: 2 | O44: ="INSERT INTO octadesk.stickets ("&$B$1&","&$D$1&","&$F$1&","&$G$1&","&$H$1&","&$I$1&","&$J$1&","&$K$1&","&$L$1&","&$M$1&") values("&IF(B44="","NULL","'"&B44&"'")&",'"&TEXT(D44,"aaaa-mm-dd hh:mm:ss")&"',"&IF(E44="","NULL","'"&TEXT(E44,"aaaa-mm-dd hh:mm:ss")&"'")&","&IF(G44="","NULL","'"&G44&"'")&","&IF(H44="","NULL","'"&H44&"'")&","&IF(I44="","NULL","'"&I44&"'")&","&IF(J44="","NULL","'"&J44&"'")&","&IF(K44="","NULL","'"&K44&"'")&","&IF(L44="","NULL","'"&L44&"'")&","&IF(M44="","NULL","'"&M44&"'")&");" -> INSERT INTO octadesk.stickets (ticket,Data_entrada,Data_resolucao,Titulo_ticket,Usuario_criador_ticket,Status,Grupo_responsavel,Responsavel_ticket,Tags_ticket,Total_de_interacoes) values('193182','2025-04-30 16:35:16','2025-05-02 13:04:29','Sua conta do WhatsApp Business está violando a política','Facebook','Resolvido','Suporte','Suporte','-','2');
B45: 193183 | C45: =IFERROR(VLOOKUP(Relatorio_[[#This Row],[ticket]],Base!A:A,1,0),"-") -> 193183 | D45: 45777.694 | F45: =IF(Relatorio_[[#This Row],[Data_resolução]]=0,"",Relatorio_[[#This Row],[Data_resolução]]) | G45: PROD - Octa-Conversas - Impossibilidade de utilizar o WOZ copiloto mesmo com os créditos adequados no ambiente - copihel1 | H45: Lucas Muniz | I45: Novo | J45: PROD - Octa-Conversas | K45: Juliana Wilcke | L45: 193066 | M45: 6 | O45: ="INSERT INTO octadesk.stickets ("&$B$1&","&$D$1&","&$F$1&","&$G$1&","&$H$1&","&$I$1&","&$J$1&","&$K$1&","&$L$1&","&$M$1&") values("&IF(B45="","NULL","'"&B45&"'")&",'"&TEXT(D45,"aaaa-mm-dd hh:mm:ss")&"',"&IF(E45="","NULL","'"&TEXT(E45,"aaaa-mm-dd hh:mm:ss")&"'")&","&IF(G45="","NULL","'"&G45&"'")&","&IF(H45="","NULL","'"&H45&"'")&","&IF(I45="","NULL","'"&I45&"'")&","&IF(J45="","NULL","'"&J45&"'")&","&IF(K45="","NULL","'"&K45&"'")&","&IF(L45="","NULL","'"&L45&"'")&","&IF(M45="","NULL","'"&M45&"'")&");" -> INSERT INTO octadesk.stickets (ticket,Data_entrada,Data_resolucao,Titulo_ticket,Usuario_criador_ticket,Status,Grupo_responsavel,Responsavel_ticket,Tags_ticket,Total_de_interacoes) values('193183','2025-04-30 16:39:08',NULL,'PROD - Octa-Conversas - Impossibilidade de utilizar o WOZ copiloto mesmo com os créditos adequados no ambiente - copihel1','Lucas Muniz','Novo','PROD - Octa-Conversas','Juliana Wilcke','193066','6');
B46: 193184 | C46: =IFERROR(VLOOKUP(Relatorio_[[#This Row],[ticket]],Base!A:A,1,0),"-") -> 193184 | D46: 45777.695 | E46: 45777.745 | F46: =IF(Relatorio_[[#This Row],[Data_resolução]]=0,"",Relatorio_[[#This Row],[Data_resolução]]) -> 45777.745 | G46: Nova fatura de Octadesk Ltda, n.º 189751-0013 | H46: Mauricio Rodrigues Borges | I46: Cancelado | J46: Suporte | K46: Brenda | L46: - | M46: 2 | O46: ="INSERT INTO octadesk.stickets ("&$B$1&","&$D$1&","&$F$1&","&$G$1&","&$H$1&","&$I$1&","&$J$1&","&$K$1&","&$L$1&","&$M$1&") values("&IF(B46="","NULL","'"&B46&"'")&",'"&TEXT(D46,"aaaa-mm-dd hh:mm:ss")&"',"&IF(E46="","NULL","'"&TEXT(E46,"aaaa-mm-dd hh:mm:ss")&"'")&","&IF(G46="","NULL","'"&G46&"'")&","&IF(H46="","NULL","'"&H46&"'")&","&IF(I46="","NULL","'"&I46&"'")&","&IF(J46="","NULL","'"&J46&"'")&","&IF(K46="","NULL","'"&K46&"'")&","&IF(L46="","NULL","'"&L46&"'")&","&IF(M46="","NULL","'"&M46&"'")&");" -> INSERT INTO octadesk.stickets (ticket,Data_entrada,Data_resolucao,Titulo_ticket,Usuario_criador_ticket,Status,Grupo_responsavel,Responsavel_ticket,Tags_ticket,Total_de_interacoes) values('193184','2025-04-30 16:41:14','2025-04-30 17:53:08','Nova fatura de Octadesk Ltda, n.º 189751-0013','Mauricio Rodrigues Borges','Cancelado','Suporte','Brenda','-','2');
B47: 193185 | C47: =IFERROR(VLOOKUP(Relatorio_[[#This Row],[ticket]],Base!A:A,1,0),"-") -> 193185 | D47: 45777.698 | F47: =IF(Relatorio_[[#This Row],[Data_resolução]]=0,"",Relatorio_[[#This Row],[Data_resolução]]) | G47: PROD - Chat-Mobile-Widget - Conversas Fora do Critério Aparecendo na Lista "Tempo Excedido" - o159525-4ea | H47: Juan C. | I47: Novo | J47: PROD - Octa-Conversas | K47: Juliana Wilcke | L47: 189947 | M47: 3 | O47: ="INSERT INTO octadesk.stickets ("&$B$1&","&$D$1&","&$F$1&","&$G$1&","&$H$1&","&$I$1&","&$J$1&","&$K$1&","&$L$1&","&$M$1&") values("&IF(B47="","NULL","'"&B47&"'")&",'"&TEXT(D47,"aaaa-mm-dd hh:mm:ss")&"',"&IF(E47="","NULL","'"&TEXT(E47,"aaaa-mm-dd hh:mm:ss")&"'")&","&IF(G47="","NULL","'"&G47&"'")&","&IF(H47="","NULL","'"&H47&"'")&","&IF(I47="","NULL","'"&I47&"'")&","&IF(J47="","NULL","'"&J47&"'")&","&IF(K47="","NULL","'"&K47&"'")&","&IF(L47="","NULL","'"&L47&"'")&","&IF(M47="","NULL","'"&M47&"'")&");" -> INSERT INTO octadesk.stickets (ticket,Data_entrada,Data_resolucao,Titulo_ticket,Usuario_criador_ticket,Status,Grupo_responsavel,Responsavel_ticket,Tags_ticket,Total_de_interacoes) values('193185','2025-04-30 16:44:36',NULL,'PROD - Chat-Mobile-Widget - Conversas Fora do Critério Aparecendo na Lista "Tempo Excedido" - o159525-4ea','Juan C.','Novo','PROD - Octa-Conversas','Juliana Wilcke','189947','3');
B48: 193186 | C48: =IFERROR(VLOOKUP(Relatorio_[[#This Row],[ticket]],Base!A:A,1,0),"-") -> 193186 | D48: 45777.7 | E48: 45777.744 | F48: =IF(Relatorio_[[#This Row],[Data_resolução]]=0,"",Relatorio_[[#This Row],[Data_resolução]]) -> 45777.744 | G48: WHATSAPP ARANTES ARIMURA ADVOCACIA - ATENÇÃO | H48: Escritório Arantes Arimura Advocacia | I48: Cancelado | J48: Suporte | K48: Brenda | L48: - | M48: 2 | O48: ="INSERT INTO octadesk.stickets ("&$B$1&","&$D$1&","&$F$1&","&$G$1&","&$H$1&","&$I$1&","&$J$1&","&$K$1&","&$L$1&","&$M$1&") values("&IF(B48="","NULL","'"&B48&"'")&",'"&TEXT(D48,"aaaa-mm-dd hh:mm:ss")&"',"&IF(E48="","NULL","'"&TEXT(E48,"aaaa-mm-dd hh:mm:ss")&"'")&","&IF(G48="","NULL","'"&G48&"'")&","&IF(H48="","NULL","'"&H48&"'")&","&IF(I48="","NULL","'"&I48&"'")&","&IF(J48="","NULL","'"&J48&"'")&","&IF(K48="","NULL","'"&K48&"'")&","&IF(L48="","NULL","'"&L48&"'")&","&IF(M48="","NULL","'"&M48&"'")&");" -> INSERT INTO octadesk.stickets (ticket,Data_entrada,Data_resolucao,Titulo_ticket,Usuario_criador_ticket,Status,Grupo_responsavel,Responsavel_ticket,Tags_ticket,Total_de_interacoes) values('193186','2025-04-30 16:48:12','2025-04-30 17:51:36','WHATSAPP ARANTES ARIMURA ADVOCACIA - ATENÇÃO','Escritório Arantes Arimura Advocacia','Cancelado','Suporte','Brenda','-','2');
B49: 193187 | C49: =IFERROR(VLOOKUP(Relatorio_[[#This Row],[ticket]],Base!A:A,1,0),"-") -> 193187 | D49: 45777.721 | F49: =IF(Relatorio_[[#This Row],[Data_resolução]]=0,"",Relatorio_[[#This Row],[Data_resolução]]) | G49: Erro para acessar estúdio de automação - o168184-297 | H49: kiara | I49: Pendente | J49: N2 | L49: chat, ticket-corrigido, problema-envio-email | M49: 7 | O49: ="INSERT INTO octadesk.stickets ("&$B$1&","&$D$1&","&$F$1&","&$G$1&","&$H$1&","&$I$1&","&$J$1&","&$K$1&","&$L$1&","&$M$1&") values("&IF(B49="","NULL","'"&B49&"'")&",'"&TEXT(D49,"aaaa-mm-dd hh:mm:ss")&"',"&IF(E49="","NULL","'"&TEXT(E49,"aaaa-mm-dd hh:mm:ss")&"'")&","&IF(G49="","NULL","'"&G49&"'")&","&IF(H49="","NULL","'"&H49&"'")&","&IF(I49="","NULL","'"&I49&"'")&","&IF(J49="","NULL","'"&J49&"'")&","&IF(K49="","NULL","'"&K49&"'")&","&IF(L49="","NULL","'"&L49&"'")&","&IF(M49="","NULL","'"&M49&"'")&");" -> INSERT INTO octadesk.stickets (ticket,Data_entrada,Data_resolucao,Titulo_ticket,Usuario_criador_ticket,Status,Grupo_responsavel,Responsavel_ticket,Tags_ticket,Total_de_interacoes) values('193187','2025-04-30 17:18:11',NULL,'Erro para acessar estúdio de automação - o168184-297','kiara','Pendente','N2',NULL,'chat, ticket-corrigido, problema-envio-email','7');
B50: 193188 | C50: =IFERROR(VLOOKUP(Relatorio_[[#This Row],[ticket]],Base!A:A,1,0),"-") -> 193188 | D50: 45777.722 | F50: =IF(Relatorio_[[#This Row],[Data_resolução]]=0,"",Relatorio_[[#This Row],[Data_resolução]]) | G50: Conversas com delay - o205589-8bc | H50: Rodrigo - Bruning Sistema | I50: Em andamento | J50: N2 | L50: chat, problema-envio-email | M50: 5 | O50: ="INSERT INTO octadesk.stickets ("&$B$1&","&$D$1&","&$F$1&","&$G$1&","&$H$1&","&$I$1&","&$J$1&","&$K$1&","&$L$1&","&$M$1&") values("&IF(B50="","NULL","'"&B50&"'")&",'"&TEXT(D50,"aaaa-mm-dd hh:mm:ss")&"',"&IF(E50="","NULL","'"&TEXT(E50,"aaaa-mm-dd hh:mm:ss")&"'")&","&IF(G50="","NULL","'"&G50&"'")&","&IF(H50="","NULL","'"&H50&"'")&","&IF(I50="","NULL","'"&I50&"'")&","&IF(J50="","NULL","'"&J50&"'")&","&IF(K50="","NULL","'"&K50&"'")&","&IF(L50="","NULL","'"&L50&"'")&","&IF(M50="","NULL","'"&M50&"'")&");" -> INSERT INTO octadesk.stickets (ticket,Data_entrada,Data_resolucao,Titulo_ticket,Usuario_criador_ticket,Status,Grupo_responsavel,Responsavel_ticket,Tags_ticket,Total_de_interacoes) values('193188','2025-04-30 17:19:32',NULL,'Conversas com delay - o205589-8bc','Rodrigo - Bruning Sistema','Em andamento','N2',NULL,'chat, problema-envio-email','5');
B51: 193189 | C51: =IFERROR(VLOOKUP(Relatorio_[[#This Row],[ticket]],Base!A:A,1,0),"-") -> 193189 | D51: 45777.727 | E51: 45777.745 | F51: =IF(Relatorio_[[#This Row],[Data_resolução]]=0,"",Relatorio_[[#This Row],[Data_resolução]]) -> 45777.745 | G51: Olá lizete magalhaes De souza, aqui está nossa conversa! | H51: lizete magalhaes De souza | I51: Cancelado | J51: Suporte | K51: Brenda | L51: - | M51: 2 | O51: ="INSERT INTO octadesk.stickets ("&$B$1&","&$D$1&","&$F$1&","&$G$1&","&$H$1&","&$I$1&","&$J$1&","&$K$1&","&$L$1&","&$M$1&") values("&IF(B51="","NULL","'"&B51&"'")&",'"&TEXT(D51,"aaaa-mm-dd hh:mm:ss")&"',"&IF(E51="","NULL","'"&TEXT(E51,"aaaa-mm-dd hh:mm:ss")&"'")&","&IF(G51="","NULL","'"&G51&"'")&","&IF(H51="","NULL","'"&H51&"'")&","&IF(I51="","NULL","'"&I51&"'")&","&IF(J51="","NULL","'"&J51&"'")&","&IF(K51="","NULL","'"&K51&"'")&","&IF(L51="","NULL","'"&L51&"'")&","&IF(M51="","NULL","'"&M51&"'")&");" -> INSERT INTO octadesk.stickets (ticket,Data_entrada,Data_resolucao,Titulo_ticket,Usuario_criador_ticket,Status,Grupo_responsavel,Responsavel_ticket,Tags_ticket,Total_de_interacoes) values('193189','2025-04-30 17:27:26','2025-04-30 17:53:16','Olá lizete magalhaes De souza, aqui está nossa conversa!','lizete magalhaes De souza','Cancelado','Suporte','Brenda','-','2');
B52: 193190 | C52: =IFERROR(VLOOKUP(Relatorio_[[#This Row],[ticket]],Base!A:A,1,0),"-") -> 193190 | D52: 45777.728 | E52: 45777.743 | F52: =IF(Relatorio_[[#This Row],[Data_resolução]]=0,"",Relatorio_[[#This Row],[Data_resolução]]) -> 45777.743 | G52: Conversas com delay - o205589-8bc | H52: Brenda | I52: Resolvido | J52: N2 | L52: problema-envio-email | M52: 7 | O52: ="INSERT INTO octadesk.stickets ("&$B$1&","&$D$1&","&$F$1&","&$G$1&","&$H$1&","&$I$1&","&$J$1&","&$K$1&","&$L$1&","&$M$1&") values("&IF(B52="","NULL","'"&B52&"'")&",'"&TEXT(D52,"aaaa-mm-dd hh:mm:ss")&"',"&IF(E52="","NULL","'"&TEXT(E52,"aaaa-mm-dd hh:mm:ss")&"'")&","&IF(G52="","NULL","'"&G52&"'")&","&IF(H52="","NULL","'"&H52&"'")&","&IF(I52="","NULL","'"&I52&"'")&","&IF(J52="","NULL","'"&J52&"'")&","&IF(K52="","NULL","'"&K52&"'")&","&IF(L52="","NULL","'"&L52&"'")&","&IF(M52="","NULL","'"&M52&"'")&");" -> INSERT INTO octadesk.stickets (ticket,Data_entrada,Data_resolucao,Titulo_ticket,Usuario_criador_ticket,Status,Grupo_responsavel,Responsavel_ticket,Tags_ticket,Total_de_interacoes) values('193190','2025-04-30 17:28:22','2025-04-30 17:49:40','Conversas com delay - o205589-8bc','Brenda','Resolvido','N2',NULL,'problema-envio-email','7');
B53: 193191 | C53: =IFERROR(VLOOKUP(Relatorio_[[#This Row],[ticket]],Base!A:A,1,0),"-") -> 193191 | D53: 45777.728 | E53: 45777.744 | F53: =IF(Relatorio_[[#This Row],[Data_resolução]]=0,"",Relatorio_[[#This Row],[Data_resolução]]) -> 45777.744 | G53: Convite para se juntar ao Octadesk | H53: octadesk | efetivação de plano | I53: Cancelado | J53: Suporte | K53: Brenda | L53: - | M53: 2 | O53: ="INSERT INTO octadesk.stickets ("&$B$1&","&$D$1&","&$F$1&","&$G$1&","&$H$1&","&$I$1&","&$J$1&","&$K$1&","&$L$1&","&$M$1&") values("&IF(B53="","NULL","'"&B53&"'")&",'"&TEXT(D53,"aaaa-mm-dd hh:mm:ss")&"',"&IF(E53="","NULL","'"&TEXT(E53,"aaaa-mm-dd hh:mm:ss")&"'")&","&IF(G53="","NULL","'"&G53&"'")&","&IF(H53="","NULL","'"&H53&"'")&","&IF(I53="","NULL","'"&I53&"'")&","&IF(J53="","NULL","'"&J53&"'")&","&IF(K53="","NULL","'"&K53&"'")&","&IF(L53="","NULL","'"&L53&"'")&","&IF(M53="","NULL","'"&M53&"'")&");" -> INSERT INTO octadesk.stickets (ticket,Data_entrada,Data_resolucao,Titulo_ticket,Usuario_criador_ticket,Status,Grupo_responsavel,Responsavel_ticket,Tags_ticket,Total_de_interacoes) values('193191','2025-04-30 17:28:53','2025-04-30 17:51:13','Convite para se juntar ao Octadesk','octadesk | efetivação de plano','Cancelado','Suporte','Brenda','-','2');
B54: 193192 | C54: =IFERROR(VLOOKUP(Relatorio_[[#This Row],[ticket]],Base!A:A,1,0),"-") -> 193192 | D54: 45777.753 | E54: 45778.477 | F54: =IF(Relatorio_[[#This Row],[Data_resolução]]=0,"",Relatorio_[[#This Row],[Data_resolução]]) -> 45778.477 | G54: Banimento frequentes da contas do Whatsapp Bussiness | H54: Vinicius De Moraes Martins | I54: Resolvido | J54: Suporte | K54: Brenda | L54: - | M54: 2 | O54: ="INSERT INTO octadesk.stickets ("&$B$1&","&$D$1&","&$F$1&","&$G$1&","&$H$1&","&$I$1&","&$J$1&","&$K$1&","&$L$1&","&$M$1&") values("&IF(B54="","NULL","'"&B54&"'")&",'"&TEXT(D54,"aaaa-mm-dd hh:mm:ss")&"',"&IF(E54="","NULL","'"&TEXT(E54,"aaaa-mm-dd hh:mm:ss")&"'")&","&IF(G54="","NULL","'"&G54&"'")&","&IF(H54="","NULL","'"&H54&"'")&","&IF(I54="","NULL","'"&I54&"'")&","&IF(J54="","NULL","'"&J54&"'")&","&IF(K54="","NULL","'"&K54&"'")&","&IF(L54="","NULL","'"&L54&"'")&","&IF(M54="","NULL","'"&M54&"'")&");" -> INSERT INTO octadesk.stickets (ticket,Data_entrada,Data_resolucao,Titulo_ticket,Usuario_criador_ticket,Status,Grupo_responsavel,Responsavel_ticket,Tags_ticket,Total_de_interacoes) values('193192','2025-04-30 18:03:55','2025-05-01 11:26:17','Banimento frequentes da contas do Whatsapp Bussiness','Vinicius De Moraes Martins','Resolvido','Suporte','Brenda','-','2');
B55: 193193 | C55: =IFERROR(VLOOKUP(Relatorio_[[#This Row],[ticket]],Base!A:A,1,0),"-") -> 193193 | D55: 45777.757 | E55: 45778.725 | F55: =IF(Relatorio_[[#This Row],[Data_resolução]]=0,"",Relatorio_[[#This Row],[Data_resolução]]) -> 45778.725 | G55: Sua conta do WhatsApp Business está violando a política | H55: Facebook | I55: Resolvido | J55: Suporte | K55: Suporte | L55: - | M55: 2 | O55: ="INSERT INTO octadesk.stickets ("&$B$1&","&$D$1&","&$F$1&","&$G$1&","&$H$1&","&$I$1&","&$J$1&","&$K$1&","&$L$1&","&$M$1&") values("&IF(B55="","NULL","'"&B55&"'")&",'"&TEXT(D55,"aaaa-mm-dd hh:mm:ss")&"',"&IF(E55="","NULL","'"&TEXT(E55,"aaaa-mm-dd hh:mm:ss")&"'")&","&IF(G55="","NULL","'"&G55&"'")&","&IF(H55="","NULL","'"&H55&"'")&","&IF(I55="","NULL","'"&I55&"'")&","&IF(J55="","NULL","'"&J55&"'")&","&IF(K55="","NULL","'"&K55&"'")&","&IF(L55="","NULL","'"&L55&"'")&","&IF(M55="","NULL","'"&M55&"'")&");" -> INSERT INTO octadesk.stickets (ticket,Data_entrada,Data_resolucao,Titulo_ticket,Usuario_criador_ticket,Status,Grupo_responsavel,Responsavel_ticket,Tags_ticket,Total_de_interacoes) values('193193','2025-04-30 18:09:24','2025-05-01 17:23:22','Sua conta do WhatsApp Business está violando a política','Facebook','Resolvido','Suporte','Suporte','-','2');
B56: 193194 | C56: =IFERROR(VLOOKUP(Relatorio_[[#This Row],[ticket]],Base!A:A,1,0),"-") -> 193194 | D56: 45777.776 | F56: =IF(Relatorio_[[#This Row],[Data_resolução]]=0,"",Relatorio_[[#This Row],[Data_resolução]]) | G56: PROD - Helpdesk - Atribuição de tickets para usuários que estejam em 2 grupos ou mais, não está ocorrendo - vários ambientes | H56: Juan C. | I56: Novo | J56: PROD - Helpdesk | K56: marcelo.toledo@liax.tech | L56: 193173, 193055, 193226 | M56: 8 | O56: ="INSERT INTO octadesk.stickets ("&$B$1&","&$D$1&","&$F$1&","&$G$1&","&$H$1&","&$I$1&","&$J$1&","&$K$1&","&$L$1&","&$M$1&") values("&IF(B56="","NULL","'"&B56&"'")&",'"&TEXT(D56,"aaaa-mm-dd hh:mm:ss")&"',"&IF(E56="","NULL","'"&TEXT(E56,"aaaa-mm-dd hh:mm:ss")&"'")&","&IF(G56="","NULL","'"&G56&"'")&","&IF(H56="","NULL","'"&H56&"'")&","&IF(I56="","NULL","'"&I56&"'")&","&IF(J56="","NULL","'"&J56&"'")&","&IF(K56="","NULL","'"&K56&"'")&","&IF(L56="","NULL","'"&L56&"'")&","&IF(M56="","NULL","'"&M56&"'")&");" -> INSERT INTO octadesk.stickets (ticket,Data_entrada,Data_resolucao,Titulo_ticket,Usuario_criador_ticket,Status,Grupo_responsavel,Responsavel_ticket,Tags_ticket,Total_de_interacoes) values('193194','2025-04-30 18:36:46',NULL,'PROD - Helpdesk - Atribuição de tickets para usuários que estejam em 2 grupos ou mais, não está ocorrendo - vários ambientes','Juan C.','Novo','PROD - Helpdesk','marcelo.toledo@liax.tech','193173, 193055, 193226','8');
B57: 193195 | C57: =IFERROR(VLOOKUP(Relatorio_[[#This Row],[ticket]],Base!A:A,1,0),"-") -> 193195 | D57: 45777.791 | F57: =IF(Relatorio_[[#This Row],[Data_resolução]]=0,"",Relatorio_[[#This Row],[Data_resolução]]) | G57: Conversa encerrada não encerrou corretamente - o201782-0d2 | H57: Samuel Marques | I57: Pendente | J57: N2 | L57: chat, problema-envio-email | M57: 7 | O57: ="INSERT INTO octadesk.stickets ("&$B$1&","&$D$1&","&$F$1&","&$G$1&","&$H$1&","&$I$1&","&$J$1&","&$K$1&","&$L$1&","&$M$1&") values("&IF(B57="","NULL","'"&B57&"'")&",'"&TEXT(D57,"aaaa-mm-dd hh:mm:ss")&"',"&IF(E57="","NULL","'"&TEXT(E57,"aaaa-mm-dd hh:mm:ss")&"'")&","&IF(G57="","NULL","'"&G57&"'")&","&IF(H57="","NULL","'"&H57&"'")&","&IF(I57="","NULL","'"&I57&"'")&","&IF(J57="","NULL","'"&J57&"'")&","&IF(K57="","NULL","'"&K57&"'")&","&IF(L57="","NULL","'"&L57&"'")&","&IF(M57="","NULL","'"&M57&"'")&");" -> INSERT INTO octadesk.stickets (ticket,Data_entrada,Data_resolucao,Titulo_ticket,Usuario_criador_ticket,Status,Grupo_responsavel,Responsavel_ticket,Tags_ticket,Total_de_interacoes) values('193195','2025-04-30 18:59:10',NULL,'Conversa encerrada não encerrou corretamente - o201782-0d2','Samuel Marques','Pendente','N2',NULL,'chat, problema-envio-email','7');
B58: 193196 | C58: =IFERROR(VLOOKUP(Relatorio_[[#This Row],[ticket]],Base!A:A,1,0),"-") -> 193196 | D58: 45777.805 | E58: 45778.384 | F58: =IF(Relatorio_[[#This Row],[Data_resolução]]=0,"",Relatorio_[[#This Row],[Data_resolução]]) -> 45778.384 | G58: ATENÇÃO - GOLPES - ARANTES ARIMURA ADVOCACIA | H58: Escritório Arantes Arimura Advocacia | I58: Cancelado | J58: Suporte | K58: Brenda | L58: - | M58: 2 | O58: ="INSERT INTO octadesk.stickets ("&$B$1&","&$D$1&","&$F$1&","&$G$1&","&$H$1&","&$I$1&","&$J$1&","&$K$1&","&$L$1&","&$M$1&") values("&IF(B58="","NULL","'"&B58&"'")&",'"&TEXT(D58,"aaaa-mm-dd hh:mm:ss")&"',"&IF(E58="","NULL","'"&TEXT(E58,"aaaa-mm-dd hh:mm:ss")&"'")&","&IF(G58="","NULL","'"&G58&"'")&","&IF(H58="","NULL","'"&H58&"'")&","&IF(I58="","NULL","'"&I58&"'")&","&IF(J58="","NULL","'"&J58&"'")&","&IF(K58="","NULL","'"&K58&"'")&","&IF(L58="","NULL","'"&L58&"'")&","&IF(M58="","NULL","'"&M58&"'")&");" -> INSERT INTO octadesk.stickets (ticket,Data_entrada,Data_resolucao,Titulo_ticket,Usuario_criador_ticket,Status,Grupo_responsavel,Responsavel_ticket,Tags_ticket,Total_de_interacoes) values('193196','2025-04-30 19:19:10','2025-05-01 09:13:23','ATENÇÃO - GOLPES - ARANTES ARIMURA ADVOCACIA','Escritório Arantes Arimura Advocacia','Cancelado','Suporte','Brenda','-','2');
B59: 193197 | C59: =IFERROR(VLOOKUP(Relatorio_[[#This Row],[ticket]],Base!A:A,1,0),"-") -> 193197 | D59: 45778.494 | E59: 45778.587 | F59: =IF(Relatorio_[[#This Row],[Data_resolução]]=0,"",Relatorio_[[#This Row],[Data_resolução]]) -> 45778.587 | G59: Sua conta do WhatsApp Business está violando a política | H59: Facebook | I59: Resolvido | J59: Suporte | K59: Suporte | L59: - | M59: 2 | O59: ="INSERT INTO octadesk.stickets ("&$B$1&","&$D$1&","&$F$1&","&$G$1&","&$H$1&","&$I$1&","&$J$1&","&$K$1&","&$L$1&","&$M$1&") values("&IF(B59="","NULL","'"&B59&"'")&",'"&TEXT(D59,"aaaa-mm-dd hh:mm:ss")&"',"&IF(E59="","NULL","'"&TEXT(E59,"aaaa-mm-dd hh:mm:ss")&"'")&","&IF(G59="","NULL","'"&G59&"'")&","&IF(H59="","NULL","'"&H59&"'")&","&IF(I59="","NULL","'"&I59&"'")&","&IF(J59="","NULL","'"&J59&"'")&","&IF(K59="","NULL","'"&K59&"'")&","&IF(L59="","NULL","'"&L59&"'")&","&IF(M59="","NULL","'"&M59&"'")&");" -> INSERT INTO octadesk.stickets (ticket,Data_entrada,Data_resolucao,Titulo_ticket,Usuario_criador_ticket,Status,Grupo_responsavel,Responsavel_ticket,Tags_ticket,Total_de_interacoes) values('193197','2025-05-01 11:50:42','2025-05-01 14:05:27','Sua conta do WhatsApp Business está violando a política','Facebook','Resolvido','Suporte','Suporte','-','2');
B60: 193198 | C60: =IFERROR(VLOOKUP(Relatorio_[[#This Row],[ticket]],Base!A:A,1,0),"-") -> 193198 | D60: 45778.586 | E60: 45778.587 | F60: =IF(Relatorio_[[#This Row],[Data_resolução]]=0,"",Relatorio_[[#This Row],[Data_resolução]]) -> 45778.587 | G60: Sua conta do WhatsApp Business está violando a política | H60: Brenda | I60: Resolvido | J60: Suporte | K60: Brenda | L60: violação_preventiva_sem_sucesso | M60: 2 | O60: ="INSERT INTO octadesk.stickets ("&$B$1&","&$D$1&","&$F$1&","&$G$1&","&$H$1&","&$I$1&","&$J$1&","&$K$1&","&$L$1&","&$M$1&") values("&IF(B60="","NULL","'"&B60&"'")&",'"&TEXT(D60,"aaaa-mm-dd hh:mm:ss")&"',"&IF(E60="","NULL","'"&TEXT(E60,"aaaa-mm-dd hh:mm:ss")&"'")&","&IF(G60="","NULL","'"&G60&"'")&","&IF(H60="","NULL","'"&H60&"'")&","&IF(I60="","NULL","'"&I60&"'")&","&IF(J60="","NULL","'"&J60&"'")&","&IF(K60="","NULL","'"&K60&"'")&","&IF(L60="","NULL","'"&L60&"'")&","&IF(M60="","NULL","'"&M60&"'")&");" -> INSERT INTO octadesk.stickets (ticket,Data_entrada,Data_resolucao,Titulo_ticket,Usuario_criador_ticket,Status,Grupo_responsavel,Responsavel_ticket,Tags_ticket,Total_de_interacoes) values('193198','2025-05-01 14:03:25','2025-05-01 14:05:53','Sua conta do WhatsApp Business está violando a política','Brenda','Resolvido','Suporte','Brenda','violação_preventiva_sem_sucesso','2');
B61: 193199 | C61: =IFERROR(VLOOKUP(Relatorio_[[#This Row],[ticket]],Base!A:A,1,0),"-") -> 193199 | D61: 45778.594 | E61: 45778.684 | F61: =IF(Relatorio_[[#This Row],[Data_resolução]]=0,"",Relatorio_[[#This Row],[Data_resolução]]) -> 45778.684 | G61: ATENÇÃO - INSTABILIDADE CANAIS DE ATENDIMENTO | H61: Escritório Arantes Arimura Advocacia | I61: Cancelado | J61: Suporte | K61: Brenda | L61: - | M61: 2 | O61: ="INSERT INTO octadesk.stickets ("&$B$1&","&$D$1&","&$F$1&","&$G$1&","&$H$1&","&$I$1&","&$J$1&","&$K$1&","&$L$1&","&$M$1&") values("&IF(B61="","NULL","'"&B61&"'")&",'"&TEXT(D61,"aaaa-mm-dd hh:mm:ss")&"',"&IF(E61="","NULL","'"&TEXT(E61,"aaaa-mm-dd hh:mm:ss")&"'")&","&IF(G61="","NULL","'"&G61&"'")&","&IF(H61="","NULL","'"&H61&"'")&","&IF(I61="","NULL","'"&I61&"'")&","&IF(J61="","NULL","'"&J61&"'")&","&IF(K61="","NULL","'"&K61&"'")&","&IF(L61="","NULL","'"&L61&"'")&","&IF(M61="","NULL","'"&M61&"'")&");" -> INSERT INTO octadesk.stickets (ticket,Data_entrada,Data_resolucao,Titulo_ticket,Usuario_criador_ticket,Status,Grupo_responsavel,Responsavel_ticket,Tags_ticket,Total_de_interacoes) values('193199','2025-05-01 14:15:43','2025-05-01 16:24:57','ATENÇÃO - INSTABILIDADE CANAIS DE ATENDIMENTO','Escritório Arantes Arimura Advocacia','Cancelado','Suporte','Brenda','-','2');
B62: 193200 | C62: =IFERROR(VLOOKUP(Relatorio_[[#This Row],[ticket]],Base!A:A,1,0),"-") -> 193200 | D62: 45778.595 | E62: 45779.37 | F62: =IF(Relatorio_[[#This Row],[Data_resolução]]=0,"",Relatorio_[[#This Row],[Data_resolução]]) -> 45779.37 | G62: Nós encontramos ThinkCentre ... que você pode gostar... | H62: Lenovo Brasil | I62: Cancelado | J62: Financeiro | L62: - | M62: 2 | O62: ="INSERT INTO octadesk.stickets ("&$B$1&","&$D$1&","&$F$1&","&$G$1&","&$H$1&","&$I$1&","&$J$1&","&$K$1&","&$L$1&","&$M$1&") values("&IF(B62="","NULL","'"&B62&"'")&",'"&TEXT(D62,"aaaa-mm-dd hh:mm:ss")&"',"&IF(E62="","NULL","'"&TEXT(E62,"aaaa-mm-dd hh:mm:ss")&"'")&","&IF(G62="","NULL","'"&G62&"'")&","&IF(H62="","NULL","'"&H62&"'")&","&IF(I62="","NULL","'"&I62&"'")&","&IF(J62="","NULL","'"&J62&"'")&","&IF(K62="","NULL","'"&K62&"'")&","&IF(L62="","NULL","'"&L62&"'")&","&IF(M62="","NULL","'"&M62&"'")&");" -> INSERT INTO octadesk.stickets (ticket,Data_entrada,Data_resolucao,Titulo_ticket,Usuario_criador_ticket,Status,Grupo_responsavel,Responsavel_ticket,Tags_ticket,Total_de_interacoes) values('193200','2025-05-01 14:17:02','2025-05-02 08:52:38','Nós encontramos ThinkCentre ... que você pode gostar...','Lenovo Brasil','Cancelado','Financeiro',NULL,'-','2');
B63: 193201 | C63: =IFERROR(VLOOKUP(Relatorio_[[#This Row],[ticket]],Base!A:A,1,0),"-") -> 193201 | D63: 45778.602 | E63: 45778.73 | F63: =IF(Relatorio_[[#This Row],[Data_resolução]]=0,"",Relatorio_[[#This Row],[Data_resolução]]) -> 45778.73 | G63: Sua conta do WhatsApp Business está violando a política | H63: Facebook | I63: Resolvido | J63: Suporte | K63: Suporte | L63: - | M63: 2 | O63: ="INSERT INTO octadesk.stickets ("&$B$1&","&$D$1&","&$F$1&","&$G$1&","&$H$1&","&$I$1&","&$J$1&","&$K$1&","&$L$1&","&$M$1&") values("&IF(B63="","NULL","'"&B63&"'")&",'"&TEXT(D63,"aaaa-mm-dd hh:mm:ss")&"',"&IF(E63="","NULL","'"&TEXT(E63,"aaaa-mm-dd hh:mm:ss")&"'")&","&IF(G63="","NULL","'"&G63&"'")&","&IF(H63="","NULL","'"&H63&"'")&","&IF(I63="","NULL","'"&I63&"'")&","&IF(J63="","NULL","'"&J63&"'")&","&IF(K63="","NULL","'"&K63&"'")&","&IF(L63="","NULL","'"&L63&"'")&","&IF(M63="","NULL","'"&M63&"'")&");" -> INSERT INTO octadesk.stickets (ticket,Data_entrada,Data_resolucao,Titulo_ticket,Usuario_criador_ticket,Status,Grupo_responsavel,Responsavel_ticket,Tags_ticket,Total_de_interacoes) values('193201','2025-05-01 14:26:17','2025-05-01 17:30:52','Sua conta do WhatsApp Business está violando a política','Facebook','Resolvido','Suporte','Suporte','-','2');
B64: 193202 | C64: =IFERROR(VLOOKUP(Relatorio_[[#This Row],[ticket]],Base!A:A,1,0),"-") -> 193202 | D64: 45778.664 | E64: 45778.727 | F64: =IF(Relatorio_[[#This Row],[Data_resolução]]=0,"",Relatorio_[[#This Row],[Data_resolução]]) -> 45778.727 | G64: Sua conta do WhatsApp Business está violando a política | H64: Facebook | I64: Resolvido | J64: Suporte | K64: Suporte | L64: - | M64: 2 | O64: ="INSERT INTO octadesk.stickets ("&$B$1&","&$D$1&","&$F$1&","&$G$1&","&$H$1&","&$I$1&","&$J$1&","&$K$1&","&$L$1&","&$M$1&") values("&IF(B64="","NULL","'"&B64&"'")&",'"&TEXT(D64,"aaaa-mm-dd hh:mm:ss")&"',"&IF(E64="","NULL","'"&TEXT(E64,"aaaa-mm-dd hh:mm:ss")&"'")&","&IF(G64="","NULL","'"&G64&"'")&","&IF(H64="","NULL","'"&H64&"'")&","&IF(I64="","NULL","'"&I64&"'")&","&IF(J64="","NULL","'"&J64&"'")&","&IF(K64="","NULL","'"&K64&"'")&","&IF(L64="","NULL","'"&L64&"'")&","&IF(M64="","NULL","'"&M64&"'")&");" -> INSERT INTO octadesk.stickets (ticket,Data_entrada,Data_resolucao,Titulo_ticket,Usuario_criador_ticket,Status,Grupo_responsavel,Responsavel_ticket,Tags_ticket,Total_de_interacoes) values('193202','2025-05-01 15:56:12','2025-05-01 17:26:47','Sua conta do WhatsApp Business está violando a política','Facebook','Resolvido','Suporte','Suporte','-','2');
B65: 193203 | C65: =IFERROR(VLOOKUP(Relatorio_[[#This Row],[ticket]],Base!A:A,1,0),"-") -> 193203 | D65: 45778.686 | E65: 45778.723 | F65: =IF(Relatorio_[[#This Row],[Data_resolução]]=0,"",Relatorio_[[#This Row],[Data_resolução]]) -> 45778.723 | G65: Sua conta do WhatsApp Business está violando a política | H65: Facebook | I65: Resolvido | J65: Suporte | K65: Suporte | L65: - | M65: 2 | O65: ="INSERT INTO octadesk.stickets ("&$B$1&","&$D$1&","&$F$1&","&$G$1&","&$H$1&","&$I$1&","&$J$1&","&$K$1&","&$L$1&","&$M$1&") values("&IF(B64="","NULL","'"&B64&"'")&",'"&TEXT(D64,"aaaa-mm-dd hh:mm:ss")&"',"&IF(E64="","NULL","'"&TEXT(E64,"aaaa-mm-dd hh:mm:ss")&"'")&","&IF(G64="","NULL","'"&G64&"'")&","&IF(H64="","NULL","'"&H64&"'")&","&IF(I64="","NULL","'"&I64&"'")&","&IF(J64="","NULL","'"&J64&"'")&","&IF(K64="","NULL","'"&K64&"'")&","&IF(L64="","NULL","'"&L64&"'")&","&IF(M64="","NULL","'"&M64&"'")&");" -> INSERT INTO octadesk.stickets (ticket,Data_entrada,Data_resolucao,Titulo_ticket,Usuario_criador_ticket,Status,Grupo_responsavel,Responsavel_ticket,Tags_ticket,Total_de_interacoes) values('193202','2025-05-01 15:56:12','2025-05-01 17:26:47','Sua conta do WhatsApp Business está violando a política','Facebook','Resolvido','Suporte','Suporte','-','2');
B66: 193204 | C66: =IFERROR(VLOOKUP(Relatorio_[[#This Row],[ticket]],Base!A:A,1,0),"-") -> 193204 | D66: 45778.686 | E66: 45778.693 | F66: =IF(Relatorio_[[#This Row],[Data_resolução]]=0,"",Relatorio_[[#This Row],[Data_resolução]]) -> 45778.693 | G66: Sua conta do WhatsApp Business está violando a política | H66: Facebook | I66: Resolvido | J66: Suporte | K66: Suporte | L66: - | M66: 2 | O66: ="INSERT INTO octadesk.stickets ("&$B$1&","&$D$1&","&$F$1&","&$G$1&","&$H$1&","&$I$1&","&$J$1&","&$K$1&","&$L$1&","&$M$1&") values("&IF(B65="","NULL","'"&B65&"'")&",'"&TEXT(D65,"aaaa-mm-dd hh:mm:ss")&"',"&IF(E65="","NULL","'"&TEXT(E65,"aaaa-mm-dd hh:mm:ss")&"'")&","&IF(G65="","NULL","'"&G65&"'")&","&IF(H65="","NULL","'"&H65&"'")&","&IF(I65="","NULL","'"&I65&"'")&","&IF(J65="","NULL","'"&J65&"'")&","&IF(K65="","NULL","'"&K65&"'")&","&IF(L65="","NULL","'"&L65&"'")&","&IF(M65="","NULL","'"&M65&"'")&");" -> INSERT INTO octadesk.stickets (ticket,Data_entrada,Data_resolucao,Titulo_ticket,Usuario_criador_ticket,Status,Grupo_responsavel,Responsavel_ticket,Tags_ticket,Total_de_interacoes) values('193203','2025-05-01 16:28:22','2025-05-01 17:20:50','Sua conta do WhatsApp Business está violando a política','Facebook','Resolvido','Suporte','Suporte','-','2');
B67: 193205 | C67: =IFERROR(VLOOKUP(Relatorio_[[#This Row],[ticket]],Base!A:A,1,0),"-") -> 193205 | D67: 45778.686 | E67: 45778.694 | F67: =IF(Relatorio_[[#This Row],[Data_resolução]]=0,"",Relatorio_[[#This Row],[Data_resolução]]) -> 45778.694 | G67: Sua conta do WhatsApp Business está violando a política | H67: Facebook | I67: Resolvido | J67: Suporte | K67: Suporte | L67: - | M67: 2 | O67: ="INSERT INTO octadesk.stickets ("&$B$1&","&$D$1&","&$F$1&","&$G$1&","&$H$1&","&$I$1&","&$J$1&","&$K$1&","&$L$1&","&$M$1&") values("&IF(B66="","NULL","'"&B66&"'")&",'"&TEXT(D66,"aaaa-mm-dd hh:mm:ss")&"',"&IF(E66="","NULL","'"&TEXT(E66,"aaaa-mm-dd hh:mm:ss")&"'")&","&IF(G66="","NULL","'"&G66&"'")&","&IF(H66="","NULL","'"&H66&"'")&","&IF(I66="","NULL","'"&I66&"'")&","&IF(J66="","NULL","'"&J66&"'")&","&IF(K66="","NULL","'"&K66&"'")&","&IF(L66="","NULL","'"&L66&"'")&","&IF(M66="","NULL","'"&M66&"'")&");" -> INSERT INTO octadesk.stickets (ticket,Data_entrada,Data_resolucao,Titulo_ticket,Usuario_criador_ticket,Status,Grupo_responsavel,Responsavel_ticket,Tags_ticket,Total_de_interacoes) values('193204','2025-05-01 16:28:29','2025-05-01 16:38:08','Sua conta do WhatsApp Business está violando a política','Facebook','Resolvido','Suporte','Suporte','-','2');
B68: 193206 | C68: =IFERROR(VLOOKUP(Relatorio_[[#This Row],[ticket]],Base!A:A,1,0),"-") -> 193206 | D68: 45778.687 | E68: 45778.688 | F68: =IF(Relatorio_[[#This Row],[Data_resolução]]=0,"",Relatorio_[[#This Row],[Data_resolução]]) -> 45778.688 | G68: Sua conta do WhatsApp Business está violando a política | H68: Brenda | I68: Resolvido | J68: Suporte | K68: Brenda | L68: violação_preventiva_sem_sucesso | M68: 2 | O68: ="INSERT INTO octadesk.stickets ("&$B$1&","&$D$1&","&$F$1&","&$G$1&","&$H$1&","&$I$1&","&$J$1&","&$K$1&","&$L$1&","&$M$1&") values("&IF(B67="","NULL","'"&B67&"'")&",'"&TEXT(D67,"aaaa-mm-dd hh:mm:ss")&"',"&IF(E67="","NULL","'"&TEXT(E67,"aaaa-mm-dd hh:mm:ss")&"'")&","&IF(G67="","NULL","'"&G67&"'")&","&IF(H67="","NULL","'"&H67&"'")&","&IF(I67="","NULL","'"&I67&"'")&","&IF(J67="","NULL","'"&J67&"'")&","&IF(K67="","NULL","'"&K67&"'")&","&IF(L67="","NULL","'"&L67&"'")&","&IF(M67="","NULL","'"&M67&"'")&");" -> INSERT INTO octadesk.stickets (ticket,Data_entrada,Data_resolucao,Titulo_ticket,Usuario_criador_ticket,Status,Grupo_responsavel,Responsavel_ticket,Tags_ticket,Total_de_interacoes) values('193205','2025-05-01 16:28:32','2025-05-01 16:38:45','Sua conta do WhatsApp Business está violando a política','Facebook','Resolvido','Suporte','Suporte','-','2');
B69: 193207 | C69: =IFERROR(VLOOKUP(Relatorio_[[#This Row],[ticket]],Base!A:A,1,0),"-") -> 193207 | D69: 45778.693 | E69: 45778.694 | F69: =IF(Relatorio_[[#This Row],[Data_resolução]]=0,"",Relatorio_[[#This Row],[Data_resolução]]) -> 45778.694 | G69: Sua conta do WhatsApp Business está violando a política | H69: Brenda | I69: Resolvido | J69: Suporte | K69: Brenda | L69: violação_preventiva_sem_sucesso | M69: 2 | O69: ="INSERT INTO octadesk.stickets ("&$B$1&","&$D$1&","&$F$1&","&$G$1&","&$H$1&","&$I$1&","&$J$1&","&$K$1&","&$L$1&","&$M$1&") values("&IF(B68="","NULL","'"&B68&"'")&",'"&TEXT(D68,"aaaa-mm-dd hh:mm:ss")&"',"&IF(E68="","NULL","'"&TEXT(E68,"aaaa-mm-dd hh:mm:ss")&"'")&","&IF(G68="","NULL","'"&G68&"'")&","&IF(H68="","NULL","'"&H68&"'")&","&IF(I68="","NULL","'"&I68&"'")&","&IF(J68="","NULL","'"&J68&"'")&","&IF(K68="","NULL","'"&K68&"'")&","&IF(L68="","NULL","'"&L68&"'")&","&IF(M68="","NULL","'"&M68&"'")&");" -> INSERT INTO octadesk.stickets (ticket,Data_entrada,Data_resolucao,Titulo_ticket,Usuario_criador_ticket,Status,Grupo_responsavel,Responsavel_ticket,Tags_ticket,Total_de_interacoes) values('193206','2025-05-01 16:29:45','2025-05-01 16:30:56','Sua conta do WhatsApp Business está violando a política','Brenda','Resolvido','Suporte','Brenda','violação_preventiva_sem_sucesso','2');
B70: 193208 | C70: =IFERROR(VLOOKUP(Relatorio_[[#This Row],[ticket]],Base!A:A,1,0),"-") -> 193208 | D70: 45778.722 | E70: 45778.723 | F70: =IF(Relatorio_[[#This Row],[Data_resolução]]=0,"",Relatorio_[[#This Row],[Data_resolução]]) -> 45778.723 | G70: Sua conta do WhatsApp Business está violando a política | H70: Brenda | I70: Resolvido | J70: Suporte | K70: Brenda | L70: violação_preventiva_sem_sucesso | M70: 2 | O70: ="INSERT INTO octadesk.stickets ("&$B$1&","&$D$1&","&$F$1&","&$G$1&","&$H$1&","&$I$1&","&$J$1&","&$K$1&","&$L$1&","&$M$1&") values("&IF(B69="","NULL","'"&B69&"'")&",'"&TEXT(D69,"aaaa-mm-dd hh:mm:ss")&"',"&IF(E69="","NULL","'"&TEXT(E69,"aaaa-mm-dd hh:mm:ss")&"'")&","&IF(G69="","NULL","'"&G69&"'")&","&IF(H69="","NULL","'"&H69&"'")&","&IF(I69="","NULL","'"&I69&"'")&","&IF(J69="","NULL","'"&J69&"'")&","&IF(K69="","NULL","'"&K69&"'")&","&IF(L69="","NULL","'"&L69&"'")&","&IF(M69="","NULL","'"&M69&"'")&");" -> INSERT INTO octadesk.stickets (ticket,Data_entrada,Data_resolucao,Titulo_ticket,Usuario_criador_ticket,Status,Grupo_responsavel,Responsavel_ticket,Tags_ticket,Total_de_interacoes) values('193207','2025-05-01 16:37:47','2025-05-01 16:39:14','Sua conta do WhatsApp Business está violando a política','Brenda','Resolvido','Suporte','Brenda','violação_preventiva_sem_sucesso','2');
B71: 193209 | C71: =IFERROR(VLOOKUP(Relatorio_[[#This Row],[ticket]],Base!A:A,1,0),"-") -> 193209 | D71: 45778.724 | E71: 45778.725 | F71: =IF(Relatorio_[[#This Row],[Data_resolução]]=0,"",Relatorio_[[#This Row],[Data_resolução]]) -> 45778.725 | G71: Sua conta do WhatsApp Business está violando a política | H71: Brenda | I71: Resolvido | J71: Suporte | K71: Brenda | L71: violação_preventiva_sem_sucesso | M71: 2 | O71: ="INSERT INTO octadesk.stickets ("&$B$1&","&$D$1&","&$F$1&","&$G$1&","&$H$1&","&$I$1&","&$J$1&","&$K$1&","&$L$1&","&$M$1&") values("&IF(B70="","NULL","'"&B70&"'")&",'"&TEXT(D70,"aaaa-mm-dd hh:mm:ss")&"',"&IF(E70="","NULL","'"&TEXT(E70,"aaaa-mm-dd hh:mm:ss")&"'")&","&IF(G70="","NULL","'"&G70&"'")&","&IF(H70="","NULL","'"&H70&"'")&","&IF(I70="","NULL","'"&I70&"'")&","&IF(J70="","NULL","'"&J70&"'")&","&IF(K70="","NULL","'"&K70&"'")&","&IF(L70="","NULL","'"&L70&"'")&","&IF(M70="","NULL","'"&M70&"'")&");" -> INSERT INTO octadesk.stickets (ticket,Data_entrada,Data_resolucao,Titulo_ticket,Usuario_criador_ticket,Status,Grupo_responsavel,Responsavel_ticket,Tags_ticket,Total_de_interacoes) values('193208','2025-05-01 17:20:03','2025-05-01 17:20:24','Sua conta do WhatsApp Business está violando a política','Brenda','Resolvido','Suporte','Brenda','violação_preventiva_sem_sucesso','2');
B72: 193210 | C72: =IFERROR(VLOOKUP(Relatorio_[[#This Row],[ticket]],Base!A:A,1,0),"-") -> 193210 | D72: 45778.727 | E72: 45778.727 | F72: =IF(Relatorio_[[#This Row],[Data_resolução]]=0,"",Relatorio_[[#This Row],[Data_resolução]]) -> 45778.727 | G72: Sua conta do WhatsApp Business está violando a política | H72: Brenda | I72: Resolvido | J72: Suporte | K72: Brenda | L72: violação_preventiva_sem_sucesso | M72: 2 | O72: ="INSERT INTO octadesk.stickets ("&$B$1&","&$D$1&","&$F$1&","&$G$1&","&$H$1&","&$I$1&","&$J$1&","&$K$1&","&$L$1&","&$M$1&") values("&IF(B71="","NULL","'"&B71&"'")&",'"&TEXT(D71,"aaaa-mm-dd hh:mm:ss")&"',"&IF(E71="","NULL","'"&TEXT(E71,"aaaa-mm-dd hh:mm:ss")&"'")&","&IF(G71="","NULL","'"&G71&"'")&","&IF(H71="","NULL","'"&H71&"'")&","&IF(I71="","NULL","'"&I71&"'")&","&IF(J71="","NULL","'"&J71&"'")&","&IF(K71="","NULL","'"&K71&"'")&","&IF(L71="","NULL","'"&L71&"'")&","&IF(M71="","NULL","'"&M71&"'")&");" -> INSERT INTO octadesk.stickets (ticket,Data_entrada,Data_resolucao,Titulo_ticket,Usuario_criador_ticket,Status,Grupo_responsavel,Responsavel_ticket,Tags_ticket,Total_de_interacoes) values('193209','2025-05-01 17:23:07','2025-05-01 17:23:41','Sua conta do WhatsApp Business está violando a política','Brenda','Resolvido','Suporte','Brenda','violação_preventiva_sem_sucesso','2');
B73: 193211 | C73: =IFERROR(VLOOKUP(Relatorio_[[#This Row],[ticket]],Base!A:A,1,0),"-") -> 193211 | D73: 45778.728 | E73: 45778.728 | F73: =IF(Relatorio_[[#This Row],[Data_resolução]]=0,"",Relatorio_[[#This Row],[Data_resolução]]) -> 45778.728 | G73: Sua conta do WhatsApp Business está violando a política | H73: Brenda | I73: Resolvido | J73: Suporte | K73: Brenda | L73: violação_preventiva_sem_sucesso | M73: 2 | O73: ="INSERT INTO octadesk.stickets ("&$B$1&","&$D$1&","&$F$1&","&$G$1&","&$H$1&","&$I$1&","&$J$1&","&$K$1&","&$L$1&","&$M$1&") values("&IF(B72="","NULL","'"&B72&"'")&",'"&TEXT(D72,"aaaa-mm-dd hh:mm:ss")&"',"&IF(E72="","NULL","'"&TEXT(E72,"aaaa-mm-dd hh:mm:ss")&"'")&","&IF(G72="","NULL","'"&G72&"'")&","&IF(H72="","NULL","'"&H72&"'")&","&IF(I72="","NULL","'"&I72&"'")&","&IF(J72="","NULL","'"&J72&"'")&","&IF(K72="","NULL","'"&K72&"'")&","&IF(L72="","NULL","'"&L72&"'")&","&IF(M72="","NULL","'"&M72&"'")&");" -> INSERT INTO octadesk.stickets (ticket,Data_entrada,Data_resolucao,Titulo_ticket,Usuario_criador_ticket,Status,Grupo_responsavel,Responsavel_ticket,Tags_ticket,Total_de_interacoes) values('193210','2025-05-01 17:26:14','2025-05-01 17:26:30','Sua conta do WhatsApp Business está violando a política','Brenda','Resolvido','Suporte','Brenda','violação_preventiva_sem_sucesso','2');
B74: 193212 | C74: =IFERROR(VLOOKUP(Relatorio_[[#This Row],[ticket]],Base!A:A,1,0),"-") -> 193212 | D74: 45778.748 | E74: 45779.517 | F74: =IF(Relatorio_[[#This Row],[Data_resolução]]=0,"",Relatorio_[[#This Row],[Data_resolução]]) -> 45779.517 | G74: Sua conta do WhatsApp Business está violando a política | H74: Facebook | I74: Resolvido | J74: Suporte | K74: Suporte | L74: - | M74: 2 | O74: ="INSERT INTO octadesk.stickets ("&$B$1&","&$D$1&","&$F$1&","&$G$1&","&$H$1&","&$I$1&","&$J$1&","&$K$1&","&$L$1&","&$M$1&") values("&IF(B73="","NULL","'"&B73&"'")&",'"&TEXT(D73,"aaaa-mm-dd hh:mm:ss")&"',"&IF(E73="","NULL","'"&TEXT(E73,"aaaa-mm-dd hh:mm:ss")&"'")&","&IF(G73="","NULL","'"&G73&"'")&","&IF(H73="","NULL","'"&H73&"'")&","&IF(I73="","NULL","'"&I73&"'")&","&IF(J73="","NULL","'"&J73&"'")&","&IF(K73="","NULL","'"&K73&"'")&","&IF(L73="","NULL","'"&L73&"'")&","&IF(M73="","NULL","'"&M73&"'")&");" -> INSERT INTO octadesk.stickets (ticket,Data_entrada,Data_resolucao,Titulo_ticket,Usuario_criador_ticket,Status,Grupo_responsavel,Responsavel_ticket,Tags_ticket,Total_de_interacoes) values('193211','2025-05-01 17:28:30','2025-05-01 17:29:01','Sua conta do WhatsApp Business está violando a política','Brenda','Resolvido','Suporte','Brenda','violação_preventiva_sem_sucesso','2');
B75: 193213 | C75: =IFERROR(VLOOKUP(Relatorio_[[#This Row],[ticket]],Base!A:A,1,0),"-") -> 193213 | D75: 45778.937 | E75: 45779.339 | F75: =IF(Relatorio_[[#This Row],[Data_resolução]]=0,"",Relatorio_[[#This Row],[Data_resolução]]) -> 45779.339 | G75: Sua conta do WhatsApp Business está violando a política | H75: Facebook | I75: Resolvido | J75: Suporte | K75: Suporte | L75: - | M75: 2 | O75: ="INSERT INTO octadesk.stickets ("&$B$1&","&$D$1&","&$F$1&","&$G$1&","&$H$1&","&$I$1&","&$J$1&","&$K$1&","&$L$1&","&$M$1&") values("&IF(B74="","NULL","'"&B74&"'")&",'"&TEXT(D74,"aaaa-mm-dd hh:mm:ss")&"',"&IF(E74="","NULL","'"&TEXT(E74,"aaaa-mm-dd hh:mm:ss")&"'")&","&IF(G74="","NULL","'"&G74&"'")&","&IF(H74="","NULL","'"&H74&"'")&","&IF(I74="","NULL","'"&I74&"'")&","&IF(J74="","NULL","'"&J74&"'")&","&IF(K74="","NULL","'"&K74&"'")&","&IF(L74="","NULL","'"&L74&"'")&","&IF(M74="","NULL","'"&M74&"'")&");" -> INSERT INTO octadesk.stickets (ticket,Data_entrada,Data_resolucao,Titulo_ticket,Usuario_criador_ticket,Status,Grupo_responsavel,Responsavel_ticket,Tags_ticket,Total_de_interacoes) values('193212','2025-05-01 17:57:20','2025-05-02 12:24:35','Sua conta do WhatsApp Business está violando a política','Facebook','Resolvido','Suporte','Suporte','-','2');
B76: 193214 | C76: =IFERROR(VLOOKUP(Relatorio_[[#This Row],[ticket]],Base!A:A,1,0),"-") -> 193214 | D76: 45779.087 | E76: 45779.337 | F76: =IF(Relatorio_[[#This Row],[Data_resolução]]=0,"",Relatorio_[[#This Row],[Data_resolução]]) -> 45779.337 | G76: Suporte , Seu Boleto Digital Amil já chegou na sua caixa de entrada - 370430122 | H76: Amil | I76: Cancelado | J76: Suporte | K76: Brenda | L76: - | M76: 2 | O76: ="INSERT INTO octadesk.stickets ("&$B$1&","&$D$1&","&$F$1&","&$G$1&","&$H$1&","&$I$1&","&$J$1&","&$K$1&","&$L$1&","&$M$1&") values("&IF(B75="","NULL","'"&B75&"'")&",'"&TEXT(D75,"aaaa-mm-dd hh:mm:ss")&"',"&IF(E75="","NULL","'"&TEXT(E75,"aaaa-mm-dd hh:mm:ss")&"'")&","&IF(G75="","NULL","'"&G75&"'")&","&IF(H75="","NULL","'"&H75&"'")&","&IF(I75="","NULL","'"&I75&"'")&","&IF(J75="","NULL","'"&J75&"'")&","&IF(K75="","NULL","'"&K75&"'")&","&IF(L75="","NULL","'"&L75&"'")&","&IF(M75="","NULL","'"&M75&"'")&");" -> INSERT INTO octadesk.stickets (ticket,Data_entrada,Data_resolucao,Titulo_ticket,Usuario_criador_ticket,Status,Grupo_responsavel,Responsavel_ticket,Tags_ticket,Total_de_interacoes) values('193213','2025-05-01 22:29:21','2025-05-02 08:07:48','Sua conta do WhatsApp Business está violando a política','Facebook','Resolvido','Suporte','Suporte','-','2');
... B84: 193222 | C84: =IFERROR(VLOOKUP(Relatorio_[[#This Row],[ticket]],Base!A:A,1,0),"-") -> 193222 | D84: 45779.393 | E84: 45779.543 | F84: =IF(Relatorio_[[#This Row],[Data_resolução]]=0,"",Relatorio_[[#This Row],[Data_resolução]]) -> 45779.543 | G84: Sua conta do WhatsApp Business está violando a política | H84: Facebook | I84: Resolvido | J84: Suporte | K84: Suporte | L84: - | M84: 2 | O84: ="INSERT INTO octadesk.stickets ("&$B$1&","&$D$1&","&$F$1&","&$G$1&","&$H$1&","&$I$1&","&$J$1&","&$K$1&","&$L$1&","&$M$1&") values("&IF(B83="","NULL","'"&B83&"'")&",'"&TEXT(D83,"aaaa-mm-dd hh:mm:ss")&"',"&IF(E83="","NULL","'"&TEXT(E83,"aaaa-mm-dd hh:mm:ss")&"'")&","&IF(G83="","NULL","'"&G83&"'")&","&IF(H83="","NULL","'"&H83&"'")&","&IF(I83="","NULL","'"&I83&"'")&","&IF(J83="","NULL","'"&J83&"'")&","&IF(K83="","NULL","'"&K83&"'")&","&IF(L83="","NULL","'"&L83&"'")&","&IF(M83="","NULL","'"&M83&"'")&");" -> INSERT INTO octadesk.stickets (ticket,Data_entrada,Data_resolucao,Titulo_ticket,Usuario_criador_ticket,Status,Grupo_responsavel,Responsavel_ticket,Tags_ticket,Total_de_interacoes) values('193221','2025-05-02 09:20:10','2025-05-02 12:22:02','Olá atendimento, aqui está nossa conversa! #99929618','atendimento','Cancelado','Suporte','Brenda','-','2');
B85: 193223 | C85: =IFERROR(VLOOKUP(Relatorio_[[#This Row],[ticket]],Base!A:A,1,0),"-") -> 193223 | D85: 45779.401 | F85: =IF(Relatorio_[[#This Row],[Data_resolução]]=0,"",Relatorio_[[#This Row],[Data_resolução]]) | G85: [ME] [TRAY] Bots não executados em conversas | H85: Gustavo Bernardo | I85: Em andamento | J85: N2 | K85: Juan C. | L85: problema-envio-email, 193254 | M85: 6 | O85: ="INSERT INTO octadesk.stickets ("&$B$1&","&$D$1&","&$F$1&","&$G$1&","&$H$1&","&$I$1&","&$J$1&","&$K$1&","&$L$1&","&$M$1&") values("&IF(B84="","NULL","'"&B84&"'")&",'"&TEXT(D84,"aaaa-mm-dd hh:mm:ss")&"',"&IF(E84="","NULL","'"&TEXT(E84,"aaaa-mm-dd hh:mm:ss")&"'")&","&IF(G84="","NULL","'"&G84&"'")&","&IF(H84="","NULL","'"&H84&"'")&","&IF(I84="","NULL","'"&I84&"'")&","&IF(J84="","NULL","'"&J84&"'")&","&IF(K84="","NULL","'"&K84&"'")&","&IF(L84="","NULL","'"&L84&"'")&","&IF(M84="","NULL","'"&M84&"'")&");" -> INSERT INTO octadesk.stickets (ticket,Data_entrada,Data_resolucao,Titulo_ticket,Usuario_criador_ticket,Status,Grupo_responsavel,Responsavel_ticket,Tags_ticket,Total_de_interacoes) values('193222','2025-05-02 09:25:57','2025-05-02 13:02:26','Sua conta do WhatsApp Business está violando a política','Facebook','Resolvido','Suporte','Suporte','-','2');
B86: 193224 | C86: =IFERROR(VLOOKUP(Relatorio_[[#This Row],[ticket]],Base!A:A,1,0),"-") -> 193224 | D86: 45779.403 | E86: 45779.416 | F86: =IF(Relatorio_[[#This Row],[Data_resolução]]=0,"",Relatorio_[[#This Row],[Data_resolução]]) -> 45779.416 | G86: Atribuição de conversas - Help | H86: Brenda | I86: Cancelado | J86: N2 | L86: problema-envio-email | M86: 4 | O86: ="INSERT INTO octadesk.stickets ("&$B$1&","&$D$1&","&$F$1&","&$G$1&","&$H$1&","&$I$1&","&$J$1&","&$K$1&","&$L$1&","&$M$1&") values("&IF(B85="","NULL","'"&B85&"'")&",'"&TEXT(D85,"aaaa-mm-dd hh:mm:ss")&"',"&IF(E85="","NULL","'"&TEXT(E85,"aaaa-mm-dd hh:mm:ss")&"'")&","&IF(G85="","NULL","'"&G85&"'")&","&IF(H85="","NULL","'"&H85&"'")&","&IF(I85="","NULL","'"&I85&"'")&","&IF(J85="","NULL","'"&J85&"'")&","&IF(K85="","NULL","'"&K85&"'")&","&IF(L85="","NULL","'"&L85&"'")&","&IF(M85="","NULL","'"&M85&"'")&");" -> INSERT INTO octadesk.stickets (ticket,Data_entrada,Data_resolucao,Titulo_ticket,Usuario_criador_ticket,Status,Grupo_responsavel,Responsavel_ticket,Tags_ticket,Total_de_interacoes) values('193223','2025-05-02 09:38:01',NULL,'[ME] [TRAY] Bots não executados em conversas','Gustavo Bernardo','Em andamento','N2','Juan C.','problema-envio-email, 193254','6');
B87: 193225 | C87: =IFERROR(VLOOKUP(Relatorio_[[#This Row],[ticket]],Base!A:A,1,0),"-") -> 193225 | D87: 45779.408 | F87: =IF(Relatorio_[[#This Row],[Data_resolução]]=0,"",Relatorio_[[#This Row],[Data_resolução]]) | G87: Créditos expirados | H87: Jéssica | I87: Novo | J87: CS | K87: Lincon L. | L87: - | M87: 8 | O87: ="INSERT INTO octadesk.stickets ("&$B$1&","&$D$1&","&$F$1&","&$G$1&","&$H$1&","&$I$1&","&$J$1&","&$K$1&","&$L$1&","&$M$1&") values("&IF(B86="","NULL","'"&B86&"'")&",'"&TEXT(D86,"aaaa-mm-dd hh:mm:ss")&"',"&IF(E86="","NULL","'"&TEXT(E86,"aaaa-mm-dd hh:mm:ss")&"'")&","&IF(G86="","NULL","'"&G86&"'")&","&IF(H86="","NULL","'"&H86&"'")&","&IF(I86="","NULL","'"&I86&"'")&","&IF(J86="","NULL","'"&J86&"'")&","&IF(K86="","NULL","'"&K86&"'")&","&IF(L86="","NULL","'"&L86&"'")&","&IF(M86="","NULL","'"&M86&"'")&");" -> INSERT INTO octadesk.stickets (ticket,Data_entrada,Data_resolucao,Titulo_ticket,Usuario_criador_ticket,Status,Grupo_responsavel,Responsavel_ticket,Tags_ticket,Total_de_interacoes) values('193224','2025-05-02 09:40:01','2025-05-02 09:58:41','Atribuição de conversas - Help','Brenda','Cancelado','N2',NULL,'problema-envio-email','4');
B88: 193226 | C88: =IFERROR(VLOOKUP(Relatorio_[[#This Row],[ticket]],Base!A:A,1,0),"-") -> 193226 | D88: 45779.409 | F88: =IF(Relatorio_[[#This Row],[Data_resolução]]=0,"",Relatorio_[[#This Row],[Data_resolução]]) | G88: Problema na atribuição dos ticket's - plequipamentos | H88: Thais Fonseca | I88: Em andamento | J88: N2 | K88: Lucas Muniz | L88: problema-envio-email, 193194 | M88: 4 | O88: ="INSERT INTO octadesk.stickets ("&$B$1&","&$D$1&","&$F$1&","&$G$1&","&$H$1&","&$I$1&","&$J$1&","&$K$1&","&$L$1&","&$M$1&") values("&IF(B87="","NULL","'"&B87&"'")&",'"&TEXT(D87,"aaaa-mm-dd hh:mm:ss")&"',"&IF(E87="","NULL","'"&TEXT(E87,"aaaa-mm-dd hh:mm:ss")&"'")&","&IF(G87="","NULL","'"&G87&"'")&","&IF(H87="","NULL","'"&H87&"'")&","&IF(I87="","NULL","'"&I87&"'")&","&IF(J87="","NULL","'"&J87&"'")&","&IF(K87="","NULL","'"&K87&"'")&","&IF(L87="","NULL","'"&L87&"'")&","&IF(M87="","NULL","'"&M87&"'")&");" -> INSERT INTO octadesk.stickets (ticket,Data_entrada,Data_resolucao,Titulo_ticket,Usuario_criador_ticket,Status,Grupo_responsavel,Responsavel_ticket,Tags_ticket,Total_de_interacoes) values('193225','2025-05-02 09:47:32',NULL,'Créditos expirados','Jéssica','Novo','CS','Lincon L.','-','8');
B89: 193227 | C89: =IFERROR(VLOOKUP(Relatorio_[[#This Row],[ticket]],Base!A:A,1,0),"-") -> 193227 | D89: 45779.418 | F89: =IF(Relatorio_[[#This Row],[Data_resolução]]=0,"",Relatorio_[[#This Row],[Data_resolução]]) | G89: Emissão de NF - Share Servicos | H89: Silvia S. | I89: Novo | J89: OTC | L89: - | M89: 1 | O89: ="INSERT INTO octadesk.stickets ("&$B$1&","&$D$1&","&$F$1&","&$G$1&","&$H$1&","&$I$1&","&$J$1&","&$K$1&","&$L$1&","&$M$1&") values("&IF(B88="","NULL","'"&B88&"'")&",'"&TEXT(D88,"aaaa-mm-dd hh:mm:ss")&"',"&IF(E88="","NULL","'"&TEXT(E88,"aaaa-mm-dd hh:mm:ss")&"'")&","&IF(G88="","NULL","'"&G88&"'")&","&IF(H88="","NULL","'"&H88&"'")&","&IF(I88="","NULL","'"&I88&"'")&","&IF(J88="","NULL","'"&J88&"'")&","&IF(K88="","NULL","'"&K88&"'")&","&IF(L88="","NULL","'"&L88&"'")&","&IF(M88="","NULL","'"&M88&"'")&");" -> INSERT INTO octadesk.stickets (ticket,Data_entrada,Data_resolucao,Titulo_ticket,Usuario_criador_ticket,Status,Grupo_responsavel,Responsavel_ticket,Tags_ticket,Total_de_interacoes) values('193226','2025-05-02 09:49:31',NULL,'Problema na atribuição dos ticket's - plequipamentos','Thais Fonseca','Em andamento','N2','Lucas Muniz','problema-envio-email, 193194','4');
B90: 193228 | C90: =IFERROR(VLOOKUP(Relatorio_[[#This Row],[ticket]],Base!A:A,1,0),"-") -> 193228 | D90: 45779.428 | F90: =IF(Relatorio_[[#This Row],[Data_resolução]]=0,"",Relatorio_[[#This Row],[Data_resolução]]) | G90: Erro na atribuição do bot | H90: Maila Ferreira | I90: Novo | J90: N2 | L90: chat | M90: 5 | O90: ="INSERT INTO octadesk.stickets ("&$B$1&","&$D$1&","&$F$1&","&$G$1&","&$H$1&","&$I$1&","&$J$1&","&$K$1&","&$L$1&","&$M$1&") values("&IF(B89="","NULL","'"&B89&"'")&",'"&TEXT(D89,"aaaa-mm-dd hh:mm:ss")&"',"&IF(E89="","NULL","'"&TEXT(E89,"aaaa-mm-dd hh:mm:ss")&"'")&","&IF(G89="","NULL","'"&G89&"'")&","&IF(H89="","NULL","'"&H89&"'")&","&IF(I89="","NULL","'"&I89&"'")&","&IF(J89="","NULL","'"&J89&"'")&","&IF(K89="","NULL","'"&K89&"'")&","&IF(L89="","NULL","'"&L89&"'")&","&IF(M89="","NULL","'"&M89&"'")&");" -> INSERT INTO octadesk.stickets (ticket,Data_entrada,Data_resolucao,Titulo_ticket,Usuario_criador_ticket,Status,Grupo_responsavel,Responsavel_ticket,Tags_ticket,Total_de_interacoes) values('193227','2025-05-02 10:01:17',NULL,'Emissão de NF - Share Servicos','Silvia S.','Novo','OTC',NULL,'-','1');
B91: 193229 | C91: =IFERROR(VLOOKUP(Relatorio_[[#This Row],[ticket]],Base!A:A,1,0),"-") -> 193229 | D91: 45779.428 | F91: =IF(Relatorio_[[#This Row],[Data_resolução]]=0,"",Relatorio_[[#This Row],[Data_resolução]]) | G91: Nota Cancelada | 172758 | H91: Larissa Godoi | Moura Leite | I91: Em andamento | J91: Financeiro | L91: - | M91: 5 | O91: ="INSERT INTO octadesk.stickets ("&$B$1&","&$D$1&","&$F$1&","&$G$1&","&$H$1&","&$I$1&","&$J$1&","&$K$1&","&$L$1&","&$M$1&") values("&IF(B90="","NULL","'"&B90&"'")&",'"&TEXT(D90,"aaaa-mm-dd hh:mm:ss")&"',"&IF(E90="","NULL","'"&TEXT(E90,"aaaa-mm-dd hh:mm:ss")&"'")&","&IF(G90="","NULL","'"&G90&"'")&","&IF(H90="","NULL","'"&H90&"'")&","&IF(I90="","NULL","'"&I90&"'")&","&IF(J90="","NULL","'"&J90&"'")&","&IF(K90="","NULL","'"&K90&"'")&","&IF(L90="","NULL","'"&L90&"'")&","&IF(M90="","NULL","'"&M90&"'")&");" -> INSERT INTO octadesk.stickets (ticket,Data_entrada,Data_resolucao,Titulo_ticket,Usuario_criador_ticket,Status,Grupo_responsavel,Responsavel_ticket,Tags_ticket,Total_de_interacoes) values('193228','2025-05-02 10:16:01',NULL,'Erro na atribuição do bot','Maila Ferreira','Novo','N2',NULL,'chat','5');
B92: 193230 | C92: =IFERROR(VLOOKUP(Relatorio_[[#This Row],[ticket]],Base!A:A,1,0),"-") -> 193230 | D92: 45779.445 | F92: =IF(Relatorio_[[#This Row],[Data_resolução]]=0,"",Relatorio_[[#This Row],[Data_resolução]]) | G92: Erro ao acessar o ticket - o138412-2b5 | H92: Natan | I92: Pendente | J92: N2 | K92: Lucas Muniz | L92: chat, problema-envio-email, ticket-corrigido | M92: 9 | O92: ="INSERT INTO octadesk.stickets ("&$B$1&","&$D$1&","&$F$1&","&$G$1&","&$H$1&","&$I$1&","&$J$1&","&$K$1&","&$L$1&","&$M$1&") values("&IF(B91="","NULL","'"&B91&"'")&",'"&TEXT(D91,"aaaa-mm-dd hh:mm:ss")&"',"&IF(E91="","NULL","'"&TEXT(E91,"aaaa-mm-dd hh:mm:ss")&"'")&","&IF(G91="","NULL","'"&G91&"'")&","&IF(H91="","NULL","'"&H91&"'")&","&IF(I91="","NULL","'"&I91&"'")&","&IF(J91="","NULL","'"&J91&"'")&","&IF(K91="","NULL","'"&K91&"'")&","&IF(L91="","NULL","'"&L91&"'")&","&IF(M91="","NULL","'"&M91&"'")&");" -> INSERT INTO octadesk.stickets (ticket,Data_entrada,Data_resolucao,Titulo_ticket,Usuario_criador_ticket,Status,Grupo_responsavel,Responsavel_ticket,Tags_ticket,Total_de_interacoes) values('193229','2025-05-02 10:16:33',NULL,'Nota Cancelada | 172758','Larissa Godoi | Moura Leite','Em andamento','Financeiro',NULL,'-','5');
B93: 193231 | C93: =IFERROR(VLOOKUP(Relatorio_[[#This Row],[ticket]],Base!A:A,1,0),"-") -> 193231 | D93: 45779.46 | F93: =IF(Relatorio_[[#This Row],[Data_resolução]]=0,"",Relatorio_[[#This Row],[Data_resolução]]) | G93: Proposta de Solução de Vendas Automatizadas via WhatsApp/Instagram com Integração ERP/CRM - Quiksilver Leblon | H93: Mauro Braga | I93: Novo | J93: Comercial | L93: - | M93: 2 | O93: ="INSERT INTO octadesk.stickets ("&$B$1&","&$D$1&","&$F$1&","&$G$1&","&$H$1&","&$I$1&","&$J$1&","&$K$1&","&$L$1&","&$M$1&") values("&IF(B92="","NULL","'"&B92&"'")&",'"&TEXT(D92,"aaaa-mm-dd hh:mm:ss")&"',"&IF(E92="","NULL","'"&TEXT(E92,"aaaa-mm-dd hh:mm:ss")&"'")&","&IF(G92="","NULL","'"&G92&"'")&","&IF(H92="","NULL","'"&H92&"'")&","&IF(I92="","NULL","'"&I92&"'")&","&IF(J92="","NULL","'"&J92&"'")&","&IF(K92="","NULL","'"&K92&"'")&","&IF(L92="","NULL","'"&L92&"'")&","&IF(M92="","NULL","'"&M92&"'")&");" -> INSERT INTO octadesk.stickets (ticket,Data_entrada,Data_resolucao,Titulo_ticket,Usuario_criador_ticket,Status,Grupo_responsavel,Responsavel_ticket,Tags_ticket,Total_de_interacoes) values('193230','2025-05-02 10:40:05',NULL,'Erro ao acessar o ticket - o138412-2b5','Natan','Pendente','N2','Lucas Muniz','chat, problema-envio-email, ticket-corrigido','9');
B94: 193232 | C94: =IFERROR(VLOOKUP(Relatorio_[[#This Row],[ticket]],Base!A:A,1,0),"-") -> 193232 | D94: 45779.483 | E94: 45779.505 | F94: =IF(Relatorio_[[#This Row],[Data_resolução]]=0,"",Relatorio_[[#This Row],[Data_resolução]]) -> 45779.505 | G94: Olá atendimento, aqui está nossa conversa! #99929634 | H94: atendimento | I94: Cancelado | J94: Suporte | K94: Brenda | L94: - | M94: 2 | O94: ="INSERT INTO octadesk.stickets ("&$B$1&","&$D$1&","&$F$1&","&$G$1&","&$H$1&","&$I$1&","&$J$1&","&$K$1&","&$L$1&","&$M$1&") values("&IF(B93="","NULL","'"&B93&"'")&",'"&TEXT(D93,"aaaa-mm-dd hh:mm:ss")&"',"&IF(E93="","NULL","'"&TEXT(E93,"aaaa-mm-dd hh:mm:ss")&"'")&","&IF(G93="","NULL","'"&G93&"'")&","&IF(H93="","NULL","'"&H93&"'")&","&IF(I93="","NULL","'"&I93&"'")&","&IF(J93="","NULL","'"&J93&"'")&","&IF(K93="","NULL","'"&K93&"'")&","&IF(L93="","NULL","'"&L93&"'")&","&IF(M93="","NULL","'"&M93&"'")&");" -> INSERT INTO octadesk.stickets (ticket,Data_entrada,Data_resolucao,Titulo_ticket,Usuario_criador_ticket,Status,Grupo_responsavel,Responsavel_ticket,Tags_ticket,Total_de_interacoes) values('193231','2025-05-02 11:02:49',NULL,'Proposta de Solução de Vendas Automatizadas via WhatsApp/Instagram com Integração ERP/CRM - Quiksilver Leblon','Mauro Braga','Novo','Comercial',NULL,'-','2');
B95: 193233 | C95: =IFERROR(VLOOKUP(Relatorio_[[#This Row],[ticket]],Base!A:A,1,0),"-") -> 193233 | D95: 45779.483 | E95: 45779.505 | F95: =IF(Relatorio_[[#This Row],[Data_resolução]]=0,"",Relatorio_[[#This Row],[Data_resolução]]) -> 45779.505 | G95: Olá atendimento, aqui está nossa conversa! #99929634 | H95: atendimento | I95: Cancelado | J95: Suporte | K95: Brenda | L95: - | M95: 2 | O95: ="INSERT INTO octadesk.stickets ("&$B$1&","&$D$1&","&$F$1&","&$G$1&","&$H$1&","&$I$1&","&$J$1&","&$K$1&","&$L$1&","&$M$1&") values("&IF(B94="","NULL","'"&B94&"'")&",'"&TEXT(D94,"aaaa-mm-dd hh:mm:ss")&"',"&IF(E94="","NULL","'"&TEXT(E94,"aaaa-mm-dd hh:mm:ss")&"'")&","&IF(G94="","NULL","'"&G94&"'")&","&IF(H94="","NULL","'"&H94&"'")&","&IF(I94="","NULL","'"&I94&"'")&","&IF(J94="","NULL","'"&J94&"'")&","&IF(K94="","NULL","'"&K94&"'")&","&IF(L94="","NULL","'"&L94&"'")&","&IF(M94="","NULL","'"&M94&"'")&");" -> INSERT INTO octadesk.stickets (ticket,Data_entrada,Data_resolucao,Titulo_ticket,Usuario_criador_ticket,Status,Grupo_responsavel,Responsavel_ticket,Tags_ticket,Total_de_interacoes) values('193232','2025-05-02 11:35:37','2025-05-02 12:07:09','Olá atendimento, aqui está nossa conversa! #99929634','atendimento','Cancelado','Suporte','Brenda','-','2');
B96: 193234 | C96: =IFERROR(VLOOKUP(Relatorio_[[#This Row],[ticket]],Base!A:A,1,0),"-") -> 193234 | D96: 45779.501 | E96: 45779.514 | F96: =IF(Relatorio_[[#This Row],[Data_resolução]]=0,"",Relatorio_[[#This Row],[Data_resolução]]) -> 45779.514 | G96: Sua conta do WhatsApp Business está violando a política | H96: Facebook | I96: Resolvido | J96: Suporte | K96: Suporte | L96: - | M96: 2 | O96: ="INSERT INTO octadesk.stickets ("&$B$1&","&$D$1&","&$F$1&","&$G$1&","&$H$1&","&$I$1&","&$J$1&","&$K$1&","&$L$1&","&$M$1&") values("&IF(B95="","NULL","'"&B95&"'")&",'"&TEXT(D95,"aaaa-mm-dd hh:mm:ss")&"',"&IF(E95="","NULL","'"&TEXT(E95,"aaaa-mm-dd hh:mm:ss")&"'")&","&IF(G95="","NULL","'"&G95&"'")&","&IF(H95="","NULL","'"&H95&"'")&","&IF(I95="","NULL","'"&I95&"'")&","&IF(J95="","NULL","'"&J95&"'")&","&IF(K95="","NULL","'"&K95&"'")&","&IF(L95="","NULL","'"&L95&"'")&","&IF(M95="","NULL","'"&M95&"'")&");" -> INSERT INTO octadesk.stickets (ticket,Data_entrada,Data_resolucao,Titulo_ticket,Usuario_criador_ticket,Status,Grupo_responsavel,Responsavel_ticket,Tags_ticket,Total_de_interacoes) values('193233','2025-05-02 11:35:38','2025-05-02 12:07:14','Olá atendimento, aqui está nossa conversa! #99929634','atendimento','Cancelado','Suporte','Brenda','-','2');
B97: 193235 | C97: =IFERROR(VLOOKUP(Relatorio_[[#This Row],[ticket]],Base!A:A,1,0),"-") -> 193235 | D97: 45779.514 | E97: 45779.515 | F97: =IF(Relatorio_[[#This Row],[Data_resolução]]=0,"",Relatorio_[[#This Row],[Data_resolução]]) -> 45779.515 | G97: Sua conta do WhatsApp Business está violando a política | H97: Brenda | I97: Resolvido | J97: Suporte | K97: Brenda | L97: violação_preventiva_sem_sucesso | M97: 2 | O97: ="INSERT INTO octadesk.stickets ("&$B$1&","&$D$1&","&$F$1&","&$G$1&","&$H$1&","&$I$1&","&$J$1&","&$K$1&","&$L$1&","&$M$1&") values("&IF(B96="","NULL","'"&B96&"'")&",'"&TEXT(D96,"aaaa-mm-dd hh:mm:ss")&"',"&IF(E96="","NULL","'"&TEXT(E96,"aaaa-mm-dd hh:mm:ss")&"'")&","&IF(G96="","NULL","'"&G96&"'")&","&IF(H96="","NULL","'"&H96&"'")&","&IF(I96="","NULL","'"&I96&"'")&","&IF(J96="","NULL","'"&J96&"'")&","&IF(K96="","NULL","'"&K96&"'")&","&IF(L96="","NULL","'"&L96&"'")&","&IF(M96="","NULL","'"&M96&"'")&");" -> INSERT INTO octadesk.stickets (ticket,Data_entrada,Data_resolucao,Titulo_ticket,Usuario_criador_ticket,Status,Grupo_responsavel,Responsavel_ticket,Tags_ticket,Total_de_interacoes) values('193234','2025-05-02 12:01:36','2025-05-02 12:20:42','Sua conta do WhatsApp Business está violando a política','Facebook','Resolvido','Suporte','Suporte','-','2');
B98: 193236 | C98: =IFERROR(VLOOKUP(Relatorio_[[#This Row],[ticket]],Base!A:A,1,0),"-") -> 193236 | D98: 45779.517 | E98: 45779.517 | F98: =IF(Relatorio_[[#This Row],[Data_resolução]]=0,"",Relatorio_[[#This Row],[Data_resolução]]) -> 45779.517 | G98: Sua conta do WhatsApp Business está violando a política | H98: Brenda | I98: Resolvido | J98: Suporte | K98: Brenda | L98: violação_preventiva_sem_sucesso | M98: 2 | O98: ="INSERT INTO octadesk.stickets ("&$B$1&","&$D$1&","&$F$1&","&$G$1&","&$H$1&","&$I$1&","&$J$1&","&$K$1&","&$L$1&","&$M$1&") values("&IF(B97="","NULL","'"&B97&"'")&",'"&TEXT(D97,"aaaa-mm-dd hh:mm:ss")&"',"&IF(E97="","NULL","'"&TEXT(E97,"aaaa-mm-dd hh:mm:ss")&"'")&","&IF(G97="","NULL","'"&G97&"'")&","&IF(H97="","NULL","'"&H97&"'")&","&IF(I97="","NULL","'"&I97&"'")&","&IF(J97="","NULL","'"&J97&"'")&","&IF(K97="","NULL","'"&K97&"'")&","&IF(L97="","NULL","'"&L97&"'")&","&IF(M97="","NULL","'"&M97&"'")&");" -> INSERT INTO octadesk.stickets (ticket,Data_entrada,Data_resolucao,Titulo_ticket,Usuario_criador_ticket,Status,Grupo_responsavel,Responsavel_ticket,Tags_ticket,Total_de_interacoes) values('193235','2025-05-02 12:20:29','2025-05-02 12:20:56','Sua conta do WhatsApp Business está violando a política','Brenda','Resolvido','Suporte','Brenda','violação_preventiva_sem_sucesso','2');
B99: 193237 | C99: =IFERROR(VLOOKUP(Relatorio_[[#This Row],[ticket]],Base!A:A,1,0),"-") -> 193237 | D99: 45779.522 | F99: =IF(Relatorio_[[#This Row],[Data_resolução]]=0,"",Relatorio_[[#This Row],[Data_resolução]]) | G99: Tela de disparo em massa indisponível - o206721-2cb | H99: Larissa Araújo - LC Sistemas | I99: Pendente | J99: N2 | K99: Lucas Muniz | L99: chat, ticket-corrigido | M99: 7 | O99: ="INSERT INTO octadesk.stickets ("&$B$1&","&$D$1&","&$F$1&","&$G$1&","&$H$1&","&$I$1&","&$J$1&","&$K$1&","&$L$1&","&$M$1&") values("&IF(B98="","NULL","'"&B98&"'")&",'"&TEXT(D98,"aaaa-mm-dd hh:mm:ss")&"',"&IF(E98="","NULL","'"&TEXT(E98,"aaaa-mm-dd hh:mm:ss")&"'")&","&IF(G98="","NULL","'"&G98&"'")&","&IF(H98="","NULL","'"&H98&"'")&","&IF(I98="","NULL","'"&I98&"'")&","&IF(J98="","NULL","'"&J98&"'")&","&IF(K98="","NULL","'"&K98&"'")&","&IF(L98="","NULL","'"&L98&"'")&","&IF(M98="","NULL","'"&M98&"'")&");" -> INSERT INTO octadesk.stickets (ticket,Data_entrada,Data_resolucao,Titulo_ticket,Usuario_criador_ticket,Status,Grupo_responsavel,Responsavel_ticket,Tags_ticket,Total_de_interacoes) values('193236','2025-05-02 12:24:21','2025-05-02 12:24:46','Sua conta do WhatsApp Business está violando a política','Brenda','Resolvido','Suporte','Brenda','violação_preventiva_sem_sucesso','2');
B100: 193238 | C100: =IFERROR(VLOOKUP(Relatorio_[[#This Row],[ticket]],Base!A:A,1,0),"-") -> 193238 | D100: 45779.524 | E100: 45779.544 | F100: =IF(Relatorio_[[#This Row],[Data_resolução]]=0,"",Relatorio_[[#This Row],[Data_resolução]]) -> 45779.544 | G100: Sua conta do WhatsApp Business está violando a política | H100: Facebook | I100: Resolvido | J100: Suporte | K100: Suporte | L100: - | M100: 2 | O100: ="INSERT INTO octadesk.stickets ("&$B$1&","&$D$1&","&$F$1&","&$G$1&","&$H$1&","&$I$1&","&$J$1&","&$K$1&","&$L$1&","&$M$1&") values("&IF(B99="","NULL","'"&B99&"'")&",'"&TEXT(D99,"aaaa-mm-dd hh:mm:ss")&"',"&IF(E99="","NULL","'"&TEXT(E99,"aaaa-mm-dd hh:mm:ss")&"'")&","&IF(G99="","NULL","'"&G99&"'")&","&IF(H99="","NULL","'"&H99&"'")&","&IF(I99="","NULL","'"&I99&"'")&","&IF(J99="","NULL","'"&J99&"'")&","&IF(K99="","NULL","'"&K99&"'")&","&IF(L99="","NULL","'"&L99&"'")&","&IF(M99="","NULL","'"&M99&"'")&");" -> INSERT INTO octadesk.stickets (ticket,Data_entrada,Data_resolucao,Titulo_ticket,Usuario_criador_ticket,Status,Grupo_responsavel,Responsavel_ticket,Tags_ticket,Total_de_interacoes) values('193237','2025-05-02 12:31:47',NULL,'Tela de disparo em massa indisponível - o206721-2cb','Larissa Araújo - LC Sistemas','Pendente','N2','Lucas Muniz','chat, ticket-corrigido','7');
B101: 193239 | C101: =IFERROR(VLOOKUP(Relatorio_[[#This Row],[ticket]],Base!A:A,1,0),"-") -> 193239 | D101: 45779.543 | E101: 45779.544 | F101: =IF(Relatorio_[[#This Row],[Data_resolução]]=0,"",Relatorio_[[#This Row],[Data_resolução]]) -> 45779.544 | G101: Sua conta do WhatsApp Business está violando a política | H101: Brenda | I101: Resolvido | J101: Suporte | K101: Brenda | L101: violação_preventiva_sem_sucesso | M101: 2 | O101: ="INSERT INTO octadesk.stickets ("&$B$1&","&$D$1&","&$F$1&","&$G$1&","&$H$1&","&$I$1&","&$J$1&","&$K$1&","&$L$1&","&$M$1&") values("&IF(B100="","NULL","'"&B100&"'")&",'"&TEXT(D100,"aaaa-mm-dd hh:mm:ss")&"',"&IF(E100="","NULL","'"&TEXT(E100,"aaaa-mm-dd hh:mm:ss")&"'")&","&IF(G100="","NULL","'"&G100&"'")&","&IF(H100="","NULL","'"&H100&"'")&","&IF(I100="","NULL","'"&I100&"'")&","&IF(J100="","NULL","'"&J100&"'")&","&IF(K100="","NULL","'"&K100&"'")&","&IF(L100="","NULL","'"&L100&"'")&","&IF(M100="","NULL","'"&M100&"'")&");" -> INSERT INTO octadesk.stickets (ticket,Data_entrada,Data_resolucao,Titulo_ticket,Usuario_criador_ticket,Status,Grupo_responsavel,Responsavel_ticket,Tags_ticket,Total_de_interacoes) values('193238','2025-05-02 12:34:00','2025-05-02 13:04:03','Sua conta do WhatsApp Business está violando a política','Facebook','Resolvido','Suporte','Suporte','-','2');
B102: 193240 | C102: =IFERROR(VLOOKUP(Relatorio_[[#This Row],[ticket]],Base!A:A,1,0),"-") -> 193240 | D102: 45779.547 | F102: =IF(Relatorio_[[#This Row],[Data_resolução]]=0,"",Relatorio_[[#This Row],[Data_resolução]]) | G102: PROD - Octa-Conversas - Erro ao Exportar Relatórios de Campanhas de Disparo em Massa antigas - Vários ambientes | H102: Juan C. | I102: Novo | J102: PROD - Octa-Conversas | L102: 193132 | M102: 2 | O102: ="INSERT INTO octadesk.stickets ("&$B$1&","&$D$1&","&$F$1&","&$G$1&","&$H$1&","&$I$1&","&$J$1&","&$K$1&","&$L$1&","&$M$1&") values("&IF(B101="","NULL","'"&B101&"'")&",'"&TEXT(D101,"aaaa-mm-dd hh:mm:ss")&"',"&IF(E101="","NULL","'"&TEXT(E101,"aaaa-mm-dd hh:mm:ss")&"'")&","&IF(G101="","NULL","'"&G101&"'")&","&IF(H101="","NULL","'"&H101&"'")&","&IF(I101="","NULL","'"&I101&"'")&","&IF(J101="","NULL","'"&J101&"'")&","&IF(K101="","NULL","'"&K101&"'")&","&IF(L101="","NULL","'"&L101&"'")&","&IF(M101="","NULL","'"&M101&"'")&");" -> INSERT INTO octadesk.stickets (ticket,Data_entrada,Data_resolucao,Titulo_ticket,Usuario_criador_ticket,Status,Grupo_responsavel,Responsavel_ticket,Tags_ticket,Total_de_interacoes) values('193239','2025-05-02 13:02:09','2025-05-02 13:02:42','Sua conta do WhatsApp Business está violando a política','Brenda','Resolvido','Suporte','Brenda','violação_preventiva_sem_sucesso','2');
B103: 193241 | C103: =IFERROR(VLOOKUP(Relatorio_[[#This Row],[ticket]],Base!A:A,1,0),"-") -> 193241 | D103: 45779.551 | F103: =IF(Relatorio_[[#This Row],[Data_resolução]]=0,"",Relatorio_[[#This Row],[Data_resolução]]) | G103: Solicitação de Backup de Conversas e Informações de Clientes | H103: Júlio César Barboza Ramalho | I103: Em andamento | J103: Suporte | K103: Brenda | L103: automacao-24horas | M103: 3 | O103: ="INSERT INTO octadesk.stickets ("&$B$1&","&$D$1&","&$F$1&","&$G$1&","&$H$1&","&$I$1&","&$J$1&","&$K$1&","&$L$1&","&$M$1&") values("&IF(B102="","NULL","'"&B102&"'")&",'"&TEXT(D102,"aaaa-mm-dd hh:mm:ss")&"',"&IF(E102="","NULL","'"&TEXT(E102,"aaaa-mm-dd hh:mm:ss")&"'")&","&IF(G102="","NULL","'"&G102&"'")&","&IF(H102="","NULL","'"&H102&"'")&","&IF(I102="","NULL","'"&I102&"'")&","&IF(J102="","NULL","'"&J102&"'")&","&IF(K102="","NULL","'"&K102&"'")&","&IF(L102="","NULL","'"&L102&"'")&","&IF(M102="","NULL","'"&M102&"'")&");" -> INSERT INTO octadesk.stickets (ticket,Data_entrada,Data_resolucao,Titulo_ticket,Usuario_criador_ticket,Status,Grupo_responsavel,Responsavel_ticket,Tags_ticket,Total_de_interacoes) values('193240','2025-05-02 13:08:10',NULL,'PROD - Octa-Conversas - Erro ao Exportar Relatórios de Campanhas de Disparo em Massa antigas - Vários ambientes','Juan C.','Novo','PROD - Octa-Conversas',NULL,'193132','2');
B104: 193242 | C104: =IFERROR(VLOOKUP(Relatorio_[[#This Row],[ticket]],Base!A:A,1,0),"-") -> 193242 | D104: 45779.554 | E104: 45779.554 | F104: =IF(Relatorio_[[#This Row],[Data_resolução]]=0,"",Relatorio_[[#This Row],[Data_resolução]]) -> 45779.554 | G104: ATENÇÃO - GOLPE FALSO ADVOGADO - AAA | H104: Escritório Arantes Arimura Advocacia | I104: Cancelado | J104: Suporte | K104: Brenda | L104: - | M104: 2 | O104: ="INSERT INTO octadesk.stickets ("&$B$1&","&$D$1&","&$F$1&","&$G$1&","&$H$1&","&$I$1&","&$J$1&","&$K$1&","&$L$1&","&$M$1&") values("&IF(B103="","NULL","'"&B103&"'")&",'"&TEXT(D103,"aaaa-mm-dd hh:mm:ss")&"',"&IF(E103="","NULL","'"&TEXT(E103,"aaaa-mm-dd hh:mm:ss")&"'")&","&IF(G103="","NULL","'"&G103&"'")&","&IF(H103="","NULL","'"&H103&"'")&","&IF(I103="","NULL","'"&I103&"'")&","&IF(J103="","NULL","'"&J103&"'")&","&IF(K103="","NULL","'"&K103&"'")&","&IF(L103="","NULL","'"&L103&"'")&","&IF(M103="","NULL","'"&M103&"'")&");" -> INSERT INTO octadesk.stickets (ticket,Data_entrada,Data_resolucao,Titulo_ticket,Usuario_criador_ticket,Status,Grupo_responsavel,Responsavel_ticket,Tags_ticket,Total_de_interacoes) values('193241','2025-05-02 13:13:09',NULL,'Solicitação de Backup de Conversas e Informações de Clientes','Júlio César Barboza Ramalho','Em andamento','Suporte','Brenda','automacao-24horas','3');
B105: 193243 | C105: =IFERROR(VLOOKUP(Relatorio_[[#This Row],[ticket]],Base!A:A,1,0),"-") -> 193243 | D105: 45779.574 | E105: 45779.611 | F105: =IF(Relatorio_[[#This Row],[Data_resolução]]=0,"",Relatorio_[[#This Row],[Data_resolução]]) -> 45779.611 | G105: I need to post on your Site I'm regular in Guest Posting marketing | H105: tamia aiza | I105: Cancelado | J105: Suporte | K105: Brenda | L105: - | M105: 2 | O105: ="INSERT INTO octadesk.stickets ("&$B$1&","&$D$1&","&$F$1&","&$G$1&","&$H$1&","&$I$1&","&$J$1&","&$K$1&","&$L$1&","&$M$1&") values("&IF(B104="","NULL","'"&B104&"'")&",'"&TEXT(D104,"aaaa-mm-dd hh:mm:ss")&"',"&IF(E104="","NULL","'"&TEXT(E104,"aaaa-mm-dd hh:mm:ss")&"'")&","&IF(G104="","NULL","'"&G104&"'")&","&IF(H104="","NULL","'"&H104&"'")&","&IF(I104="","NULL","'"&I104&"'")&","&IF(J104="","NULL","'"&J104&"'")&","&IF(K104="","NULL","'"&K104&"'")&","&IF(L104="","NULL","'"&L104&"'")&","&IF(M104="","NULL","'"&M104&"'")&");" -> INSERT INTO octadesk.stickets (ticket,Data_entrada,Data_resolucao,Titulo_ticket,Usuario_criador_ticket,Status,Grupo_responsavel,Responsavel_ticket,Tags_ticket,Total_de_interacoes) values('193242','2025-05-02 13:17:24','2025-05-02 13:17:58','ATENÇÃO - GOLPE FALSO ADVOGADO - AAA','Escritório Arantes Arimura Advocacia','Cancelado','Suporte','Brenda','-','2');
B106: 193244 | C106: =IFERROR(VLOOKUP(Relatorio_[[#This Row],[ticket]],Base!A:A,1,0),"-") -> 193244 | D106: 45779.581 | E106: 45779.616 | F106: =IF(Relatorio_[[#This Row],[Data_resolução]]=0,"",Relatorio_[[#This Row],[Data_resolução]]) -> 45779.616 | G106: BOLETO PAGO | H106: Aline Pereira | I106: Resolvido | J106: Financeiro | L106: - | M106: 3 | O106: ="INSERT INTO octadesk.stickets ("&$B$1&","&$D$1&","&$F$1&","&$G$1&","&$H$1&","&$I$1&","&$J$1&","&$K$1&","&$L$1&","&$M$1&") values("&IF(B105="","NULL","'"&B105&"'")&",'"&TEXT(D105,"aaaa-mm-dd hh:mm:ss")&"',"&IF(E105="","NULL","'"&TEXT(E105,"aaaa-mm-dd hh:mm:ss")&"'")&","&IF(G105="","NULL","'"&G105&"'")&","&IF(H105="","NULL","'"&H105&"'")&","&IF(I105="","NULL","'"&I105&"'")&","&IF(J105="","NULL","'"&J105&"'")&","&IF(K105="","NULL","'"&K105&"'")&","&IF(L105="","NULL","'"&L105&"'")&","&IF(M105="","NULL","'"&M105&"'")&");" -> INSERT INTO octadesk.stickets (ticket,Data_entrada,Data_resolucao,Titulo_ticket,Usuario_criador_ticket,Status,Grupo_responsavel,Responsavel_ticket,Tags_ticket,Total_de_interacoes) values('193243','2025-05-02 13:46:55','2025-05-02 14:39:19','I need to post on your Site I'm regular in Guest Posting marketing','tamia aiza','Cancelado','Suporte','Brenda','-','2');
B107: 193245 | C107: =IFERROR(VLOOKUP(Relatorio_[[#This Row],[ticket]],Base!A:A,1,0),"-") -> 193245 | D107: 45779.611 | E107: 45779.616 | F107: =IF(Relatorio_[[#This Row],[Data_resolução]]=0,"",Relatorio_[[#This Row],[Data_resolução]]) -> 45779.616 | G107: Neymar Jr. Retorna às Mesas: O Impacto de Sua Paixão pelo Poker no Crescimento do Jogo no Brasil | H107: Poker de Botequim | I107: Cancelado | J107: Financeiro | L107: - | M107: 4 | O107: ="INSERT INTO octadesk.stickets ("&$B$1&","&$D$1&","&$F$1&","&$G$1&","&$H$1&","&$I$1&","&$J$1&","&$K$1&","&$L$1&","&$M$1&") values("&IF(B106="","NULL","'"&B106&"'")&",'"&TEXT(D106,"aaaa-mm-dd hh:mm:ss")&"',"&IF(E106="","NULL","'"&TEXT(E106,"aaaa-mm-dd hh:mm:ss")&"'")&","&IF(G106="","NULL","'"&G106&"'")&","&IF(H106="","NULL","'"&H106&"'")&","&IF(I106="","NULL","'"&I106&"'")&","&IF(J106="","NULL","'"&J106&"'")&","&IF(K106="","NULL","'"&K106&"'")&","&IF(L106="","NULL","'"&L106&"'")&","&IF(M106="","NULL","'"&M106&"'")&");" -> INSERT INTO octadesk.stickets (ticket,Data_entrada,Data_resolucao,Titulo_ticket,Usuario_criador_ticket,Status,Grupo_responsavel,Responsavel_ticket,Tags_ticket,Total_de_interacoes) values('193244','2025-05-02 13:57:11','2025-05-02 14:47:12','BOLETO PAGO','Aline Pereira','Resolvido','Financeiro',NULL,'-','3');
...
